Workbook

Sheet Parameters
A1: Parameter | B1: FY 24/25 Value | C1: Notes | D1: Sources | E1: Source notes
A2: EmploymentRate_WorkingAge | B2: 0.781 | C2: fraction of 15–64 employed | D2: https://infoshare.stats.govt.nz/ViewTable.aspx?pxID=a16e84d4-00a9-41d6-8a4a-8bf771bd2d2d | E2: Labour Force Status for people aged 15 to 64 years (Annual-Mar) | Employment rate | 2025
A3: EmploymentRate_65Plus | B3: 0.249 | C3: fraction of 65+ employed | D3: https://infoshare.stats.govt.nz/SelectVariables.aspx?pxID=a3faf5f4-e39a-4dbb-be8e-f81723992bcb | E3: Table: Labour Force Status by Sex by Age Group (Annual-Mar) | Total Both Sexes | Aged 65 years and over | Employment rate | 2025
A4: NZS_Annual single | B4: =519.47*52 -> 27012.44 | C4: net annual NZS per person | D4: https://www.workandincome.govt.nz/map/deskfile/nz-superannuation-and-veterans-pension-tables/new-zealand-superannuation-and-veterans-pension-ra.html
A5: NZS_annual couple | B5: =399.59*52 -> 20778.68 | C5: net annual NZS per person (half couple's rate) | D5: https://www.workandincome.govt.nz/map/deskfile/nz-superannuation-and-veterans-pension-tables/new-zealand-superannuation-and-veterans-pension-ra.html
A6: Average inflation | B6: 0.026 | C6: average 2005-2025 | D6: https://www.stats.govt.nz/news/annual-inflation-at-2-7-percent-in-june-2025/
A7: Average real wage growth | B7: 0.03688 | C7: average 1999-2023 | D7: https://www.stats.govt.nz/news/income-growth-for-wage-and-salary-earners-remains-strong/
A8: Multiplier | B8: =(B7-B6) + 1 -> 1.01088 | C8: Real wage growth - inflation + 1
A9: Ratio 65+ pop partnered | B9: 0.58 | D9: https://explore.data.stats.govt.nz/vis?tm=relationship&pg=0&snb=14&df%5bds%5d=ds-nsiws-disseminate&df%5bid%5d=CEN23_POP_008&df%5bag%5d=STATSNZ&df%5bvs%5d=1.0&dq=2013%2B2018%2B2023.9999%2B99999%2B999999.99...99&to%5bTIME%5d=false
A10: Ratio 65+ pop single | B10: 0.42 | D10: https://explore.data.stats.govt.nz/vis?tm=relationship&pg=0&snb=14&df%5bds%5d=ds-nsiws-disseminate&df%5bid%5d=CEN23_POP_008&df%5bag%5d=STATSNZ&df%5bvs%5d=1.0&dq=2013%2B2018%2B2023.9999%2B99999%2B999999.99...99&to%5bTIME%5d=false
A11: Income from wealth | B11: 0.05
A14: Parameters by Income Decile | B14: Base year total income | C14: Revenue share BAU | D14: Revenue share progressive | E14: Share of employed 65+ population | F14: Weights for share of employed 65+ population
A15: 1 | B15: =798.1*1000000 -> 798100000 | C15: ='Revenue share calc'!E2 -> 0.0036096394 | D15: ='Revenue share calc'!H2 -> 0 | E15: =F15/55 -> 0.18181818 | F15: 10
A16: 2 | B16: =3618.3*1000000 -> 3618300000 | C16: ='Revenue share calc'!E3 -> 0.014401036 | D16: ='Revenue share calc'!H3 -> 0.0034800777 | E16: =F16/55 -> 0.16363636 | F16: 9
A17: 3 | B17: =7546.1*1000000 -> 7546100000 | C17: ='Revenue share calc'!E4 -> 0.031399077 | D17: ='Revenue share calc'!H4 -> 0.010886748 | E17: =F17/55 -> 0.14545455 | F17: 8
A18: 4 | B18: =11905.5*1000000 -> 11905500000 | C18: ='Revenue share calc'!E5 -> 0.051692243 | D18: ='Revenue share calc'!H5 -> 0.022901399 | E18: =F18/55 -> 0.12727273 | F18: 7
A19: 5 | B19: =15606.1*1000000 -> 15606100000 | C19: ='Revenue share calc'!E6 -> 0.070583126 | D19: ='Revenue share calc'!H6 -> 0.037524833 | E19: =F19/55 -> 0.10909091 | F19: 6
A20: 6 | B20: =18610.5*1000000 -> 18610500000 | C20: ='Revenue share calc'!E7 -> 0.090905111 | D20: ='Revenue share calc'!H7 -> 0.053698687 | E20: =F20/55 -> 0.090909091 | F20: 5
A21: 7 | B21: =21785.7*1000000 -> 21785700000 | C21: ='Revenue share calc'!E8 -> 0.11035602 | D21: ='Revenue share calc'!H8 -> 0.083813868 | E21: =F21/55 -> 0.072727273 | F21: 4
A22: 8 | B22: =25966.5*1000000 -> 25966500000 | C22: ='Revenue share calc'!E9 -> 0.13623162 | D22: ='Revenue share calc'!H9 -> 0.13736006 | E22: =F22/55 -> 0.054545455 | F22: 3
A23: 9 | B23: =32317.2*1000000 -> 32317200000 | C23: ='Revenue share calc'!E10 -> 0.17539672 | D23: ='Revenue share calc'!H10 -> 0.21757858 | E23: =F23/55 -> 0.036363636 | F23: 2
A24: 10 | B24: =56243*1000000 -> 56243000000 | C24: ='Revenue share calc'!E11 -> 0.3154254 | D24: ='Revenue share calc'!H11 -> 0.43275574 | E24: =F24/55 -> 0.018181818 | F24: 1
A25: Source: https://www.ird.govt.nz/about-us/tax-statistics/revenue-refunds/wage-salary-distributions/wage-and-salary-statistics-datasets
A28: Wealth base year: FY 23/24
A29: Parameters by Wealth Quintile | B29: Total Wealth | C29: Value of owner-occupied dwelings | D29: Adjusted for negative values+ housing value | E29: Income from wealth | F29: Weighting of 65+ population | G29: Share of 65+ population
A30: 1 | B30: -3546560000 | C30: 11832606000 | D30: 0 | E30: 0 | F30: 1 | G30: =F30/15 -> 0.066666667
A31: 2 | B31: 59384533000 | C31: 39772526000 | D31: =B31-C31 -> 19612007000 | E31: =D31*$B$11 -> 980600350 | F31: 2 | G31: =F31/15 -> 0.13333333
A32: 3 | B32: 213316981000 | C32: 182423471000 | D32: =B32-C32 -> 30893510000 | E32: =D32*$B$11 -> 1544675500 | F32: 3 | G32: =F32/15 -> 0.2
A33: 4 | B33: 426978284000 | C33: 296903566000 | D33: =B33-C33 -> 130074718000 | E33: =D33*$B$11 -> 6503735900 | F33: 4 | G33: =F33/15 -> 0.26666667
A34: 5 | B34: 1371364554000 | C34: 395607963000 | D34: =B34-C34 -> 975756591000 | E34: =D34*$B$11 -> 48787829550 | F34: 5 | G34: =F34/15 -> 0.33333333
A36: Population projections
A37: Year | B37: 65+ | C37: 15-64 | D37: 65+ scaling factor from 2025 | E37: working age scaling factor from base year
A38: 2025 | B38: 902100 | C38: 3465800 | D38: 1 | E38: 1
A39: 2026 | B39: 932200 | C39: 3493500 | D39: =B39/B38 -> 1.0333666 | E39: =C39/$C$38 -> 1.0079924
A40: 2040 | B40: 1287900 | C40: 3911000 | D40: =B40/B38 -> 1.4276688 | E40: =C40/$C$38 -> 1.1284552
A41: 2060 | B41: 1776600 | C41: 4303300 | D41: =B41/B38 -> 1.9694047 | E41: =C41/$C$38 -> 1.241647
A42: 2078 | B42: 2239600 | C42: 4564400 | D42: =B42/B38 -> 2.4826516 | E42: =C42/C38 -> 1.3169831
A43: https://explore.data.stats.govt.nz/vis?fs[0]=Society%2C1%7CPopulation%20projections%23CAT_POPULATION_PROJECTIONS%23%7CNational%20population%20projections%23CAT_NATIONAL_POPULATION_PROJECTIONS%23&pg=0&fc=Society&bp=true&snb=9&df[ds]=ds-nsiws-disseminate&df[id]=POPPR_NAT_007&df[ag]=STATSNZ&df[vs]=1.0&dq=.2025%2B2040%2B2060%2B2078.SEX3.AGE6500%2BAGE4064%2BAGE1539%2BTOTALALLAGES&ly[rw]=YEAR_POPPR_NAT_007&ly[cl]=SCENARIO_POPPR_NAT_007&to[TIME]=false
A44: Based on Median projections
A46: Dependency ratios
A47: 2026 | B47: =C39/B39 -> 3.7475864
A48: 2040 | B48: =C40/B40 -> 3.0367265
A49: 2078 | B49: =C42/B42 -> 2.0380425

Sheet Wealth Models
A1: Quintile | B1: Year | E1: NZS income per recipient | P1: Baseline tax | S1: Progressive tax | V1: Gross income | X1: Net Income baseline tax | Z1: Net income Progressive tax | AB1: Utility score baseline tax | AD1: Utility score progressive tax | AF1: Welfare score baesline tax post-NZS income isoelastic utility | AJ1: Welfare score progressive tax post-NZS income isoelastic utility | AN1: Welfare score baesline tax post-NZS income log utility | AR1: Welfare score progressive tax post-NZS income log utility
B2: Year | C2: Years since base NZS | D2: Years since base wealth | E2: Base year annual rate singles | F2: Base year annual rate couples | G2: Mulitplier | H2: Current year real rate singles | I2: Current year annual rate couples | J2: Total 65+ population | K2: Single | L2: In a relationship | M2: NZS paid singles rate | N2: NZS paid couples rate | O2: NZS paid total to 65+ | P2: Revenue share | Q2: Required tax rate | R2: Decile NZS cost | S2: Revenue share | T2: Required tax rate | U2: Decile NZS cost | V2: Wealth income | W2: Pension income | X2: Total income post NZS | Y2: pre-NZS | Z2: Total income post-NZS | AA2: pre-NZS | AB2: Isoelastic p = 1.26 | AC2: Isoelsatic p = 1 | AD2: Isoelastic p = 1.26 | AE2: Isoelsatic p = 1 | AF2: Utilitarian | AG2: Adjusted score | AH2: Prioritarian | AI2: Maximin | AJ2: Utilitarian | AK2: Adjusted score | AL2: Prioritarian | AM2: Maximin | AN2: Utilitarian | AO2: Adjusted score | AP2: Prioritarian | AQ2: Maximin | AR2: Utilitarian | AS2: Adjusted score | AT2: Prioritarian | AU2: Maximin
A3: Overall | B3: 2026 | C3: 2 | D3: 3 | E3: =Parameters!$B$4 -> 27012.44 | F3: =Parameters!$B$5 -> 20778.68 | G3: =Parameters!$B$8 -> 1.01088 | H3: =E3*POWER(G3,C3) -> 27603.428 | I3: =F3*POWER(G3,C3) -> 21233.284 | J3: =Parameters!B39 -> 932200 | K3: =J3*Parameters!$B$10 -> 391524 | L3: =J3*Parameters!$B$9 -> 540676 | M3: =K3*H3 -> 1.0807405e+10 | N3: =L3*I3 -> 1.1480327e+10 | O3: =N3+M3 -> 2.2287732e+10 | R3: =SUM(R4:R8) -> 2.1575807e+10 | U3: =SUM(U4:U13) -> 2.1575807e+10 | V3: =SUM(V4:V8) -> 5.972459e+10 | W3: =SUM(W4:W8) -> 2.2287732e+10 | X3: =V3+W3-R3 -> 6.0436514e+10 | Y3: =V3-R3 -> 3.8148782e+10 | Z3: =V3+W3-U3 -> 6.0436514e+10 | AA3: =V3-U3 -> 3.8148782e+10 | AC3: Sensitivity check | AE3: Sensitivity check | AF3: =SUM(AB4:AB8) -> 19.1748 | AH3: =SUM(AG4:AG8) -> 9.7915261 | AI3: =MIN(AB5:AB8) -> 3.8336413 | AJ3: =SUM(AD4:AD8) -> 19.175203 | AL3: =SUM(AK4:AK8) -> 9.7916291 | AM3: =MIN(AD5:AD8) -> 3.8338069 | AN3: =SUM(AC4:AC8) -> 49.094742 | AP3: =SUM(AO4:AO8) -> 15.663051 | AQ3: =MIN(AC5:AC8) -> 9.5680079 | AR3: =SUM(AE4:AE8) -> 49.151587 | AT3: =SUM(AS4:AS8) -> 15.672206 | AU3: =MIN(AE5:AE8) -> 9.5902539
A4: 1 | P4: ='Revenue share calc'!E18 -> 0 | Q4: 0 | R4: =$O$3*P4 -> 0 | S4: ='Revenue share calc'!H18 -> 0 | T4: 0 | U4: =$O$3*S4 -> 0 | V4: =Parameters!E30*POWER(Parameters!$B$8, $D$3) -> 0 | W4: =$O$3*Parameters!G30 -> 1.4858488e+09 | X4: =V4+W4-R4 -> 1.4858488e+09 | Y4: =V4-R4 -> 0 | Z4: =V4+W4-U4 -> 1.4858488e+09 | AA4: =V4-U4 -> 0 | AB4: =(POWER(X4, -0.26) - 1)/-0.26 -> 3.8302935 | AC4: =LOG(X4) -> 9.1719746 | AD4: =(POWER(Z4, -0.26) - 1)/-0.26 -> 3.8302935 | AE4: =LOG(Z4) -> 9.1719746 | AG4: {=SQRT(AB4:AB8)} -> 1.9571136 | AK4: {=SQRT(AD4:AD8)} -> 1.9571136 | AO4: =SQRT(AC4) -> 3.0285268 | AS4: =SQRT(AE4) -> 3.0285268
A5: 2 | P5: ='Revenue share calc'!E19 -> 0.013269739 | Q5: =(P5*$O$3)/(Parameters!E31*POWER(Parameters!$B$8, $D$3)) -> 0.29196943 | R5: =Q5*Parameters!E31 -> 2.8630533e+08 | S5: ='Revenue share calc'!H19 -> 0.0042606706 | T5: =(S5*$O$3)/(Parameters!E31*POWER(Parameters!$B$8,$D$3)) -> 0.09374605 | U5: =T5*Parameters!E31 -> 91927409 | V5: =Parameters!E31*POWER(Parameters!$B$8, $D$3) -> 1.0129566e+09 | W5: =$O$3*Parameters!G31 -> 2.9716975e+09 | X5: =V5+W5-R5 -> 3.6983489e+09 | Y5: =V5-R5 -> 7.2665131e+08 | Z5: =V5+W5-U5 -> 3.8927268e+09 | AA5: =V5-U5 -> 9.2102923e+08 | AB5: =(POWER(X5, -0.26) - 1)/-0.26 -> 3.8336413 | AC5: =LOG(X5) -> 9.5680079 | AD5: =(POWER(Z5, -0.26) - 1)/-0.26 -> 3.8338069 | AE5: =LOG(Z5) -> 9.5902539 | AG5: 1.9579687 | AK5: 1.9580109 | AO5: =SQRT(AC5) -> 3.0932197 | AS5: =SQRT(AE5) -> 3.0968135
A6: 3 | P6: ='Revenue share calc'!E20 -> 0.023126668 | Q6: =(P6*$O$3)/(Parameters!E32*POWER(Parameters!$B$8, $D$3)) -> 0.32303001 | R6: =Q6*Parameters!E32 -> 4.9897654e+08 | S6: ='Revenue share calc'!H20 -> 0.01054673 | T6: =(S6*$O$3)/(Parameters!E32*POWER(Parameters!$B$8,$D$3)) -> 0.14731522 | U6: =T6*Parameters!E32 -> 2.2755421e+08 | V6: =Parameters!E32*POWER(Parameters!$B$8, $D$3) -> 1.5956442e+09 | W6: =$O$3*Parameters!G32 -> 4.4575463e+09 | X6: =V6+W6-R6 -> 5.554214e+09 | Y6: =V6-R6 -> 1.0966677e+09 | Z6: =V6+W6-U6 -> 5.8256363e+09 | AA6: =V6-U6 -> 1.36809e+09 | AB6: =(POWER(X6, -0.26) - 1)/-0.26 -> 3.8348968 | AC6: =LOG(X6) -> 9.7446226 | AD6: =(POWER(Z6, -0.26) - 1)/-0.26 -> 3.8350356 | AE6: =LOG(Z6) -> 9.7653434 | AG6: 1.9582893 | AK6: 1.9583247 | AO6: =SQRT(AC6) -> 3.1216378 | AS6: =SQRT(AE6) -> 3.1249549
A7: 4 | P7: ='Revenue share calc'!E21 -> 0.10673583 | Q7: =(P7*$O$3)/(Parameters!E33*POWER(Parameters!$B$8, $D$3)) -> 0.35409059 | R7: =Q7*Parameters!E33 -> 2.3029117e+09 | S7: ='Revenue share calc'!H21 -> 0.076701592 | T7: =(S7*$O$3)/(Parameters!E33*POWER(Parameters!$B$8,$D$3)) -> 0.25445356 | U7: =T7*Parameters!E33 -> 1.6548988e+09 | V7: =Parameters!E33*POWER(Parameters!$B$8, $D$3) -> 6.7183358e+09 | W7: =$O$3*Parameters!G33 -> 5.9433951e+09 | X7: =V7+W7-R7 -> 1.0358819e+10 | Y7: =V7-R7 -> 4.4154242e+09 | Z7: =V7+W7-U7 -> 1.1006832e+10 | AA7: =V7-U7 -> 5.0634371e+09 | AB7: =(POWER(X7, -0.26) - 1)/-0.26 -> 3.8365809 | AC7: =LOG(X7) -> 10.01531 | AD7: =(POWER(Z7, -0.26) - 1)/-0.26 -> 3.8367307 | AE7: =LOG(Z7) -> 10.041662 | AG7: 1.9587192 | AK7: 1.9587574 | AO7: =SQRT(AC7) -> 3.1646975 | AS7: =SQRT(AE7) -> 3.1688582
A8: 5 | P8: ='Revenue share calc'!E22 -> 0.85686776 | Q8: =(P8*$O$3)/(Parameters!E34*POWER(Parameters!$B$8, $D$3)) -> 0.37893905 | R8: =Q8*Parameters!E34 -> 1.8487614e+10 | S8: ='Revenue share calc'!H22 -> 0.90849101 | T8: =(S8*$O$3)/(Parameters!E34*POWER(Parameters!$B$8,$D$3)) -> 0.40176878 | U8: =T8*Parameters!E34 -> 1.9601427e+10 | V8: =Parameters!E34*POWER(Parameters!$B$8, $D$3) -> 5.0397653e+10 | W8: =$O$3*Parameters!G34 -> 7.4292439e+09 | X8: =V8+W8-R8 -> 3.9339283e+10 | Y8: =V8-R8 -> 3.1910039e+10 | Z8: =V8+W8-U8 -> 3.822547e+10 | AA8: =V8-U8 -> 3.0796226e+10 | AB8: =(POWER(X8, -0.26) - 1)/-0.26 -> 3.8393872 | AC8: =LOG(X8) -> 10.594826 | AD8: =(POWER(Z8, -0.26) - 1)/-0.26 -> 3.8393365 | AE8: =LOG(Z8) -> 10.582353 | AG8: 1.9594354 | AK8: 1.9594225 | AO8: =SQRT(AC8) -> 3.2549695 | AS8: =SQRT(AE8) -> 3.2530528
A12: Simple means test - top 2 quintiles no NZS
A13: Quintile | B13: Year | E13: NZS income per recipient | P13: Baseline tax | S13: Progressive tax | V13: Gross income | X13: Net Income baseline tax | Z13: Net income Progressive tax | AB13: Utility score baseline tax | AD13: Utility score progressive tax | AF13: Welfare score baesline tax post-NZS income isoelastic utility | AJ13: Welfare score progressive tax post-NZS income isoelastic utility | AN13: Welfare score baesline tax post-NZS income log utility | AR13: Welfare score progressive tax post-NZS income log utility
B14: Year | C14: Years since base NZS | D14: Years since base wealth | E14: Base year annual rate singles | F14: Base year annual rate couples | G14: Mulitplier | H14: Current year real rate singles | I14: Current year annual rate couples | J14: Total 65+ population | K14: Single | L14: In a relationship | M14: NZS paid singles rate | N14: NZS paid couples rate | O14: NZS paid total to 65+ | P14: Revenue share | Q14: Required tax rate | R14: Decile NZS cost | S14: Revenue share | T14: Required tax rate | U14: Decile NZS cost | V14: Wealth income | W14: Pension income after means test | X14: Total income post-NZS | Y14: pre-NZS | Z14: Total income post-NZSs | AA14: pre-NZS | AB14: Isoelastic p = 1.26 | AC14: Isoelsatic p = 1 | AD14: Isoelastic p = 1.26 | AE14: Isoelsatic p = 1 | AF14: Utilitarian | AG14: Adjusted score | AH14: Prioritarian | AI14: Maximin | AJ14: Utilitarian | AK14: Adjusted score | AL14: Prioritarian | AM14: Maximin | AN14: Utilitarian | AO14: Adjusted score | AP14: Prioritarian | AQ14: Maximin | AR14: Utilitarian | AS14: Adjusted score | AT14: Prioritarian | AU14: Maximin
A15: Overall | B15: 2026 | C15: 2 | D15: 3 | E15: =Parameters!$B$4 -> 27012.44 | F15: =Parameters!$B$5 -> 20778.68 | G15: =Parameters!$B$8 -> 1.01088 | H15: =E15*POWER(G15,C15) -> 27603.428 | I15: =F15*POWER(G15,C15) -> 21233.284 | J15: =Parameters!B39 -> 932200 | K15: =J15*Parameters!$B$10 -> 391524 | L15: =J15*Parameters!$B$9 -> 540676 | M15: =K15*H15 -> 1.0807405e+10 | N15: =L15*I15 -> 1.1480327e+10 | O15: =N15+M15 -> 2.2287732e+10 | R15: =SUM(R16:R20) -> 8.9150926e+09 | U15: =SUM(U16:U25) -> 8.9150926e+09 | V15: =SUM(V16:V20) -> 5.972459e+10 | W15: =SUM(W16:W18) -> 8.9150926e+09 | X15: =V15+W15-R15 -> 5.972459e+10 | Y15: =V15-R15 -> 5.0809497e+10 | Z15: =V15+W15-U15 -> 5.972459e+10 | AA15: =V15-U15 -> 5.0809497e+10 | AC15: Sensitivity check | AE15: Sensitivity check | AF15: =SUM(AB16:AB25) -> 19.173663 | AH15: =SUM(AG16:AG20) -> 9.7912359 | AI15: =MIN(AB17:AB25) -> 3.833785 | AJ15: =SUM(AD16:AD20) -> 19.173896 | AL15: =SUM(AK16:AK20) -> 9.7912954 | AM15: =MIN(AD17:AD25) -> 3.833851 | AN15: =SUM(AC16:AC20) -> 48.918167 | AP15: =SUM(AO16:AO20) -> 15.634847 | AQ15: =MIN(AC17:AC20) -> 9.5873015 | AR15: =SUM(AE16:AE20) -> 48.950358 | AT15: =SUM(AS16:AS20) -> 15.640041 | AU15: =MIN(AE17:AE21) -> 9.5962308
A16: 1 | O16: =Parameters!G30*$O$15 -> 1.4858488e+09 | P16: ='Revenue share calc'!E18 -> 0 | Q16: 0 | R16: =P16*SUM($O$16:$O$18) -> 0 | S16: ='Revenue share calc'!H18 -> 0 | T16: 0 | U16: =S16*SUM($O$16:$O$18) -> 0 | V16: =Parameters!E30*POWER(Parameters!$B$8, $D$15) -> 0 | W16: =O16 -> 1.4858488e+09 | X16: =V16+W16-R16 -> 1.4858488e+09 | Y16: =V16-R16 -> 0 | Z16: =V16+W16-U16 -> 1.4858488e+09 | AA16: =V16-U16 -> 0 | AB16: =(POWER(X16, -0.26) - 1)/-0.26 -> 3.8302935 | AC16: =LOG(X16) -> 9.1719746 | AD16: =(POWER(Z16, -0.26) - 1)/-0.26 -> 3.8302935 | AE16: =LOG(Z16) -> 9.1719746 | AG16: =SQRT(AB16) -> 1.9571136 | AK16: =SQRT(AD16) -> 1.9571136 | AO16: =SQRT(AC16) -> 3.0285268 | AS16: =SQRT(AE16) -> 3.0285268
A17: 2 | O17: =Parameters!G31*$O$15 -> 2.9716975e+09 | P17: ='Revenue share calc'!E19 -> 0.013269739 | Q17: =(P17*$O$22)/(Parameters!E31*POWER(Parameters!$B$8,$D$15)) -> 0.11678777 | R17: =P17*SUM($O$16:$O$18) -> 1.1830095e+08 | S17: ='Revenue share calc'!H19 -> 0.0042606706 | T17: =(S17*$O$22)/(Parameters!E31*POWER(Parameters!$B$8,$D$15)) -> 0.03749842 | U17: =S17*SUM($O$16:$O$18) -> 37984273 | V17: =Parameters!E31*POWER(Parameters!$B$8, $D$15) -> 1.0129566e+09 | W17: =O17 -> 2.9716975e+09 | X17: =V17+W17-R17 -> 3.8663532e+09 | Y17: =V17-R17 -> 8.9465569e+08 | Z17: =V17+W17-U17 -> 3.9466699e+09 | AA17: =V17-U17 -> 9.7497237e+08 | AB17: =(POWER(X17, -0.26) - 1)/-0.26 -> 3.833785 | AC17: =LOG(X17) -> 9.5873015 | AD17: =(POWER(Z17, -0.26) - 1)/-0.26 -> 3.833851 | AE17: =LOG(Z17) -> 9.5962308 | AG17: =SQRT(AB17) -> 1.9580054 | AK17: =SQRT(AD17) -> 1.9580222 | AO17: =SQRT(AC17) -> 3.0963368 | AS17: =SQRT(AE17) -> 3.0977784
A18: 3 | O18: =Parameters!G32*$O$15 -> 4.4575463e+09 | P18: ='Revenue share calc'!E20 -> 0.023126668 | Q18: =(P18*$O$22)/(Parameters!E32*POWER(Parameters!$B$8,$D$15)) -> 0.129212 | R18: =P18*SUM($O$16:$O$18) -> 2.0617639e+08 | S18: ='Revenue share calc'!H20 -> 0.01054673 | T18: =(S18*$O$22)/(Parameters!E32*POWER(Parameters!$B$8,$D$15)) -> 0.058926088 | U18: =S18*SUM($O$16:$O$18) -> 94025074 | V18: =Parameters!E32*POWER(Parameters!$B$8, $D$15) -> 1.5956442e+09 | W18: =O18 -> 4.4575463e+09 | X18: =V18+W18-R18 -> 5.8470142e+09 | Y18: =V18-R18 -> 1.3894679e+09 | Z18: =V18+W18-U18 -> 5.9591655e+09 | AA18: =V18-U18 -> 1.5016192e+09 | AB18: =(POWER(X18, -0.26) - 1)/-0.26 -> 3.8350462 | AC18: =LOG(X18) -> 9.7669341 | AD18: =(POWER(Z18, -0.26) - 1)/-0.26 -> 3.8351009 | AE18: =LOG(Z18) -> 9.7751854 | AG18: =SQRT(AB18) -> 1.9583274 | AK18: =SQRT(AD18) -> 1.9583414 | AO18: =SQRT(AC18) -> 3.1252095 | AS18: =SQRT(AE18) -> 3.1265293
A19: 4 | O19: =Parameters!G33*$O$15 -> 5.9433951e+09 | P19: ='Revenue share calc'!E21 -> 0.10673583 | Q19: =(P19*$O$22)/(Parameters!E33*POWER(Parameters!$B$8,$D$15)) -> 0.14163624 | R19: =P19*SUM($O$16:$O$18) -> 9.515598e+08 | S19: ='Revenue share calc'!H21 -> 0.076701592 | T19: =(S19*$O$22)/(Parameters!E33*POWER(Parameters!$B$8,$D$15)) -> 0.10178143 | U19: =S19*SUM($O$16:$O$18) -> 6.838018e+08 | V19: =Parameters!E33*POWER(Parameters!$B$8, $D$15) -> 6.7183358e+09 | W19: 0 | X19: =V19+W19-R19 -> 5.766776e+09 | Y19: =V19-R19 -> 5.766776e+09 | Z19: =V19+W19-U19 -> 6.034534e+09 | AA19: =V19-U19 -> 6.034534e+09 | AB19: =(POWER(X19, -0.26) - 1)/-0.26 -> 3.8350062 | AC19: =LOG(X19) -> 9.7609331 | AD19: =(POWER(Z19, -0.26) - 1)/-0.26 -> 3.8351369 | AE19: =LOG(Z19) -> 9.7806437 | AG19: =SQRT(AB19) -> 1.9583172 | AK19: =SQRT(AD19) -> 1.9583506 | AO19: =SQRT(AC19) -> 3.1242492 | AS19: =SQRT(AE19) -> 3.1274021
A20: 5 | O20: =Parameters!G34*$O$15 -> 7.4292439e+09 | P20: ='Revenue share calc'!E22 -> 0.85686776 | Q20: =(P20*$O$22)/(Parameters!E34*POWER(Parameters!$B$8,$D$15)) -> 0.15157562 | R20: =P20*SUM($O$16:$O$18) -> 7.6390555e+09 | S20: ='Revenue share calc'!H22 -> 0.90849101 | T20: =(S20*$O$22)/(Parameters!E34*POWER(Parameters!$B$8,$D$15)) -> 0.16070751 | U20: =S20*SUM($O$16:$O$18) -> 8.0992815e+09 | V20: =Parameters!E34*POWER(Parameters!$B$8, $D$15) -> 5.0397653e+10 | W20: 0 | X20: =V20+W20-R20 -> 4.2758597e+10 | Y20: =V20-R20 -> 4.2758597e+10 | Z20: =V20+W20-U20 -> 4.2298371e+10 | AA20: =V20-U20 -> 4.2298371e+10 | AB20: =(POWER(X20, -0.26) - 1)/-0.26 -> 3.8395323 | AC20: =LOG(X20) -> 10.631023 | AD20: =(POWER(Z20, -0.26) - 1)/-0.26 -> 3.8395136 | AE20: =LOG(Z20) -> 10.626324 | AG20: =SQRT(AB20) -> 1.9594725 | AK20: =SQRT(AD20) -> 1.9594677 | AO20: =SQRT(AC20) -> 3.260525 | AS20: =SQRT(AE20) -> 3.2598042
N22: NZS paid after means testing: | O22: =SUM(O16:O18) -> 8.9150926e+09

Sheet Income means-test 5 deciles
A1: Decile | B1: Year | D1: NZS income per recipient | V1: Baseline Tax | Y1: Progressive Tax | AB1: Size tax paying group by income group | AD1: Gross income | AF1: Net Income Baseline | AG1: Net income Progressive | AH1: Quintile size | AI1: Average income pp baseline | AK1: Average income pp progressive | AM1: Utility score baseline | AP1: Utility score progressive | AS1: Social welfare function basline tax isoelastic utility | AW1: SWF baseline tax log utility | BA1: SWF progressive tax isoelastic utility | BE1: SWF progressive tax log utility
B2: Year | C2: Years since base | D2: Base year annual rate singles | E2: Base year annual rate couples | F2: Mulitplier | G2: Current year real rate singles | H2: Current year annual rate couples | I2: 65+ employed population current year | J2: Single | K2: In a relationship | L2: NZS paid singles rate | M2: NZS paid couples rate | N2: NZS paid total to employed 65+ | O2: Total 65+ population | P2: Single | Q2: In a relationship | R2: NZS paid singles rate | S2: NZS paid couples rate | T2: NZS paid total to 65+ | U2: NZS paid total after means test | V2: Revenue share | W2: Implied average tax rate | X2: Decile NZS cost | Y2: Revenue share | Z2: Implied average tax rate | AA2: Decile NZS cost | AB2: Employed working age pop current year | AC2: Total tax paying population | AD2: Employment income | AE2: Pension income | AF2: Total income | AG2: Total income | AM2: Isoelastic p=1.26 | AN2: Isoelastic normalised | AO2: Isoelsatic p = 1 | AP2: Isoelastic p=1.26 | AQ2: Isoelastic normalised | AR2: Isoelsatic p = 1 | AS2: Utilitarian | AT2: Adjusted score | AU2: Prioritarian | AV2: Maximin | AW2: Utilitarian | AX2: Adjusted score | AY2: Prioritarian | AZ2: Maximin | BA2: Utilitarian | BB2: Adjusted score | BC2: Prioritarian | BD2: Maximin | BE2: Utilitarian | BF2: Adjusted score | BG2: Prioritarian | BH2: Maximin
A3: Overall | B3: 2026 | C3: 2 | D3: =Parameters!$B$4 -> 27012.44 | E3: =Parameters!$B$5 -> 20778.68 | F3: =Parameters!$B$8 -> 1.01088 | G3: =D3*POWER(F3,C3) -> 27603.428 | H3: =E3*POWER(F3,C3) -> 21233.284 | I3: =Parameters!B3*Parameters!B39 -> 232117.8 | J3: =I3*Parameters!$B$10 -> 97489.476 | K3: =I3*Parameters!$B$9 -> 134628.32 | L3: =J3*G3 -> 2.6910438e+09 | M3: =K3*H3 -> 2.8586014e+09 | N3: =M3+L3 -> 5.5496452e+09 | O3: =Parameters!B39 -> 932200 | P3: =O3*Parameters!$B$10 -> 391524 | Q3: =O3*Parameters!$B$9 -> 540676 | R3: =P3*G3 -> 1.0807405e+10 | S3: =Q3*H3 -> 1.1480327e+10 | T3: =S3+R3 -> 2.2287732e+10 | U3: =T3-SUM(N9:N13) -> 2.0774192e+10 | AA3: =SUM(AA4:AA13) -> 2.0774192e+10 | AB3: =Parameters!C39*Parameters!B2 -> 2728423.5 | AC3: =AB3+I3 -> 2960541.3 | AD3: =SUM(AD4:AD13) -> 1.9865009e+11 | AE3: =N3 -> 5.5496452e+09 | AF3: =AD3+AE3-X3 -> 2.0419974e+11 | AG3: =AD3+AE3-AA3 -> 1.8342554e+11 | AI3: post NZS | AJ3: pre-NZS | AK3: post-NZS | AL3: pre-NZS | AS3: =SUM(AM4:AM13) -> 35.993957 | AT3: Prioriatian | AU3: =SUM(AT4:AT13) -> 18.97128 | AV3: =MIN(AM5:AM13) -> 3.5279445 | AW3: =SUM(AO4:AO13) -> 46.393417 | AX3: Prioriatian | AY3: =SUM(AX4:AX13) -> 21.51785 | AZ3: =MIN(AO5:AO13) -> 4.1627449 | BA3: =SUM(AP4:AP13) -> 36.012333 | BB3: Prioriatian | BC3: =SUM(BB4:BB13) -> 18.976165 | BD3: =MIN(AP5:AP13) -> 3.532164 | BE3: =SUM(AR4:AR13) -> 46.493775 | BF3: Prioriatian | BG3: =SUM(BF3:BF13) -> 21.542261 | BH3: =MIN(AR5:AR13) -> 4.1850424
A4: 1 | N4: =$N$3*Parameters!E15 -> 1.0090264e+09 | V4: =Parameters!C15 -> 0.0036096394 | W4: =(V4*$U$3)/(Parameters!B15*POWER(Parameters!$B$8,$C$3)) -> 0.091945703 | X4: =$U$3*V4 -> 74987341 | Y4: {=Parameters!D15:D24} -> 0 | Z4: =(Y4*$U$3)/(Parameters!B15*POWER(Parameters!$B$8, $C$3)) -> 0 | AA4: =$U$3*Y4 -> 0 | AD4: =Parameters!B15*POWER(Parameters!$B$8,$C$3) -> 8.1556113e+08 | AE4: =$AE$3*Parameters!E15 -> 1.0090264e+09 | AF4: =AD4+AE4-X4 -> 1.7496002e+09 | AG4: =AD4+AE4-AA4 -> 1.8245875e+09 | AH4: =($AB$3+$I$3)/10 -> 296054.13 | AI4: =AF4/AH4 -> 5909.7307 | AJ4: =(AF4-AE4)/AH4 -> 2501.481 | AK4: =AG4/AH4 -> 6163.02 | AL4: =(AG4-AE4)/AH4 -> 2754.7703 | AM4: =(POWER(AI4, -0.26) - 1)/-0.26 -> 3.4439752 | AN4: =(AM4-$AM$4)*100 -> 0 | AO4: =LOG(AI4) -> 3.7715677 | AP4: =(POWER(AK4, -0.26) - 1)/-0.26 -> 3.4483396 | AQ4: =(AP4-$AP$4)*100 -> 0 | AR4: =LOG(AK4) -> 3.7897936 | AT4: =SQRT(AM4) -> 1.855795 | AX4: =SQRT(AO4) -> 1.9420524 | BB4: {=SQRT(AP4:AP13)} -> 1.8569705 | BF4: =SQRT(AR4) -> 1.9467392
A5: 2 | N5: =$N$3*Parameters!E16 -> 9.0812375e+08 | V5: =Parameters!C16 -> 0.014401036 | W5: =(V5*$U$3)/(Parameters!B16*POWER(Parameters!$B$8,$C$3)) -> 0.080912218 | X5: =$U$3*V5 -> 2.991699e+08 | Y5: 0.0034800777 | Z5: =(Y5*$U$3)/(Parameters!B16*POWER(Parameters!$B$8, $C$3)) -> 0.019552816 | AA5: =$U$3*Y5 -> 72295803 | AD5: =Parameters!B16*POWER(Parameters!$B$8,$C$3) -> 3.6974625e+09 | AE5: =$AE$3*Parameters!E16 -> 9.0812375e+08 | AF5: =AD5+AE5-X5 -> 4.3064164e+09 | AG5: =AD5+AE5-AA5 -> 4.5332905e+09 | AH5: =($AB$3+$I$3)/10 -> 296054.13 | AI5: =AF5/AH5 -> 14546.044 | AJ5: =(AF5-AE5)/AH5 -> 11478.619 | AK5: =AG5/AH5 -> 15312.37 | AL5: =(AG5-AE5)/AH5 -> 12244.946 | AM5: =(POWER(AI5, -0.26) - 1)/-0.26 -> 3.5279445 | AN5: =(AM5-$AM$4)*100 -> 8.3969306 | AO5: =LOG(AI5) -> 4.1627449 | AP5: =(POWER(AK5, -0.26) - 1)/-0.26 -> 3.532164 | AQ5: =(AP5-$AP$4)*100 -> 8.3824378 | AR5: =LOG(AK5) -> 4.1850424 | AT5: =SQRT(AM5) -> 1.8782823 | AX5: =SQRT(AO5) -> 2.0402806 | BB5: 1.8794052 | BF5: =SQRT(AR5) -> 2.0457376
A6: 3 | N6: =$N$3*Parameters!E17 -> 8.0722111e+08 | V6: =Parameters!C17 -> 0.031399077 | W6: =(V6*$U$3)/(Parameters!B17*POWER(Parameters!$B$8,$C$3)) -> 0.084590046 | X6: =$U$3*V6 -> 6.5229046e+08 | Y6: 0.010886748 | Z6: =(Y6*$U$3)/(Parameters!B17*POWER(Parameters!$B$8, $C$3)) -> 0.029329224 | AA6: =$U$3*Y6 -> 2.261634e+08 | AD6: =Parameters!B17*POWER(Parameters!$B$8,$C$3) -> 7.7111964e+09 | AE6: =$AE$3*Parameters!E17 -> 8.0722111e+08 | AF6: =AD6+AE6-X6 -> 7.8661271e+09 | AG6: =AD6+AE6-AA6 -> 8.2922541e+09 | AH6: =($AB$3+$I$3)/10 -> 296054.13 | AI6: =AF6/AH6 -> 26569.895 | AJ6: =(AF6-AE6)/AH6 -> 23843.295 | AK6: =AG6/AH6 -> 28009.25 | AL6: =(AG6-AE6)/AH6 -> 25282.65 | AM6: =(POWER(AI6, -0.26) - 1)/-0.26 -> 3.5740809 | AN6: =(AM6-$AM$4)*100 -> 13.010578 | AO6: =LOG(AI6) -> 4.4243898 | AP6: =(POWER(AK6, -0.26) - 1)/-0.26 -> 3.5777874 | AQ6: =(AP6-$AP$4)*100 -> 12.944776 | AR6: =LOG(AK6) -> 4.4473015 | AT6: =SQRT(AM6) -> 1.890524 | AX6: =SQRT(AO6) -> 2.1034234 | BB6: 1.891504 | BF6: =SQRT(AR6) -> 2.1088626
A7: 4 | N7: =$N$3*Parameters!E18 -> 7.0631848e+08 | V7: =Parameters!C18 -> 0.051692243 | W7: =(V7*$U$3)/(Parameters!B18*POWER(Parameters!$B$8,$C$3)) -> 0.088267875 | X7: =$U$3*V7 -> 1.0738646e+09 | Y7: 0.022901399 | Z7: =(Y7*$U$3)/(Parameters!B18*POWER(Parameters!$B$8, $C$3)) -> 0.039105631 | AA7: =$U$3*Y7 -> 4.7575806e+08 | AD7: =Parameters!B18*POWER(Parameters!$B$8,$C$3) -> 1.2165973e+10 | AE7: =$AE$3*Parameters!E18 -> 7.0631848e+08 | AF7: =AD7+AE7-X7 -> 1.1798427e+10 | AG7: =AD7+AE7-AA7 -> 1.2396533e+10 | AH7: =($AB$3+$I$3)/10 -> 296054.13 | AI7: =AF7/AH7 -> 39852.262 | AJ7: =(AF7-AE7)/AH7 -> 37466.488 | AK7: =AG7/AH7 -> 41872.523 | AL7: =(AG7-AE7)/AH7 -> 39486.748 | AM7: =(POWER(AI7, -0.26) - 1)/-0.26 -> 3.6012989 | AN7: =(AM7-$AM$4)*100 -> 15.732374 | AO7: =LOG(AI7) -> 4.600453 | AP7: =(POWER(AK7, -0.26) - 1)/-0.26 -> 3.6044269 | AQ7: =(AP7-$AP$4)*100 -> 15.608728 | AR7: =LOG(AK7) -> 4.6219291 | AT7: =SQRT(AM7) -> 1.8977089 | AX7: =SQRT(AO7) -> 2.1448667 | BB7: 1.8985328 | BF7: =SQRT(AR7) -> 2.1498672
A8: 5 | N8: =$N$3*Parameters!E19 -> 6.0541584e+08 | V8: =Parameters!C19 -> 0.070583126 | W8: =(V8*$U$3)/(Parameters!B19*POWER(Parameters!$B$8,$C$3)) -> 0.091945703 | X8: =$U$3*V8 -> 1.4663074e+09 | Y8: 0.037524833 | Z8: =(Y8*$U$3)/(Parameters!B19*POWER(Parameters!$B$8, $C$3)) -> 0.048882039 | AA8: =$U$3*Y8 -> 7.7954809e+08 | AD8: =Parameters!B19*POWER(Parameters!$B$8,$C$3) -> 1.5947536e+10 | AE8: =$AE$3*Parameters!E19 -> 6.0541584e+08 | AF8: =AD8+AE8-X8 -> 1.5086645e+10 | AG8: =AD8+AE8-AA8 -> 1.5773404e+10 | AH8: =($AB$3+$I$3)/10 -> 296054.13 | AI8: =AF8/AH8 -> 50959.075 | AJ8: =(AF8-AE8)/AH8 -> 48914.125 | AK8: =AG8/AH8 -> 53278.783 | AL8: =(AG8-AE8)/AH8 -> 51233.834 | AM8: =(POWER(AI8, -0.26) - 1)/-0.26 -> 3.6164602 | AN8: =(AM8-$AM$4)*100 -> 17.2485 | AO8: =LOG(AI8) -> 4.7072215 | AP8: =(POWER(AK8, -0.26) - 1)/-0.26 -> 3.6191033 | AQ8: =(AP8-$AP$4)*100 -> 17.07637 | AR8: =LOG(AK8) -> 4.7265543 | AT8: =SQRT(AM8) -> 1.9016993 | AX8: =SQRT(AO8) -> 2.1696132 | BB8: 1.9023941 | BF8: =SQRT(AR8) -> 2.174064
A9: 6 | N9: =$N$3*Parameters!E20 -> 5.045132e+08 | V9: =Parameters!C20 -> 0.090905111 | W9: =(V9*$U$3)/(Parameters!B20*POWER(Parameters!$B$8,$C$3)) -> 0.099301359 | X9: =$U$3*V9 -> 1.8884802e+09 | Y9: 0.053698687 | Z9: =(Y9*$U$3)/(Parameters!B20*POWER(Parameters!$B$8, $C$3)) -> 0.058658447 | AA9: =$U$3*Y9 -> 1.1155468e+09 | AD9: =Parameters!B20*POWER(Parameters!$B$8,$C$3) -> 1.9017667e+10 | AF9: =AD9+AE9-X9 -> 1.7129187e+10 | AG9: =AD9+AE9-AA9 -> 1.7902121e+10 | AH9: =($AB$3+$I$3)/10 -> 296054.13 | AI9: =AF9/AH9 -> 57858.295 | AJ9: =(AF9-AE9)/AH9 -> 57858.295 | AK9: =AG9/AH9 -> 60469.079 | AL9: =(AG9-AE9)/AH9 -> 60469.079 | AM9: =(POWER(AI9, -0.26) - 1)/-0.26 -> 3.6239193 | AN9: =(AM9-$AM$4)*100 -> 17.994413 | AO9: =LOG(AI9) -> 4.7623656 | AP9: =(POWER(AK9, -0.26) - 1)/-0.26 -> 3.6264549 | AQ9: =(AP9-$AP$4)*100 -> 17.811529 | AR9: =LOG(AK9) -> 4.7815334 | AT9: =SQRT(AM9) -> 1.9036594 | AX9: =SQRT(AO9) -> 2.1822845 | BB9: 1.9043253 | BF9: =SQRT(AR9) -> 2.1866718
A10: 7 | N10: =$N$3*Parameters!E21 -> 4.0361056e+08 | V10: =Parameters!C21 -> 0.11035602 | W10: =(V10*$U$3)/(Parameters!B21*POWER(Parameters!$B$8,$C$3)) -> 0.10297919 | X10: =$U$3*V10 -> 2.2925572e+09 | Y10: 0.083813868 | Z10: =(Y10*$U$3)/(Parameters!B21*POWER(Parameters!$B$8, $C$3)) -> 0.078211263 | AA10: =$U$3*Y10 -> 1.7411654e+09 | AD10: =Parameters!B21*POWER(Parameters!$B$8,$C$3) -> 2.2262336e+10 | AF10: =AD10+AE10-X10 -> 1.9969778e+10 | AG10: =AD10+AE10-AA10 -> 2.052117e+10 | AH10: =($AB$3+$I$3)/10 -> 296054.13 | AI10: =AF10/AH10 -> 67453.133 | AJ10: =(AF10-AE10)/AH10 -> 67453.133 | AK10: =AG10/AH10 -> 69315.602 | AL10: =(AG10-AE10)/AH10 -> 69315.602 | AM10: =(POWER(AI10, -0.26) - 1)/-0.26 -> 3.6326105 | AN10: =(AM10-$AM$4)*100 -> 18.863531 | AO10: =LOG(AI10) -> 4.8290021 | AP10: =(POWER(AK10, -0.26) - 1)/-0.26 -> 3.6341174 | AQ10: =(AP10-$AP$4)*100 -> 18.577775 | AR10: =LOG(AK10) -> 4.840831 | AT10: =SQRT(AM10) -> 1.9059408 | AX10: =SQRT(AO10) -> 2.1974991 | BB10: 1.9063361 | BF10: =SQRT(AR10) -> 2.2001889
A11: 8 | N11: =$N$3*Parameters!E22 -> 3.0270792e+08 | V11: =Parameters!C22 -> 0.13623162 | W11: =(V11*$U$3)/(Parameters!B22*POWER(Parameters!$B$8,$C$3)) -> 0.10665702 | X11: =$U$3*V11 -> 2.8301017e+09 | Y11: 0.13736006 | Z11: =(Y11*$U$3)/(Parameters!B22*POWER(Parameters!$B$8, $C$3)) -> 0.10754049 | AA11: =$U$3*Y11 -> 2.8535443e+09 | AD11: =Parameters!B22*POWER(Parameters!$B$8,$C$3) -> 2.6534605e+10 | AF11: =AD11+AE11-X11 -> 2.3704503e+10 | AG11: =AD11+AE11-AA11 -> 2.3681061e+10 | AH11: =($AB$3+$I$3)/10 -> 296054.13 | AI11: =AF11/AH11 -> 80068.138 | AJ11: =(AF11-AE11)/AH11 -> 80068.138 | AK11: =AG11/AH11 -> 79988.955 | AL11: =(AG11-AE11)/AH11 -> 79988.955 | AM11: =(POWER(AI11, -0.26) - 1)/-0.26 -> 3.6419203 | AN11: =(AM11-$AM$4)*100 -> 19.794512 | AO11: =LOG(AI11) -> 4.9034597 | AP11: =(POWER(AK11, -0.26) - 1)/-0.26 -> 3.6418677 | AQ11: =(AP11-$AP$4)*100 -> 19.352812 | AR11: =LOG(AK11) -> 4.90303 | AT11: =SQRT(AM11) -> 1.9083816 | AX11: =SQRT(AO11) -> 2.2143757 | BB11: 1.9083678 | BF11: =SQRT(AR11) -> 2.2142787
A12: 9 | N12: =$N$3*Parameters!E23 -> 2.0180528e+08 | V12: =Parameters!C23 -> 0.17539672 | W12: =(V12*$U$3)/(Parameters!B23*POWER(Parameters!$B$8,$C$3)) -> 0.11033484 | X12: =$U$3*V12 -> 3.6437252e+09 | Y12: 0.21757858 | Z12: =(Y12*$U$3)/(Parameters!B23*POWER(Parameters!$B$8, $C$3)) -> 0.13686971 | AA12: =$U$3*Y12 -> 4.5200192e+09 | AD12: =Parameters!B23*POWER(Parameters!$B$8,$C$3) -> 3.3024248e+10 | AF12: =AD12+AE12-X12 -> 2.9380523e+10 | AG12: =AD12+AE12-AA12 -> 2.8504229e+10 | AH12: =($AB$3+$I$3)/10 -> 296054.13 | AI12: =AF12/AH12 -> 99240.374 | AJ12: =(AF12-AE12)/AH12 -> 99240.374 | AK12: =AG12/AH12 -> 96280.463 | AL12: =(AG12-AE12)/AH12 -> 96280.463 | AM12: =(POWER(AI12, -0.26) - 1)/-0.26 -> 3.653007 | AN12: =(AM12-$AM$4)*100 -> 20.903182 | AO12: =LOG(AI12) -> 4.9966884 | AP12: =(POWER(AK12, -0.26) - 1)/-0.26 -> 3.6514804 | AQ12: =(AP12-$AP$4)*100 -> 20.314079 | AR12: =LOG(AK12) -> 4.9835382 | AT12: =SQRT(AM12) -> 1.9112841 | AX12: =SQRT(AO12) -> 2.2353274 | BB12: 1.9108847 | BF12: =SQRT(AR12) -> 2.232384
A13: 10 | N13: =$N$3*Parameters!E24 -> 1.0090264e+08 | V13: =Parameters!C24 -> 0.3154254 | W13: =(V13*$U$3)/(Parameters!B24*POWER(Parameters!$B$8,$C$3)) -> 0.11401267 | X13: =$U$3*V13 -> 6.5527079e+09 | Y13: 0.43275574 | Z13: =(Y13*$U$3)/(Parameters!B24*POWER(Parameters!$B$8, $C$3)) -> 0.15642253 | AA13: =$U$3*Y13 -> 8.9901509e+09 | AD13: =Parameters!B24*POWER(Parameters!$B$8,$C$3) -> 5.7473505e+10 | AF13: =AD13+AE13-X13 -> 5.0920798e+10 | AG13: =AD13+AE13-AA13 -> 4.8483355e+10 | AH13: =($AB$3+$I$3)/10 -> 296054.13 | AI13: =AF13/AH13 -> 171998.27 | AJ13: =(AF13-AE13)/AH13 -> 171998.27 | AK13: =AG13/AH13 -> 163765.17 | AL13: =(AG13-AE13)/AH13 -> 163765.17 | AM13: =(POWER(AI13, -0.26) - 1)/-0.26 -> 3.6787404 | AN13: =(AM13-$AM$4)*100 -> 23.476522 | AO13: =LOG(AI13) -> 5.2355241 | AP13: =(POWER(AK13, -0.26) - 1)/-0.26 -> 3.6765916 | AQ13: =(AP13-$AP$4)*100 -> 22.825203 | AR13: =LOG(AK13) -> 5.2142215 | AT13: =SQRT(AM13) -> 1.9180043 | AX13: =SQRT(AO13) -> 2.2881268 | BB13: 1.917444 | BF13: =SQRT(AR13) -> 2.283467
A15: Decile | B15: Year | D15: NZS income per recipient | V15: Baseline Tax | Y15: Progressive Tax | AB15: Size tax paying group by income group | AD15: Gross income | AF15: Net Income Baseline | AG15: Net income Progressive | AH15: Quintile size | AI15: Average income pp baseline | AK15: Average income pp progressive | AM15: Utility score baseline | AP15: Utility score progressive | AS15: Social welfare function basline tax isoelastic utility | AW15: SWF baseline tax log utility | BA15: SWF progressive tax isoelastic utility | BE15: SWF progressive tax log utility
B16: Year | C16: Years since base | D16: Base year annual rate singles | E16: Base year annual rate couples | F16: Mulitplier | G16: Current year real rate singles | H16: Current year annual rate couples | I16: 65+ employed population current year | J16: Single | K16: In a relationship | L16: NZS paid singles rate | M16: NZS paid couples rate | N16: NZS paid total to employed 65+ | O16: Total 65+ population | P16: Single | Q16: In a relationship | R16: NZS paid singles rate | S16: NZS paid couples rate | T16: NZS paid total to 65+ | U16: NZS paid total after means test | V16: Revenue share | W16: Implied average tax rate | X16: Decile NZS cost | Y16: Revenue share | Z16: Implied average tax rate | AA16: Decile NZS cost | AB16: Employed working age pop current year | AC16: Total tax paying population | AD16: Employment income | AE16: Pension income | AF16: Total income | AG16: Total income | AM16: Isoelastic p=1.26 | AN16: Isoelastic normalised | AO16: Isoelsatic p = 1 | AP16: Isoelastic p=1.26 | AQ16: Isoelastic normalised | AR16: Isoelsatic p = 1 | AS16: Utilitarian | AT16: Adjusted score | AU16: Prioritarian | AV16: Maximin | AW16: Utilitarian | AX16: Adjusted score | AY16: Prioritarian | AZ16: Maximin | BA16: Utilitarian | BB16: Adjusted score | BC16: Prioritarian | BD16: Maximin | BE16: Utilitarian | BF16: Adjusted score | BG16: Prioritarian | BH16: Maximin
A17: Overall | B17: 2040 | C17: 16 | D17: =Parameters!$B$4 -> 27012.44 | E17: =Parameters!$B$5 -> 20778.68 | F17: =Parameters!$B$8 -> 1.01088 | G17: =D17*POWER(F17,C17) -> 32118.665 | H17: =E17*POWER(F17,C17) -> 24706.523 | I17: =Parameters!B3*Parameters!B40 -> 320687.1 | J17: =I17*Parameters!$B$10 -> 134688.58 | K17: =I17*Parameters!$B$9 -> 185998.52 | L17: =J17*G17 -> 4.3260174e+09 | M17: =K17*H17 -> 4.5953766e+09 | N17: =M17+L17 -> 8.921394e+09 | O17: =Parameters!B40 -> 1287900 | P17: =O17*Parameters!$B$10 -> 540918 | Q17: =O17*Parameters!$B$9 -> 746982 | R17: =P17*G17 -> 1.7373564e+10 | S17: =Q17*H17 -> 1.8455328e+10 | T17: =S17+R17 -> 3.5828892e+10 | U17: =T17-SUM(N23:N27) -> 3.3395784e+10 | AA17: =SUM(AA18:AA27) -> 3.3395784e+10 | AB17: =Parameters!C40*Parameters!B2 -> 3054491 | AC17: =AB17+I17 -> 3375178.1 | AD17: =SUM(AD18:AD27) -> 2.3114432e+11 | AE17: =N17 -> 8.921394e+09 | AF17: =AD17+AE17-X17 -> 2.4006571e+11 | AG17: =AD17+AE17-AA17 -> 2.0666993e+11 | AS17: =SUM(AN18:AN27) -> 161.75946 | AT17: Prioriatian | AU17: =SUM(AT18:AT27) -> 18.965071 | AV17: =MIN(AM19:AM27) -> 3.5248376 | AW17: =SUM(AO18:AO27) -> 46.2526 | AX17: Prioriatian | AY17: =SUM(AX18:AX27) -> 21.484384 | AZ17: =MIN(AO19:AO27) -> 4.1465154 | BA17: =SUM(AQ18:AQ27) -> 157.70466 | BB17: Prioriatian | BC17: =SUM(BB18:BB27) -> 18.972193 | BD17: =MIN(AP19:AP27) -> 3.5309841 | BE17: =SUM(AR18:AR27) -> 46.396815 | BF17: Prioriatian | BG17: =SUM(BF17:BF27) -> 21.519555 | BH17: =MIN(AR19:AR27) -> 4.1787776
A18: 1 | N18: =$N$17*Parameters!E15 -> 1.6220716e+09 | V18: {=Parameters!C15:C24} -> 0.0036096394 | W18: =(V18*$U$17)/(Parameters!B15*POWER(Parameters!$B$8, $C$17)) -> 0.12702947 | X18: =$U$17*V18 -> 1.2054674e+08 | Y18: =Parameters!D15 -> 0 | Z18: =(Y18*$U$17)/(Parameters!B15*POWER(Parameters!$B$8, $C$17)) -> 0 | AA18: =$U$17*Y18 -> 0 | AD18: =Parameters!B15*POWER(Parameters!$B$8, $C$17) -> 9.4896671e+08 | AE18: =$AE$3*Parameters!E15 -> 1.0090264e+09 | AF18: =AD18+AE18-X18 -> 1.8374464e+09 | AG18: =AD18+AE18-AA18 -> 1.9579931e+09 | AH18: =($AB$17+$I$17)/10 -> 337517.81 | AI18: =AF18/AH18 -> 5443.9983 | AK18: =AG18/AH18 -> 5801.1549 | AM18: =(POWER(AI18, -0.26) - 1)/-0.26 -> 3.4352994 | AN18: =(AM18-$AM$18)*100 -> 0 | AO18: =LOG(AI18) -> 3.735918 | AP18: =(POWER(AK18, -0.26) - 1)/-0.26 -> 3.4420315 | AQ18: =(AP18-$AP$18)*100 -> 0 | AR18: =LOG(AK18) -> 3.7635145 | AT18: {=SQRT(AM18:AM27)} -> 1.8534561 | AX18: =SQRT(AO18) -> 1.9328523 | BB18: {=SQRT(AP18:AP27)} -> 1.8552713 | BF18: =SQRT(AR18) -> 1.939978
A19: 2 | N19: =$N$17*Parameters!E16 -> 1.4598645e+09 | V19: 0.014401036 | W19: =(V19*$U$17)/(Parameters!B16*POWER(Parameters!$B$8, $C$17)) -> 0.11178593 | X19: =$U$17*V19 -> 4.809339e+08 | Y19: =Parameters!D16 -> 0.0034800777 | Z19: =(Y19*$U$17)/(Parameters!B16*POWER(Parameters!$B$8, $C$17)) -> 0.027013593 | AA19: =$U$17*Y19 -> 1.1621993e+08 | AD19: =Parameters!B16*POWER(Parameters!$B$8, $C$17) -> 4.3022757e+09 | AE19: =$AE$3*Parameters!E16 -> 9.0812375e+08 | AF19: =AD19+AE19-X19 -> 4.7294656e+09 | AG19: =AD19+AE19-AA19 -> 5.0941796e+09 | AH19: =($AB$17+$I$17)/10 -> 337517.81 | AI19: =AF19/AH19 -> 14012.492 | AK19: =AG19/AH19 -> 15093.069 | AM19: =(POWER(AI19, -0.26) - 1)/-0.26 -> 3.5248376 | AN19: =(AM19-$AM$18)*100 -> 8.953821 | AO19: =LOG(AI19) -> 4.1465154 | AP19: =(POWER(AK19, -0.26) - 1)/-0.26 -> 3.5309841 | AQ19: =(AP19-$AP$18)*100 -> 8.8952649 | AR19: =LOG(AK19) -> 4.1787776 | AT19: 1.8774551 | AX19: =SQRT(AO19) -> 2.0362994 | BB19: 1.8790913 | BF19: =SQRT(AR19) -> 2.0442058
A20: 3 | N20: =$N$17*Parameters!E17 -> 1.2976573e+09 | V20: 0.031399077 | W20: =(V20*$U$17)/(Parameters!B17*POWER(Parameters!$B$8, $C$17)) -> 0.11686711 | X20: =$U$17*V20 -> 1.0485968e+09 | Y20: =Parameters!D17 -> 0.010886748 | Z20: =(Y20*$U$17)/(Parameters!B17*POWER(Parameters!$B$8, $C$17)) -> 0.040520389 | AA20: =$U$17*Y20 -> 3.635715e+08 | AD20: =Parameters!B17*POWER(Parameters!$B$8, $C$17) -> 8.972557e+09 | AE20: =$AE$3*Parameters!E17 -> 8.0722111e+08 | AF20: =AD20+AE20-X20 -> 8.7311813e+09 | AG20: =AD20+AE20-AA20 -> 9.4162066e+09 | AH20: =($AB$17+$I$17)/10 -> 337517.81 | AI20: =AF20/AH20 -> 25868.802 | AK20: =AG20/AH20 -> 27898.399 | AM20: =(POWER(AI20, -0.26) - 1)/-0.26 -> 3.5721827 | AN20: =(AM20-$AM$18)*100 -> 13.68833 | AO20: =LOG(AI20) -> 4.4127763 | AP20: =(POWER(AK20, -0.26) - 1)/-0.26 -> 3.5775105 | AQ20: =(AP20-$AP$18)*100 -> 13.547905 | AR20: =LOG(AK20) -> 4.4455793 | AT20: 1.8900219 | AX20: =SQRT(AO20) -> 2.1006609 | BB20: 1.8914308 | BF20: =SQRT(AR20) -> 2.1084542
A21: 4 | N21: =$N$17*Parameters!E18 -> 1.1354501e+09 | V21: 0.051692243 | W21: =(V21*$U$17)/(Parameters!B18*POWER(Parameters!$B$8, $C$17)) -> 0.12194829 | X21: =$U$17*V21 -> 1.726303e+09 | Y21: =Parameters!D18 -> 0.022901399 | Z21: =(Y21*$U$17)/(Parameters!B18*POWER(Parameters!$B$8, $C$17)) -> 0.054027186 | AA21: =$U$17*Y21 -> 7.6481017e+08 | AD21: =Parameters!B18*POWER(Parameters!$B$8, $C$17) -> 1.4156025e+10 | AE21: =$AE$3*Parameters!E18 -> 7.0631848e+08 | AF21: =AD21+AE21-X21 -> 1.313604e+10 | AG21: =AD21+AE21-AA21 -> 1.4097533e+10 | AH21: =($AB$17+$I$17)/10 -> 337517.81 | AI21: =AF21/AH21 -> 38919.546 | AK21: =AG21/AH21 -> 41768.264 | AM21: =(POWER(AI21, -0.26) - 1)/-0.26 -> 3.5997866 | AN21: =(AM21-$AM$18)*100 -> 16.448715 | AO21: =LOG(AI21) -> 4.5901678 | AP21: =(POWER(AK21, -0.26) - 1)/-0.26 -> 3.6042702 | AQ21: =(AP21-$AP$18)*100 -> 16.223868 | AR21: =LOG(AK21) -> 4.6208464 | AT21: 1.8973104 | AX21: =SQRT(AO21) -> 2.1424677 | BB21: 1.8984915 | BF21: =SQRT(AR21) -> 2.1496154
A22: 5 | N22: =$N$17*Parameters!E19 -> 9.7324298e+08 | V22: 0.070583126 | W22: =(V22*$U$17)/(Parameters!B19*POWER(Parameters!$B$8, $C$17)) -> 0.12702947 | X22: =$U$17*V22 -> 2.3571788e+09 | Y22: =Parameters!D19 -> 0.037524833 | Z22: =(Y22*$U$17)/(Parameters!B19*POWER(Parameters!$B$8, $C$17)) -> 0.067533982 | AA22: =$U$17*Y22 -> 1.2531712e+09 | AD22: =Parameters!B19*POWER(Parameters!$B$8, $C$17) -> 1.8556158e+10 | AE22: =$AE$3*Parameters!E19 -> 6.0541584e+08 | AF22: =AD22+AE22-X22 -> 1.6804395e+10 | AG22: =AD22+AE22-AA22 -> 1.7908402e+10 | AH22: =($AB$17+$I$17)/10 -> 337517.81 | AI22: =AF22/AH22 -> 49788.172 | AK22: =AG22/AH22 -> 53059.133 | AM22: =(POWER(AI22, -0.26) - 1)/-0.26 -> 3.6150677 | AN22: =(AM22-$AM$18)*100 -> 17.976832 | AO22: =LOG(AI22) -> 4.6971262 | AP22: =(POWER(AK22, -0.26) - 1)/-0.26 -> 3.6188593 | AQ22: =(AP22-$AP$18)*100 -> 17.682782 | AR22: =LOG(AK22) -> 4.7247601 | AT22: 1.9013331 | AX22: =SQRT(AO22) -> 2.1672854 | BB22: 1.90233 | BF22: =SQRT(AR22) -> 2.1736513
A23: 6 | N23: =$N$17*Parameters!E20 -> 8.1103582e+08 | V23: 0.090905111 | W23: =(V23*$U$17)/(Parameters!B20*POWER(Parameters!$B$8, $C$17)) -> 0.13719183 | X23: =$U$17*V23 -> 3.0358475e+09 | Y23: =Parameters!D20 -> 0.053698687 | Z23: =(Y23*$U$17)/(Parameters!B20*POWER(Parameters!$B$8, $C$17)) -> 0.081040779 | AA23: =$U$17*Y23 -> 1.7933098e+09 | AD23: =Parameters!B20*POWER(Parameters!$B$8, $C$17) -> 2.2128486e+10 | AF23: =AD23+AE23-X23 -> 1.9092639e+10 | AG23: =AD23+AE23-AA23 -> 2.0335177e+10 | AH23: =($AB$17+$I$17)/10 -> 337517.81 | AI23: =AF23/AH23 -> 56567.797 | AK23: =AG23/AH23 -> 60249.196 | AM23: =(POWER(AI23, -0.26) - 1)/-0.26 -> 3.6226121 | AN23: =(AM23-$AM$18)*100 -> 18.731269 | AO23: =LOG(AI23) -> 4.7525693 | AP23: =(POWER(AK23, -0.26) - 1)/-0.26 -> 3.6262467 | AQ23: =(AP23-$AP$18)*100 -> 18.421523 | AR23: =LOG(AK23) -> 4.7799513 | AT23: 1.9033161 | AX23: =SQRT(AO23) -> 2.1800388 | BB23: 1.9042706 | BF23: =SQRT(AR23) -> 2.18631
A24: 7 | N24: =$N$17*Parameters!E21 -> 6.4882865e+08 | V24: 0.11035602 | W24: =(V24*$U$17)/(Parameters!B21*POWER(Parameters!$B$8, $C$17)) -> 0.142273 | X24: =$U$17*V24 -> 3.685426e+09 | Y24: =Parameters!D21 -> 0.083813868 | Z24: =(Y24*$U$17)/(Parameters!B21*POWER(Parameters!$B$8, $C$17)) -> 0.10805437 | AA24: =$U$17*Y24 -> 2.7990298e+09 | AD24: =Parameters!B21*POWER(Parameters!$B$8, $C$17) -> 2.5903902e+10 | AF24: =AD24+AE24-X24 -> 2.2218476e+10 | AG24: =AD24+AE24-AA24 -> 2.3104872e+10 | AH24: =($AB$17+$I$17)/10 -> 337517.81 | AI24: =AF24/AH24 -> 65829.047 | AK24: =AG24/AH24 -> 68455.268 | AM24: =(POWER(AI24, -0.26) - 1)/-0.26 -> 3.631253 | AN24: =(AM24-$AM$18)*100 -> 19.595361 | AO24: =LOG(AI24) -> 4.8184176 | AP24: =(POWER(AK24, -0.26) - 1)/-0.26 -> 3.6334277 | AQ24: =(AP24-$AP$18)*100 -> 19.139623 | AR24: =LOG(AK24) -> 4.8354069 | AT24: 1.9055847 | AX24: =SQRT(AO24) -> 2.1950894 | BB24: 1.9061552 | BF24: =SQRT(AR24) -> 2.1989559
A25: 8 | N25: =$N$17*Parameters!E22 -> 4.8662149e+08 | V25: 0.13623162 | W25: =(V25*$U$17)/(Parameters!B22*POWER(Parameters!$B$8, $C$17)) -> 0.14735418 | X25: =$U$17*V25 -> 4.5495616e+09 | Y25: =Parameters!D22 -> 0.13736006 | Z25: =(Y25*$U$17)/(Parameters!B22*POWER(Parameters!$B$8, $C$17)) -> 0.14857476 | AA25: =$U$17*Y25 -> 4.587247e+09 | AD25: =Parameters!B22*POWER(Parameters!$B$8, $C$17) -> 3.0875008e+10 | AF25: =AD25+AE25-X25 -> 2.6325447e+10 | AG25: =AD25+AE25-AA25 -> 2.6287761e+10 | AH25: =($AB$17+$I$17)/10 -> 337517.81 | AI25: =AF25/AH25 -> 77997.208 | AK25: =AG25/AH25 -> 77885.553 | AM25: =(POWER(AI25, -0.26) - 1)/-0.26 -> 3.640524 | AN25: =(AM25-$AM$18)*100 -> 20.522461 | AO25: =LOG(AI25) -> 4.8920791 | AP25: =(POWER(AK25, -0.26) - 1)/-0.26 -> 3.6404474 | AQ25: =(AP25-$AP$18)*100 -> 19.841595 | AR25: =LOG(AK25) -> 4.8914569 | AT25: 1.9080157 | AX25: =SQRT(AO25) -> 2.2118045 | BB25: 1.9079957 | BF25: =SQRT(AR25) -> 2.2116638
A26: 9 | N26: =$N$17*Parameters!E23 -> 3.2441433e+08 | V26: 0.17539672 | W26: =(V26*$U$17)/(Parameters!B23*POWER(Parameters!$B$8, $C$17)) -> 0.15243536 | X26: =$U$17*V26 -> 5.8575111e+09 | Y26: =Parameters!D23 -> 0.21757858 | Z26: =(Y26*$U$17)/(Parameters!B23*POWER(Parameters!$B$8, $C$17)) -> 0.18909515 | AA26: =$U$17*Y26 -> 7.2662073e+09 | AD26: =Parameters!B23*POWER(Parameters!$B$8, $C$17) -> 3.8426196e+10 | AF26: =AD26+AE26-X26 -> 3.2568685e+10 | AG26: =AD26+AE26-AA26 -> 3.1159989e+10 | AH26: =($AB$17+$I$17)/10 -> 337517.81 | AI26: =AF26/AH26 -> 96494.715 | AK26: =AG26/AH26 -> 92321.021 | AM26: =(POWER(AI26, -0.26) - 1)/-0.26 -> 3.6515929 | AN26: =(AM26-$AM$18)*100 -> 21.629346 | AO26: =LOG(AI26) -> 4.9845035 | AP26: =(POWER(AK26, -0.26) - 1)/-0.26 -> 3.6493432 | AQ26: =(AP26-$AP$18)*100 -> 20.731176 | AR26: =LOG(AK26) -> 4.9653006 | AT26: 1.9109141 | AX26: =SQRT(AO26) -> 2.2326002 | BB26: 1.9103254 | BF26: =SQRT(AR26) -> 2.2282954
A27: 10 | N27: =$N$17*Parameters!E24 -> 1.6220716e+08 | V27: 0.3154254 | W27: =(V27*$U$17)/(Parameters!B24*POWER(Parameters!$B$8, $C$17)) -> 0.15751654 | X27: =$U$17*V27 -> 1.0533879e+10 | Y27: =Parameters!D24 -> 0.43275574 | Z27: =(Y27*$U$17)/(Parameters!B24*POWER(Parameters!$B$8, $C$17)) -> 0.21610874 | AA27: =$U$17*Y27 -> 1.4452217e+10 | AD27: =Parameters!B24*POWER(Parameters!$B$8, $C$17) -> 6.6874746e+10 | AF27: =AD27+AE27-X27 -> 5.6340867e+10 | AG27: =AD27+AE27-AA27 -> 5.2422529e+10 | AH27: =($AB$17+$I$17)/10 -> 337517.81 | AI27: =AF27/AH27 -> 166927.09 | AK27: =AG27/AH27 -> 155317.81 | AM27: =(POWER(AI27, -0.26) - 1)/-0.26 -> 3.6774326 | AN27: =(AM27-$AM$18)*100 -> 24.213323 | AO27: =LOG(AI27) -> 5.2225268 | AP27: =(POWER(AK27, -0.26) - 1)/-0.26 -> 3.6742407 | AQ27: =(AP27-$AP$18)*100 -> 23.220921 | AR27: =LOG(AK27) -> 5.1912213 | AT27: 1.9176633 | AX27: =SQRT(AO27) -> 2.2852848 | BB27: 1.9168309 | BF27: =SQRT(AR27) -> 2.2784252
A29: Decile | B29: Year | D29: NZS income per recipient | V29: Baseline Tax | Y29: Progressive Tax | AB29: Size tax paying group by income group | AD29: Gross income | AF29: Net Income Baseline | AG29: Net income Progressive | AH29: Quintile size | AI29: Average income pp baseline | AK29: Average income pp progressive | AM29: Utility score baseline | AP29: Utility score progressive | AS29: Social welfare function basline tax isoelastic utility | AW29: SWF baseline tax log utility | BA29: SWF progressive tax isoelastic utility | BE29: SWF progressive tax log utility
B30: Year | C30: Years since base | D30: Base year annual rate singles | E30: Base year annual rate couples | F30: Mulitplier | G30: Current year real rate singles | H30: Current year annual rate couples | I30: 65+ employed population current year | J30: Single | K30: In a relationship | L30: NZS paid singles rate | M30: NZS paid couples rate | N30: NZS paid total to employed 65+ | O30: Total 65+ population | P30: Single | Q30: In a relationship | R30: NZS paid singles rate | S30: NZS paid couples rate | T30: NZS paid total to 65+ | U30: NZS paid total after means test | V30: Revenue share | W30: Implied average tax rate | X30: Decile NZS cost | Y30: Revenue share | Z30: Implied average tax rate | AA30: Decile NZS cost | AB30: Employed working age pop current year | AC30: Total tax paying population | AD30: Employment income | AE30: Pension income | AF30: Total income | AG30: Total income | AM30: Isoelastic p=1.26 | AN30: Isoelastic normalised | AO30: Isoelsatic p = 1 | AP30: Isoelastic p=1.26 | AQ30: Isoelastic normalised | AR30: Isoelsatic p = 1 | AS30: Utilitarian | AT30: Adjusted score | AU30: Prioritarian | AV30: Maximin | AW30: Utilitarian | AX30: Adjusted score | AY30: Prioritarian | AZ30: Maximin | BA30: Utilitarian | BB30: Adjusted score | BC30: Prioritarian | BD30: Maximin | BE30: Utilitarian | BF30: Adjusted score | BG30: Prioritarian | BH30: Maximin
A31: Overall | B31: 2078 | C31: 54 | D31: =Parameters!$B$4 -> 27012.44 | E31: =Parameters!$B$5 -> 20778.68 | F31: =Parameters!$B$8 -> 1.01088 | G31: =D31*POWER(F31,C31) -> 48455.429 | H31: =E31*POWER(F31,C31) -> 37273.192 | I31: =Parameters!$B$3*Parameters!B42 -> 557660.4 | J31: =I31*Parameters!$B$10 -> 234217.37 | K31: =I31*Parameters!$B$9 -> 323443.03 | L31: =J31*G31 -> 1.1349103e+10 | M31: =K31*H31 -> 1.2055754e+10 | N31: =M31+L31 -> 2.3404857e+10 | O31: =Parameters!B42 -> 2239600 | P31: =O31*Parameters!$B$10 -> 940632 | Q31: =O31*Parameters!$B$9 -> 1298968 | R31: =P31*G31 -> 4.5578727e+10 | S31: =Q31*H31 -> 4.8416683e+10 | T31: =S31+R31 -> 9.399541e+10 | U31: =T31-SUM(N37:N41) -> 8.7612268e+10 | AA31: =SUM(AA32:AA41) -> 8.7612268e+10 | AB31: =Parameters!C42*Parameters!B2 -> 3564796.4 | AC31: =AB31+I31 -> 4122456.8 | AD31: =SUM(AD32:AD41) -> 3.4871304e+11 | AE31: =N31 -> 2.3404857e+10 | AF31: =AD31+AE31-X31 -> 3.721179e+11 | AG31: =AD31+AE31-AA31 -> 2.8450563e+11 | AS31: =SUM(AN32:AN41) -> 179.87872 | AT31: Prioriatian | AU31: =SUM(AT32:AT41) -> 19.013252 | AV31: =MIN(AM33:AM41) -> 3.5603096 | AW31: =SUM(AO32:AO41) -> 47.27866 | AX31: Prioritarian | AY31: =SUM(AX32:AX41) -> 21.731569 | AZ31: =MIN(AO33:AO41) -> 4.3419123 | BA31: =SUM(AQ32:AQ41) -> 176.44567 | BB31: Prioriatian | BC31: =SUM(BB32:BB41) -> 19.021975 | BD31: =MIN(AP33:AP41) -> 3.5676754 | BE31: =SUM(AR32:AR41) -> 47.478881 | BF31: Prioriatian | BG31: =SUM(BF31:BF41) -> 21.779335 | BH31: =MIN(AR33:AR41) -> 4.3855193
A32: 1 | N32: =$N$31*Parameters!E15 -> 4.2554286e+09 | V32: =Parameters!C15 -> 0.0036096394 | W32: =(V32*$U$31)/(Parameters!B15*POWER(Parameters!$B$8,$C$31)) -> 0.22089852 | X32: =$U$31*V32 -> 3.1624869e+08 | Y32: =Parameters!D15 -> 0 | Z32: =(Y32*$U$31)/(Parameters!B15*POWER(Parameters!$B$8,$C$31)) -> 0 | AA32: =$U$31*Y32 -> 0 | AD32: =Parameters!B15*POWER(Parameters!$B$8,$C$31) -> 1.431647e+09 | AE32: =$AE$31*Parameters!E15 -> 4.2554286e+09 | AF32: =AD32+AE32-X32 -> 5.3708269e+09 | AG32: =AD32+AE32-AA32 -> 5.6870756e+09 | AH32: =($AB$31+$I$31)/10 -> 412245.68 | AI32: =AF32/AH32 -> 13028.219 | AK32: =AG32/AH32 -> 13795.355 | AM32: =(POWER(AI32, -0.26) - 1)/-0.26 -> 3.5186951 | AN32: =(AM32-$AM$18)*100 -> 8.3395727 | AO32: =LOG(AI32) -> 4.114885 | AP32: =(POWER(AK32, -0.26) - 1)/-0.26 -> 3.5235303 | AQ32: =(AP32-$AP$18)*100 -> 8.1498793 | AR32: =LOG(AK32) -> 4.1397329 | AT32: {=SQRT(AM32:AM41)} -> 1.8758185 | AX32: =SQRT(AO32) -> 2.0285179 | BB32: {=SQRT(AP32:AP41)} -> 1.8771069 | BF32: =SQRT(AR32) -> 2.0346334
A33: 2 | N33: =$N$31*Parameters!E16 -> 3.8298857e+09 | V33: =Parameters!C16 -> 0.014401036 | W33: =(V33*$U$31)/(Parameters!B16*POWER(Parameters!$B$8,$C$31)) -> 0.19439069 | X33: =$U$31*V33 -> 1.2617075e+09 | Y33: =Parameters!D16 -> 0.0034800777 | Z33: =(Y33*$U$31)/(Parameters!B16*POWER(Parameters!$B$8,$C$31)) -> 0.04697542 | AA33: =$U$31*Y33 -> 3.048975e+08 | AD33: =Parameters!B16*POWER(Parameters!$B$8,$C$31) -> 6.4905754e+09 | AE33: =$AE$31*Parameters!E16 -> 3.8298857e+09 | AF33: =AD33+AE33-X33 -> 9.0587537e+09 | AG33: =AD33+AE33-AA33 -> 1.0015564e+10 | AH33: =($AB$31+$I$31)/10 -> 412245.68 | AI33: =AF33/AH33 -> 21974.163 | AK33: =AG33/AH33 -> 24295.133 | AM33: =(POWER(AI33, -0.26) - 1)/-0.26 -> 3.5603096 | AN33: =(AM33-$AM$18)*100 -> 12.501019 | AO33: =LOG(AI33) -> 4.3419123 | AP33: =(POWER(AK33, -0.26) - 1)/-0.26 -> 3.5676754 | AQ33: =(AP33-$AP$18)*100 -> 12.564389 | AR33: =LOG(AK33) -> 4.3855193 | AT33: 1.8868783 | AX33: =SQRT(AO33) -> 2.0837256 | BB33: 1.8888291 | BF33: =SQRT(AR33) -> 2.0941631
A34: 3 | N34: =$N$31*Parameters!E17 -> 3.4043429e+09 | V34: =Parameters!C17 -> 0.031399077 | W34: =(V34*$U$31)/(Parameters!B17*POWER(Parameters!$B$8,$C$31)) -> 0.20322663 | X34: =$U$31*V34 -> 2.7509444e+09 | Y34: =Parameters!D17 -> 0.010886748 | Z34: =(Y34*$U$31)/(Parameters!B17*POWER(Parameters!$B$8,$C$31)) -> 0.070463129 | AA34: =$U$31*Y34 -> 9.5381272e+08 | AD34: =Parameters!B17*POWER(Parameters!$B$8,$C$31) -> 1.3536338e+10 | AE34: =$AE$31*Parameters!E17 -> 3.4043429e+09 | AF34: =AD34+AE34-X34 -> 1.4189736e+10 | AG34: =AD34+AE34-AA34 -> 1.5986868e+10 | AH34: =($AB$31+$I$31)/10 -> 412245.68 | AI34: =AF34/AH34 -> 34420.582 | AK34: =AG34/AH34 -> 38779.953 | AM34: =(POWER(AI34, -0.26) - 1)/-0.26 -> 3.5917909 | AN34: =(AM34-$AM$18)*100 -> 15.649145 | AO34: =LOG(AI34) -> 4.5368182 | AP34: =(POWER(AK34, -0.26) - 1)/-0.26 -> 3.5995563 | AQ34: =(AP34-$AP$18)*100 -> 15.752482 | AR34: =LOG(AK34) -> 4.5886073 | AT34: 1.8952021 | AX34: =SQRT(AO34) -> 2.1299808 | BB34: 1.8972497 | BF34: =SQRT(AR34) -> 2.1421035
A35: 4 | N35: =$N$31*Parameters!E18 -> 2.9788e+09 | V35: =Parameters!C18 -> 0.051692243 | W35: =(V35*$U$31)/(Parameters!B18*POWER(Parameters!$B$8,$C$31)) -> 0.21206257 | X35: =$U$31*V35 -> 4.5288746e+09 | Y35: =Parameters!D18 -> 0.022901399 | Z35: =(Y35*$U$31)/(Parameters!B18*POWER(Parameters!$B$8,$C$31)) -> 0.093950839 | AA35: =$U$31*Y35 -> 2.0064435e+09 | AD35: =Parameters!B18*POWER(Parameters!$B$8,$C$31) -> 2.1356313e+10 | AE35: =$AE$31*Parameters!E18 -> 2.9788e+09 | AF35: =AD35+AE35-X35 -> 1.9806238e+10 | AG35: =AD35+AE35-AA35 -> 2.2328669e+10 | AH35: =($AB$31+$I$31)/10 -> 412245.68 | AI35: =AF35/AH35 -> 48044.743 | AK35: =AG35/AH35 -> 54163.5 | AM35: =(POWER(AI35, -0.26) - 1)/-0.26 -> 3.6129162 | AN35: =(AM35-$AM$18)*100 -> 17.761675 | AO35: =LOG(AI35) -> 4.6816459 | AP35: =(POWER(AK35, -0.26) - 1)/-0.26 -> 3.6200735 | AQ35: =(AP35-$AP$18)*100 -> 17.804197 | AR35: =LOG(AK35) -> 4.7337067 | AT35: 1.9007673 | AX35: =SQRT(AO35) -> 2.1637111 | BB35: 1.9026491 | BF35: =SQRT(AR35) -> 2.1757083
A36: 5 | N36: =$N$31*Parameters!E19 -> 2.5532571e+09 | V36: =Parameters!C19 -> 0.070583126 | W36: =(V36*$U$31)/(Parameters!B19*POWER(Parameters!$B$8,$C$31)) -> 0.22089852 | X36: =$U$31*V36 -> 6.1839477e+09 | Y36: =Parameters!D19 -> 0.037524833 | Z36: =(Y36*$U$31)/(Parameters!B19*POWER(Parameters!$B$8,$C$31)) -> 0.11743855 | AA36: =$U$31*Y36 -> 3.2876357e+09 | AD36: =Parameters!B19*POWER(Parameters!$B$8,$C$31) -> 2.7994519e+10 | AE36: =$AE$31*Parameters!E19 -> 2.5532571e+09 | AF36: =AD36+AE36-X36 -> 2.4363829e+10 | AG36: =AD36+AE36-AA36 -> 2.7260141e+10 | AH36: =($AB$31+$I$31)/10 -> 412245.68 | AI36: =AF36/AH36 -> 59100.264 | AK36: =AG36/AH36 -> 66125.958 | AM36: =(POWER(AI36, -0.26) - 1)/-0.26 -> 3.6251431 | AN36: =(AM36-$AM$18)*100 -> 18.984368 | AO36: =LOG(AI36) -> 4.7715894 | AP36: =(POWER(AK36, -0.26) - 1)/-0.26 -> 3.6315043 | AQ36: =(AP36-$AP$18)*100 -> 18.947284 | AR36: =LOG(AK36) -> 4.820372 | AT36: 1.9039809 | AX36: =SQRT(AO36) -> 2.1843968 | BB36: 1.9056506 | BF36: =SQRT(AR36) -> 2.1955346
A37: 6 | N37: =$N$31*Parameters!E20 -> 2.1277143e+09 | V37: =Parameters!C20 -> 0.090905111 | W37: =(V37*$U$31)/(Parameters!B20*POWER(Parameters!$B$8,$C$31)) -> 0.2385704 | X37: =$U$31*V37 -> 7.9644029e+09 | Y37: =Parameters!D20 -> 0.053698687 | Z37: =(Y37*$U$31)/(Parameters!B20*POWER(Parameters!$B$8,$C$31)) -> 0.14092626 | AA37: =$U$31*Y37 -> 4.7046638e+09 | AD37: =Parameters!B20*POWER(Parameters!$B$8,$C$31) -> 3.3383869e+10 | AF37: =AD37+AE37-X37 -> 2.5419466e+10 | AG37: =AD37+AE37-AA37 -> 2.8679205e+10 | AH37: =($AB$31+$I$31)/10 -> 412245.68 | AI37: =AF37/AH37 -> 61660.965 | AK37: =AG37/AH37 -> 69568.237 | AM37: =(POWER(AI37, -0.26) - 1)/-0.26 -> 3.627567 | AN37: =(AM37-$AM$18)*100 -> 19.226761 | AO37: =LOG(AI37) -> 4.7900103 | AP37: =(POWER(AK37, -0.26) - 1)/-0.26 -> 3.6343178 | AQ37: =(AP37-$AP$18)*100 -> 19.228636 | AR37: =LOG(AK37) -> 4.842411 | AT37: 1.9046173 | AX37: =SQRT(AO37) -> 2.1886092 | BB37: 1.9063887 | BF37: =SQRT(AR37) -> 2.2005479
A38: 7 | N38: =$N$31*Parameters!E21 -> 1.7021714e+09 | V38: =Parameters!C21 -> 0.11035602 | W38: =(V38*$U$31)/(Parameters!B21*POWER(Parameters!$B$8,$C$31)) -> 0.24740634 | X38: =$U$31*V38 -> 9.6685415e+09 | Y38: =Parameters!D21 -> 0.083813868 | Z38: =(Y38*$U$31)/(Parameters!B21*POWER(Parameters!$B$8,$C$31)) -> 0.18790168 | AA38: =$U$31*Y38 -> 7.343123e+09 | AD38: =Parameters!B21*POWER(Parameters!$B$8,$C$31) -> 3.9079603e+10 | AF38: =AD38+AE38-X38 -> 2.9411062e+10 | AG38: =AD38+AE38-AA38 -> 3.173648e+10 | AH38: =($AB$31+$I$31)/10 -> 412245.68 | AI38: =AF38/AH38 -> 71343.53 | AK38: =AG38/AH38 -> 76984.385 | AM38: =(POWER(AI38, -0.26) - 1)/-0.26 -> 3.6357012 | AN38: =(AM38-$AM$18)*100 -> 20.040175 | AO38: =LOG(AI38) -> 4.8533546 | AP38: =(POWER(AK38, -0.26) - 1)/-0.26 -> 3.639824 | AQ38: =(AP38-$AP$18)*100 -> 19.779257 | AR38: =LOG(AK38) -> 4.8864026 | AT38: 1.9067515 | AX38: =SQRT(AO38) -> 2.203033 | BB38: 1.9078323 | BF38: =SQRT(AR38) -> 2.2105209
A39: 8 | N39: =$N$31*Parameters!E22 -> 1.2766286e+09 | V39: =Parameters!C22 -> 0.13623162 | W39: =(V39*$U$31)/(Parameters!B22*POWER(Parameters!$B$8,$C$31)) -> 0.25624228 | X39: =$U$31*V39 -> 1.1935561e+10 | Y39: =Parameters!D22 -> 0.13736006 | Z39: =(Y39*$U$31)/(Parameters!B22*POWER(Parameters!$B$8,$C$31)) -> 0.25836481 | AA39: =$U$31*Y39 -> 1.2034427e+10 | AD39: =Parameters!B22*POWER(Parameters!$B$8,$C$31) -> 4.6579202e+10 | AF39: =AD39+AE39-X39 -> 3.4643641e+10 | AG39: =AD39+AE39-AA39 -> 3.4544775e+10 | AH39: =($AB$31+$I$31)/10 -> 412245.68 | AI39: =AF39/AH39 -> 84036.396 | AK39: =AG39/AH39 -> 83796.574 | AM39: =(POWER(AI39, -0.26) - 1)/-0.26 -> 3.6444728 | AN39: =(AM39-$AM$18)*100 -> 20.917337 | AO39: =LOG(AI39) -> 4.9244674 | AP39: =(POWER(AK39, -0.26) - 1)/-0.26 -> 3.6443229 | AQ39: =(AP39-$AP$18)*100 -> 20.229139 | AR39: =LOG(AK39) -> 4.9232263 | AT39: 1.9090502 | AX39: =SQRT(AO39) -> 2.2191141 | BB39: 1.909011 | BF39: =SQRT(AR39) -> 2.2188344
A40: 9 | N40: =$N$31*Parameters!E23 -> 8.5108572e+08 | V40: =Parameters!C23 -> 0.17539672 | W40: =(V40*$U$31)/(Parameters!B23*POWER(Parameters!$B$8,$C$31)) -> 0.26507822 | X40: =$U$31*V40 -> 1.5366905e+10 | Y40: =Parameters!D23 -> 0.21757858 | Z40: =(Y40*$U$31)/(Parameters!B23*POWER(Parameters!$B$8,$C$31)) -> 0.32882794 | AA40: =$U$31*Y40 -> 1.9062553e+10 | AD40: =Parameters!B23*POWER(Parameters!$B$8,$C$31) -> 5.7971209e+10 | AF40: =AD40+AE40-X40 -> 4.2604304e+10 | AG40: =AD40+AE40-AA40 -> 3.8908656e+10 | AH40: =($AB$31+$I$31)/10 -> 412245.68 | AI40: =AF40/AH40 -> 103346.88 | AK40: =AG40/AH40 -> 94382.203 | AM40: =(POWER(AI40, -0.26) - 1)/-0.26 -> 3.6550324 | AN40: =(AM40-$AM$18)*100 -> 21.973302 | AO40: =LOG(AI40) -> 5.0142974 | AP40: =(POWER(AK40, -0.26) - 1)/-0.26 -> 3.6504699 | AQ40: =(AP40-$AP$18)*100 -> 20.843841 | AR40: =LOG(AK40) -> 4.9748901 | AT40: 1.9118139 | AX40: =SQRT(AO40) -> 2.2392627 | BB40: 1.9106203 | BF40: =SQRT(AR40) -> 2.2304462
A41: 10 | N41: =$N$31*Parameters!E24 -> 4.2554286e+08 | V41: =Parameters!C24 -> 0.3154254 | W41: =(V41*$U$31)/(Parameters!B24*POWER(Parameters!$B$8,$C$31)) -> 0.27391416 | X41: =$U$31*V41 -> 2.7635135e+10 | Y41: =Parameters!D24 -> 0.43275574 | Z41: =(Y41*$U$31)/(Parameters!B24*POWER(Parameters!$B$8,$C$31)) -> 0.37580336 | AA41: =$U$31*Y41 -> 3.7914712e+10 | AD41: =Parameters!B24*POWER(Parameters!$B$8,$C$31) -> 1.0088976e+11 | AF41: =AD41+AE41-X41 -> 7.3254629e+10 | AG41: =AD41+AE41-AA41 -> 6.2975052e+10 | AH41: =($AB$31+$I$31)/10 -> 412245.68 | AI41: =AF41/AH41 -> 177696.54 | AK41: =AG41/AH41 -> 152760.98 | AM41: =(POWER(AI41, -0.26) - 1)/-0.26 -> 3.6801531 | AN41: =(AM41-$AM$18)*100 -> 24.485366 | AO41: =LOG(AI41) -> 5.249679 | AP41: =(POWER(AK41, -0.26) - 1)/-0.26 -> 3.6734972 | AQ41: =(AP41-$AP$18)*100 -> 23.146568 | AR41: =LOG(AK41) -> 5.1840124 | AT41: 1.9183725 | AX41: =SQRT(AO41) -> 2.2912178 | BB41: 1.9166369 | BF41: =SQRT(AR41) -> 2.2768426
A44: Only the bottom five deciles get NZS
A45: Sensitivity check

Sheet Income means-test 4 deciles
A1: Decile | B1: Year | D1: NZS income per recipient | V1: Baseline tax | Y1: Progressive tax | AB1: Size tax paying group by income group | AD1: Gross income | AF1: Net Income Baseline tax | AG1: Net income Progressive tax | AH1: Quintile size | AI1: Average income pp baseline tax | AK1: Average income pp progressive | AM1: Utility score baseline tax | AP1: Utility scores progressive tax | AS1: Welfare score baseline tax isoelastic utility | AW1: Welfare score baseline tax log utility | BA1: Welfare score progressive tax isoelastic utility | BE1: Welfare score progressive tax log utility
B2: Year | C2: Years since base | D2: Base year annual rate singles | E2: Base year annual rate couples | F2: Mulitplier | G2: Current year real rate singles | H2: Current year annual rate couples | I2: 65+ employed population current year | J2: Single | K2: In a relationship | L2: NZS paid singles rate | M2: NZS paid couples rate | N2: NZS paid total to employed 65+ | O2: Total 65+ population | P2: Single | Q2: In a relationship | R2: NZS paid singles rate | S2: NZS paid couples rate | T2: NZS paid total to 65+ | U2: NZS paid total after means test | V2: Revenue share | W2: Implied average tax rate | X2: Decile NZS cost | Y2: Revenue share | Z2: Implied average tax rate | AA2: Decile NZS cost | AB2: Employed working age pop current year | AC2: Total tax paying population | AD2: Employment income | AE2: Pension income | AF2: Total income | AG2: Total income | AM2: Isoelastic utility p = 1.26 | AN2: Isoelastic normalised | AO2: Isoelsatic p = 1 | AP2: Isoelastic utility p = 1.26 | AQ2: Isoelastic normalised | AR2: Isoelsatic p = 1 | AS2: Utilitarian | AT2: Adjusted score | AU2: Prioritarian | AV2: Maximin | AW2: Utilitarian | AX2: Adjusted score | AY2: Prioritarian | AZ2: Maximin | BA2: Utilitarian | BB2: Adjusted score | BC2: Prioritarian | BD2: Maximin | BE2: Utilitarian | BF2: Adjusted score | BG2: Prioritarian | BH2: Maximin
A3: Overall | B3: 2026 | C3: 2 | D3: =Parameters!$B$4 -> 27012.44 | E3: =Parameters!$B$5 -> 20778.68 | F3: =Parameters!$B$8 -> 1.01088 | G3: =D3*POWER(F3,C3) -> 27603.428 | H3: =E3*POWER(F3,C3) -> 21233.284 | I3: =Parameters!B3*Parameters!B39 -> 232117.8 | J3: =I3*Parameters!$B$10 -> 97489.476 | K3: =I3*Parameters!$B$9 -> 134628.32 | L3: =J3*G3 -> 2.6910438e+09 | M3: =K3*H3 -> 2.8586014e+09 | N3: =M3+L3 -> 5.5496452e+09 | O3: =Parameters!B39 -> 932200 | P3: =O3*Parameters!$B$10 -> 391524 | Q3: =O3*Parameters!$B$9 -> 540676 | R3: =P3*G3 -> 1.0807405e+10 | S3: =Q3*H3 -> 1.1480327e+10 | T3: =S3+R3 -> 2.2287732e+10 | U3: =T3-SUM(N8:N13) -> 2.0168776e+10 | AA3: =SUM(AA4:AA13) -> 2.0168776e+10 | AB3: =Parameters!C39*Parameters!B2 -> 2728423.5 | AC3: =AB3+I3 -> 2960541.3 | AD3: =SUM(AD4:AD13) -> 1.9865009e+11 | AE3: =N3 -> 5.5496452e+09 | AF3: =AD3+AE3-X3 -> 2.0419974e+11 | AG3: =AD3+AE3-AA3 -> 1.8403096e+11 | AI3: post NZS | AJ3: pre-NZS | AK3: post-NZS | AL3: pre-NZS | AS3: =SUM(AM4:AM13) -> 35.993212 | AU3: =SUM(AT4:AT13) -> 18.971085 | AV3: =MIN(AM5:AM13) -> 3.5281118 | AW3: =SUM(AO4:AO13) -> 46.388073 | AY3: =SUM(AX4:AX13) -> 21.51661 | AZ3: =MIN(AO5:AO13) -> 4.1636233 | BA3: =SUM(AP4:AP13) -> 36.01116 | BC3: =SUM(BB4:BB13) -> 18.975856 | BD3: =MIN(AP5:AP13) -> 3.5322019 | BE3: =SUM(AR4:AR13) -> 46.486186 | BG3: =SUM(BF3:BF13) -> 21.540471 | BH3: =MIN(AR5:AR13) -> 4.1852442
A4: 1 | N4: =$N$3*Parameters!E15 -> 1.0090264e+09 | V4: =Parameters!C15 -> 0.0036096394 | W4: =(V4*$U$3)/(Parameters!B15*POWER(Parameters!$B$8, $C$3)) -> 0.089266158 | X4: =$U$3*V4 -> 72802008 | Y4: {=Parameters!D15:D24} -> 0 | Z4: =(Y4*$U$3)/(Parameters!B15*POWER(Parameters!$B$8, $C$3)) -> 0 | AA4: =$U$3*Y4 -> 0 | AD4: =Parameters!B15*POWER(Parameters!$B$8,$C$3) -> 8.1556113e+08 | AE4: =$AE$3*Parameters!E15 -> 1.0090264e+09 | AF4: =AD4+AE4-X4 -> 1.7517855e+09 | AG4: =AD4+AE4-AA4 -> 1.8245875e+09 | AH4: =($AB$3+$I$3)/10 -> 296054.13 | AI4: =AF4/AH4 -> 5917.1122 | AJ4: =(AF4-AE4)/AH4 -> 2508.8626 | AK4: =AG4/AH4 -> 6163.02 | AL4: =(AG4-AE4)/AH4 -> 2754.7703 | AM4: =(POWER(AI4, -0.26) - 1)/-0.26 -> 3.4441057 | AN4: =(AM4-$AM$4)*100 -> 0 | AO4: =LOG(AI4) -> 3.7721098 | AP4: =(POWER(AK4, -0.26) - 1)/-0.26 -> 3.4483396 | AQ4: =(AP4-$AP$4)*100 -> 0 | AR4: =LOG(AK4) -> 3.7897936 | AT4: =SQRT(AM4) -> 1.8558302 | AX4: =SQRT(AO4) -> 1.942192 | BB4: {=SQRT(AP4:AP13)} -> 1.8569705 | BF4: =SQRT(AR4) -> 1.9467392
A5: 2 | N5: =$N$3*Parameters!E16 -> 9.0812375e+08 | V5: =Parameters!C16 -> 0.014401036 | W5: =(V5*$U$3)/(Parameters!B16*POWER(Parameters!$B$8, $C$3)) -> 0.078554219 | X5: =$U$3*V5 -> 2.9045128e+08 | Y5: 0.0034800777 | Z5: =(Y5*$U$3)/(Parameters!B16*POWER(Parameters!$B$8, $C$3)) -> 0.018982994 | AA5: =$U$3*Y5 -> 70188909 | AD5: =Parameters!B16*POWER(Parameters!$B$8,$C$3) -> 3.6974625e+09 | AE5: =$AE$3*Parameters!E16 -> 9.0812375e+08 | AF5: =AD5+AE5-X5 -> 4.315135e+09 | AG5: =AD5+AE5-AA5 -> 4.5353974e+09 | AH5: =($AB$3+$I$3)/10 -> 296054.13 | AI5: =AF5/AH5 -> 14575.493 | AJ5: =(AF5-AE5)/AH5 -> 11508.069 | AK5: =AG5/AH5 -> 15319.487 | AL5: =(AG5-AE5)/AH5 -> 12252.062 | AM5: =(POWER(AI5, -0.26) - 1)/-0.26 -> 3.5281118 | AN5: =(AM5-$AM$4)*100 -> 8.4006088 | AO5: =LOG(AI5) -> 4.1636233 | AP5: =(POWER(AK5, -0.26) - 1)/-0.26 -> 3.5322019 | AQ5: =(AP5-$AP$4)*100 -> 8.3862309 | AR5: =LOG(AK5) -> 4.1852442 | AT5: =SQRT(AM5) -> 1.8783268 | AX5: =SQRT(AO5) -> 2.0404958 | BB5: 1.8794153 | BF5: =SQRT(AR5) -> 2.0457869
A6: 3 | N6: =$N$3*Parameters!E17 -> 8.0722111e+08 | V6: =Parameters!C17 -> 0.031399077 | W6: =(V6*$U$3)/(Parameters!B17*POWER(Parameters!$B$8, $C$3)) -> 0.082124865 | X6: =$U$3*V6 -> 6.3328096e+08 | Y6: 0.010886748 | Z6: =(Y6*$U$3)/(Parameters!B17*POWER(Parameters!$B$8, $C$3)) -> 0.028474491 | AA6: =$U$3*Y6 -> 2.1957239e+08 | AD6: =Parameters!B17*POWER(Parameters!$B$8,$C$3) -> 7.7111964e+09 | AE6: =$AE$3*Parameters!E17 -> 8.0722111e+08 | AF6: =AD6+AE6-X6 -> 7.8851366e+09 | AG6: =AD6+AE6-AA6 -> 8.2988451e+09 | AH6: =($AB$3+$I$3)/10 -> 296054.13 | AI6: =AF6/AH6 -> 26634.104 | AJ6: =(AF6-AE6)/AH6 -> 23907.504 | AK6: =AG6/AH6 -> 28031.513 | AL6: =(AG6-AE6)/AH6 -> 25304.913 | AM6: =(POWER(AI6, -0.26) - 1)/-0.26 -> 3.5742516 | AN6: =(AM6-$AM$4)*100 -> 13.014597 | AO6: =LOG(AI6) -> 4.4254381 | AP6: =(POWER(AK6, -0.26) - 1)/-0.26 -> 3.5778428 | AQ6: =(AP6-$AP$4)*100 -> 12.950319 | AR6: =LOG(AK6) -> 4.4476465 | AT6: =SQRT(AM6) -> 1.8905691 | AX6: =SQRT(AO6) -> 2.1036725 | BB6: 1.8915186 | BF6: =SQRT(AR6) -> 2.1089444
A7: 4 | N7: =$N$3*Parameters!E18 -> 7.0631848e+08 | V7: =Parameters!C18 -> 0.051692243 | W7: =(V7*$U$3)/(Parameters!B18*POWER(Parameters!$B$8, $C$3)) -> 0.085695511 | X7: =$U$3*V7 -> 1.0425693e+09 | Y7: 0.022901399 | Z7: =(Y7*$U$3)/(Parameters!B18*POWER(Parameters!$B$8, $C$3)) -> 0.037965988 | AA7: =$U$3*Y7 -> 4.6189319e+08 | AD7: =Parameters!B18*POWER(Parameters!$B$8,$C$3) -> 1.2165973e+10 | AE7: =$AE$3*Parameters!E18 -> 7.0631848e+08 | AF7: =AD7+AE7-X7 -> 1.1829722e+10 | AG7: =AD7+AE7-AA7 -> 1.2410398e+10 | AH7: =($AB$3+$I$3)/10 -> 296054.13 | AI7: =AF7/AH7 -> 39957.97 | AJ7: =(AF7-AE7)/AH7 -> 37572.196 | AK7: =AG7/AH7 -> 41919.355 | AL7: =(AG7-AE7)/AH7 -> 39533.581 | AM7: =(POWER(AI7, -0.26) - 1)/-0.26 -> 3.6014675 | AN7: =(AM7-$AM$4)*100 -> 15.736182 | AO7: =LOG(AI7) -> 4.6016034 | AP7: =(POWER(AK7, -0.26) - 1)/-0.26 -> 3.6044971 | AQ7: =(AP7-$AP$4)*100 -> 15.615753 | AR7: =LOG(AK7) -> 4.6224146 | AT7: =SQRT(AM7) -> 1.8977533 | AX7: =SQRT(AO7) -> 2.1451348 | BB7: 1.8985513 | BF7: =SQRT(AR7) -> 2.1499801
A8: 5 | N8: =$N$3*Parameters!E19 -> 6.0541584e+08 | V8: =Parameters!C19 -> 0.070583126 | W8: =(V8*$U$3)/(Parameters!B19*POWER(Parameters!$B$8, $C$3)) -> 0.089266158 | X8: =$U$3*V8 -> 1.4235753e+09 | Y8: 0.037524833 | Z8: =(Y8*$U$3)/(Parameters!B19*POWER(Parameters!$B$8, $C$3)) -> 0.047457485 | AA8: =$U$3*Y8 -> 7.5682996e+08 | AD8: =Parameters!B19*POWER(Parameters!$B$8,$C$3) -> 1.5947536e+10 | AF8: =AD8+AE8-X8 -> 1.4523961e+10 | AG8: =AD8+AE8-AA8 -> 1.5190706e+10 | AH8: =($AB$3+$I$3)/10 -> 296054.13 | AI8: =AF8/AH8 -> 49058.464 | AJ8: =(AF8-AE8)/AH8 -> 49058.464 | AK8: =AG8/AH8 -> 51310.57 | AL8: =(AG8-AE8)/AH8 -> 51310.57 | AM8: =(POWER(AI8, -0.26) - 1)/-0.26 -> 3.6141789 | AN8: =(AM8-$AM$4)*100 -> 17.007327 | AO8: =LOG(AI8) -> 4.6907139 | AP8: =(POWER(AK8, -0.26) - 1)/-0.26 -> 3.6168703 | AQ8: =(AP8-$AP$4)*100 -> 16.85307 | AR8: =LOG(AK8) -> 4.7102068 | AT8: =SQRT(AM8) -> 1.9010994 | AX8: =SQRT(AO8) -> 2.1658056 | BB8: 1.9018071 | BF8: =SQRT(AR8) -> 2.1703011
A9: 6 | N9: =$N$3*Parameters!E20 -> 5.045132e+08 | V9: =Parameters!C20 -> 0.090905111 | W9: =(V9*$U$3)/(Parameters!B20*POWER(Parameters!$B$8, $C$3)) -> 0.09640745 | X9: =$U$3*V9 -> 1.8334448e+09 | Y9: 0.053698687 | Z9: =(Y9*$U$3)/(Parameters!B20*POWER(Parameters!$B$8, $C$3)) -> 0.056948982 | AA9: =$U$3*Y9 -> 1.0830368e+09 | AD9: =Parameters!B20*POWER(Parameters!$B$8,$C$3) -> 1.9017667e+10 | AF9: =AD9+AE9-X9 -> 1.7184223e+10 | AG9: =AD9+AE9-AA9 -> 1.7934631e+10 | AH9: =($AB$3+$I$3)/10 -> 296054.13 | AI9: =AF9/AH9 -> 58044.192 | AJ9: =(AF9-AE9)/AH9 -> 58044.192 | AK9: =AG9/AH9 -> 60578.89 | AL9: =(AG9-AE9)/AH9 -> 60578.89 | AM9: =(POWER(AI9, -0.26) - 1)/-0.26 -> 3.6241046 | AN9: =(AM9-$AM$4)*100 -> 17.99989 | AO9: =LOG(AI9) -> 4.7637588 | AP9: =(POWER(AK9, -0.26) - 1)/-0.26 -> 3.6265585 | AQ9: =(AP9-$AP$4)*100 -> 17.82189 | AR9: =LOG(AK9) -> 4.7823213 | AT9: =SQRT(AM9) -> 1.9037081 | AX9: =SQRT(AO9) -> 2.1826037 | BB9: 1.9043525 | BF9: =SQRT(AR9) -> 2.1868519
A10: 7 | N10: =$N$3*Parameters!E21 -> 4.0361056e+08 | V10: =Parameters!C21 -> 0.11035602 | W10: =(V10*$U$3)/(Parameters!B21*POWER(Parameters!$B$8, $C$3)) -> 0.099978097 | X10: =$U$3*V10 -> 2.2257459e+09 | Y10: 0.083813868 | Z10: =(Y10*$U$3)/(Parameters!B21*POWER(Parameters!$B$8, $C$3)) -> 0.075931976 | AA10: =$U$3*Y10 -> 1.6904231e+09 | AD10: =Parameters!B21*POWER(Parameters!$B$8,$C$3) -> 2.2262336e+10 | AF10: =AD10+AE10-X10 -> 2.003659e+10 | AG10: =AD10+AE10-AA10 -> 2.0571913e+10 | AH10: =($AB$3+$I$3)/10 -> 296054.13 | AI10: =AF10/AH10 -> 67678.805 | AJ10: =(AF10-AE10)/AH10 -> 67678.805 | AK10: =AG10/AH10 -> 69486.997 | AL10: =(AG10-AE10)/AH10 -> 69486.997 | AM10: =(POWER(AI10, -0.26) - 1)/-0.26 -> 3.6327958 | AN10: =(AM10-$AM$4)*100 -> 18.869017 | AO10: =LOG(AI10) -> 4.8304527 | AP10: =(POWER(AK10, -0.26) - 1)/-0.26 -> 3.6342535 | AQ10: =(AP10-$AP$4)*100 -> 18.591386 | AR10: =LOG(AK10) -> 4.8419035 | AT10: =SQRT(AM10) -> 1.9059895 | AX10: =SQRT(AO10) -> 2.1978291 | BB10: 1.9063718 | BF10: =SQRT(AR10) -> 2.2004326
A11: 8 | N11: =$N$3*Parameters!E22 -> 3.0270792e+08 | V11: =Parameters!C22 -> 0.13623162 | W11: =(V11*$U$3)/(Parameters!B22*POWER(Parameters!$B$8, $C$3)) -> 0.10354874 | X11: =$U$3*V11 -> 2.747625e+09 | Y11: 0.13736006 | Z11: =(Y11*$U$3)/(Parameters!B22*POWER(Parameters!$B$8, $C$3)) -> 0.10440647 | AA11: =$U$3*Y11 -> 2.7703844e+09 | AD11: =Parameters!B22*POWER(Parameters!$B$8,$C$3) -> 2.6534605e+10 | AF11: =AD11+AE11-X11 -> 2.378698e+10 | AG11: =AD11+AE11-AA11 -> 2.376422e+10 | AH11: =($AB$3+$I$3)/10 -> 296054.13 | AI11: =AF11/AH11 -> 80346.725 | AJ11: =(AF11-AE11)/AH11 -> 80346.725 | AK11: =AG11/AH11 -> 80269.849 | AL11: =(AG11-AE11)/AH11 -> 80269.849 | AM11: =(POWER(AI11, -0.26) - 1)/-0.26 -> 3.6421046 | AN11: =(AM11-$AM$4)*100 -> 19.799897 | AO11: =LOG(AI11) -> 4.9049682 | AP11: =(POWER(AK11, -0.26) - 1)/-0.26 -> 3.6420538 | AQ11: =(AP11-$AP$4)*100 -> 19.371423 | AR11: =LOG(AK11) -> 4.9045524 | AT11: =SQRT(AM11) -> 1.9084299 | AX11: =SQRT(AO11) -> 2.2147163 | BB11: 1.9084166 | BF11: =SQRT(AR11) -> 2.2146224
A12: 9 | N12: =$N$3*Parameters!E23 -> 2.0180528e+08 | V12: =Parameters!C23 -> 0.17539672 | W12: =(V12*$U$3)/(Parameters!B23*POWER(Parameters!$B$8, $C$3)) -> 0.10711939 | X12: =$U$3*V12 -> 3.5375373e+09 | Y12: 0.21757858 | Z12: =(Y12*$U$3)/(Parameters!B23*POWER(Parameters!$B$8, $C$3)) -> 0.13288096 | AA12: =$U$3*Y12 -> 4.3882937e+09 | AD12: =Parameters!B23*POWER(Parameters!$B$8,$C$3) -> 3.3024248e+10 | AF12: =AD12+AE12-X12 -> 2.9486711e+10 | AG12: =AD12+AE12-AA12 -> 2.8635954e+10 | AH12: =($AB$3+$I$3)/10 -> 296054.13 | AI12: =AF12/AH12 -> 99599.052 | AJ12: =(AF12-AE12)/AH12 -> 99599.052 | AK12: =AG12/AH12 -> 96725.4 | AL12: =(AG12-AE12)/AH12 -> 96725.4 | AM12: =(POWER(AI12, -0.26) - 1)/-0.26 -> 3.6531881 | AN12: =(AM12-$AM$4)*100 -> 20.90824 | AO12: =LOG(AI12) -> 4.9982552 | AP12: =(POWER(AK12, -0.26) - 1)/-0.26 -> 3.6517136 | AQ12: =(AP12-$AP$4)*100 -> 20.337401 | AR12: =LOG(AK12) -> 4.9855405 | AT12: =SQRT(AM12) -> 1.9113315 | AX12: =SQRT(AO12) -> 2.2356778 | BB12: 1.9109457 | BF12: =SQRT(AR12) -> 2.2328324
A13: 10 | N13: =$N$3*Parameters!E24 -> 1.0090264e+08 | V13: =Parameters!C24 -> 0.3154254 | W13: =(V13*$U$3)/(Parameters!B24*POWER(Parameters!$B$8, $C$3)) -> 0.11069004 | X13: =$U$3*V13 -> 6.3617444e+09 | Y13: 0.43275574 | Z13: =(Y13*$U$3)/(Parameters!B24*POWER(Parameters!$B$8, $C$3)) -> 0.15186395 | AA13: =$U$3*Y13 -> 8.7281537e+09 | AD13: =Parameters!B24*POWER(Parameters!$B$8,$C$3) -> 5.7473505e+10 | AF13: =AD13+AE13-X13 -> 5.1111761e+10 | AG13: =AD13+AE13-AA13 -> 4.8745352e+10 | AH13: =($AB$3+$I$3)/10 -> 296054.13 | AI13: =AF13/AH13 -> 172643.3 | AJ13: =(AF13-AE13)/AH13 -> 172643.3 | AK13: =AG13/AH13 -> 164650.13 | AL13: =(AG13-AE13)/AH13 -> 164650.13 | AM13: =(POWER(AI13, -0.26) - 1)/-0.26 -> 3.6789032 | AN13: =(AM13-$AM$4)*100 -> 23.479757 | AO13: =LOG(AI13) -> 5.2371497 | AP13: =(POWER(AK13, -0.26) - 1)/-0.26 -> 3.6768291 | AQ13: =(AP13-$AP$4)*100 -> 22.848946 | AR13: =LOG(AK13) -> 5.2165621 | AT13: =SQRT(AM13) -> 1.9180467 | AX13: =SQRT(AO13) -> 2.288482 | BB13: 1.917506 | BF13: =SQRT(AR13) -> 2.2839794
A15: Decile | B15: Year | D15: NZS income per recipient | V15: Baseline tax | Y15: Progressive tax | AB15: Size tax paying group by income group | AD15: Gross income | AF15: Net Income Baseline tax | AG15: Net income Progressive tax | AH15: Quintile size | AI15: Average income pp baseline tax | AK15: Average income pp progressive | AM15: Utility score baseline tax | AP15: Utility scores progressive tax | AS15: Welfare score baseline tax isoelastic utility | AW15: Welfare score baseline tax log utility | BA15: Welfare score progressive tax isoelastic utility | BE15: Welfare score progressive tax log utility
B16: Year | C16: Years since base | D16: Base year annual rate singles | E16: Base year annual rate couples | F16: Mulitplier | G16: Current year real rate singles | H16: Current year annual rate couples | I16: 65+ employed population current year | J16: Single | K16: In a relationship | L16: NZS paid singles rate | M16: NZS paid couples rate | N16: NZS paid total to employed 65+ | O16: Total 65+ population | P16: Single | Q16: In a relationship | R16: NZS paid singles rate | S16: NZS paid couples rate | T16: NZS paid total to 65+ | U16: NZS paid total after means test | V16: Revenue share | W16: Implied average tax rate | X16: Decile NZS cost | Y16: Revenue share | Z16: Implied average tax rate | AA16: Decile NZS cost | AB16: Employed working age pop current year | AC16: Total tax paying population | AD16: Employment income | AE16: Pension income | AF16: Total income | AG16: Total income | AM16: Isoelastic utility p = 1.26 | AN16: Isoelastic normalised | AO16: Isoelsatic p = 1 | AP16: Isoelastic utility p = 1.26 | AQ16: Isoelastic normalised | AR16: Isoelsatic p = 1 | AS16: Utilitarian | AT16: Adjusted score | AU16: Prioritarian | AV16: Maximin | AW16: Utilitarian | AX16: Adjusted score | AY16: Prioritarian | AZ16: Maximin | BA16: Utilitarian | BB16: Adjusted score | BC16: Prioritarian | BD16: Maximin | BE16: Utilitarian | BF16: Adjusted score | BG16: Prioritarian | BH16: Maximin
A17: Overall | B17: 2040 | C17: 16 | D17: =Parameters!$B$4 -> 27012.44 | E17: =Parameters!$B$5 -> 20778.68 | F17: =Parameters!$B$8 -> 1.01088 | G17: =D17*POWER(F17,C17) -> 32118.665 | H17: =E17*POWER(F17,C17) -> 24706.523 | I17: =Parameters!B3*Parameters!B40 -> 320687.1 | J17: =I17*Parameters!$B$10 -> 134688.58 | K17: =I17*Parameters!$B$9 -> 185998.52 | L17: =J17*G17 -> 4.3260174e+09 | M17: =K17*H17 -> 4.5953766e+09 | N17: =M17+L17 -> 8.921394e+09 | O17: =Parameters!B40 -> 1287900 | P17: =O17*Parameters!$B$10 -> 540918 | Q17: =O17*Parameters!$B$9 -> 746982 | R17: =P17*G17 -> 1.7373564e+10 | S17: =Q17*H17 -> 1.8455328e+10 | T17: =S17+R17 -> 3.5828892e+10 | U17: =T17-SUM(N22:N27) -> 3.2422541e+10 | AA17: =SUM(AA18:AA27) -> 3.2422541e+10 | AB17: =Parameters!C40*Parameters!B2 -> 3054491 | AC17: =AB17+I17 -> 3375178.1 | AD17: =SUM(AD18:AD27) -> 2.3114432e+11 | AE17: =N17 -> 8.921394e+09 | AF17: =AD17+AE17-X17 -> 2.4006571e+11 | AG17: =AD17+AE17-AA17 -> 2.0764317e+11 | AS17: =SUM(AN18:AN27) -> 161.58494 | AU17: =SUM(AT18:AT27) -> 18.965149 | AV17: =MIN(AM19:AM27) -> 3.5250847 | AW17: =SUM(AO18:AO27) -> 46.254709 | AY17: =SUM(AX18:AX27) -> 21.484863 | AZ17: =MIN(AO19:AO27) -> 4.1478005 | BA17: =SUM(AQ18:AQ27) -> 157.66793 | BC17: =SUM(BB18:BB27) -> 18.972095 | BD17: =MIN(AP19:AP27) -> 3.5310386 | BE17: =SUM(AR18:AR27) -> 46.395523 | BG17: =SUM(BF17:BF27) -> 21.519197 | BH17: =MIN(AR19:AR27) -> 4.1790662
A18: 1 | N18: =$N$17*Parameters!E15 -> 1.6220716e+09 | V18: {=Parameters!C15:C24} -> 0.0036096394 | W18: =(V18*$U$17)/(Parameters!B15*POWER(Parameters!$B$8, $C$17)) -> 0.12332749 | X18: =$U$17*V18 -> 1.1703368e+08 | Y18: =Parameters!D15 -> 0 | Z18: =(Y18*$U$17)/(Parameters!B15*POWER(Parameters!$B$8, $C$17)) -> 0 | AA18: =$U$17*Y18 -> 0 | AD18: =Parameters!B15*POWER(Parameters!$B$8, $C$17) -> 9.4896671e+08 | AE18: =$AE$3*Parameters!E15 -> 1.0090264e+09 | AF18: =AD18+AE18-X18 -> 1.8409594e+09 | AG18: =AD18+AE18-AA18 -> 1.9579931e+09 | AH18: =($AB$17+$I$17)/10 -> 337517.81 | AI18: =AF18/AH18 -> 5454.4068 | AK18: =AG18/AH18 -> 5801.1549 | AM18: =(POWER(AI18, -0.26) - 1)/-0.26 -> 3.4355034 | AN18: =(AM18-$AM$18)*100 -> 0 | AO18: =LOG(AI18) -> 3.7367475 | AP18: =(POWER(AK18, -0.26) - 1)/-0.26 -> 3.4420315 | AQ18: =(AP18-$AP$18)*100 -> 0 | AR18: =LOG(AK18) -> 3.7635145 | AT18: {=SQRT(AM18:AM27)} -> 1.8535111 | AX18: =SQRT(AO18) -> 1.9330669 | BB18: {=SQRT(AP18:AP27)} -> 1.8552713 | BF18: =SQRT(AR18) -> 1.939978
A19: 2 | N19: =$N$17*Parameters!E16 -> 1.4598645e+09 | V19: 0.014401036 | W19: =(V19*$U$17)/(Parameters!B16*POWER(Parameters!$B$8, $C$17)) -> 0.10852819 | X19: =$U$17*V19 -> 4.6691819e+08 | Y19: =Parameters!D16 -> 0.0034800777 | Z19: =(Y19*$U$17)/(Parameters!B16*POWER(Parameters!$B$8, $C$17)) -> 0.026226344 | AA19: =$U$17*Y19 -> 1.1283296e+08 | AD19: =Parameters!B16*POWER(Parameters!$B$8, $C$17) -> 4.3022757e+09 | AE19: =$AE$3*Parameters!E16 -> 9.0812375e+08 | AF19: =AD19+AE19-X19 -> 4.7434813e+09 | AG19: =AD19+AE19-AA19 -> 5.0975665e+09 | AH19: =($AB$17+$I$17)/10 -> 337517.81 | AI19: =AF19/AH19 -> 14054.018 | AK19: =AG19/AH19 -> 15103.104 | AM19: =(POWER(AI19, -0.26) - 1)/-0.26 -> 3.5250847 | AN19: =(AM19-$AM$18)*100 -> 8.9581335 | AO19: =LOG(AI19) -> 4.1478005 | AP19: =(POWER(AK19, -0.26) - 1)/-0.26 -> 3.5310386 | AQ19: =(AP19-$AP$18)*100 -> 8.9007108 | AR19: =LOG(AK19) -> 4.1790662 | AT19: 1.8775209 | AX19: =SQRT(AO19) -> 2.036615 | BB19: 1.8791058 | BF19: =SQRT(AR19) -> 2.0442765
A20: 3 | N20: =$N$17*Parameters!E17 -> 1.2976573e+09 | V20: 0.031399077 | W20: =(V20*$U$17)/(Parameters!B17*POWER(Parameters!$B$8, $C$17)) -> 0.11346129 | X20: =$U$17*V20 -> 1.0180379e+09 | Y20: =Parameters!D17 -> 0.010886748 | Z20: =(Y20*$U$17)/(Parameters!B17*POWER(Parameters!$B$8, $C$17)) -> 0.039339516 | AA20: =$U$17*Y20 -> 3.5297605e+08 | AD20: =Parameters!B17*POWER(Parameters!$B$8, $C$17) -> 8.972557e+09 | AE20: =$AE$3*Parameters!E17 -> 8.0722111e+08 | AF20: =AD20+AE20-X20 -> 8.7617402e+09 | AG20: =AD20+AE20-AA20 -> 9.426802e+09 | AH20: =($AB$17+$I$17)/10 -> 337517.81 | AI20: =AF20/AH20 -> 25959.342 | AK20: =AG20/AH20 -> 27929.791 | AM20: =(POWER(AI20, -0.26) - 1)/-0.26 -> 3.5724315 | AN20: =(AM20-$AM$18)*100 -> 13.692807 | AO20: =LOG(AI20) -> 4.4142937 | AP20: =(POWER(AK20, -0.26) - 1)/-0.26 -> 3.5775891 | AQ20: =(AP20-$AP$18)*100 -> 13.555759 | AR20: =LOG(AK20) -> 4.4460677 | AT20: 1.8900877 | AX20: =SQRT(AO20) -> 2.1010221 | BB20: 1.8914516 | BF20: =SQRT(AR20) -> 2.1085701
A21: 4 | N21: =$N$17*Parameters!E18 -> 1.1354501e+09 | V21: 0.051692243 | W21: =(V21*$U$17)/(Parameters!B18*POWER(Parameters!$B$8, $C$17)) -> 0.11839439 | X21: =$U$17*V21 -> 1.6759939e+09 | Y21: =Parameters!D18 -> 0.022901399 | Z21: =(Y21*$U$17)/(Parameters!B18*POWER(Parameters!$B$8, $C$17)) -> 0.052452688 | AA21: =$U$17*Y21 -> 7.4252154e+08 | AD21: =Parameters!B18*POWER(Parameters!$B$8, $C$17) -> 1.4156025e+10 | AE21: =$AE$3*Parameters!E18 -> 7.0631848e+08 | AF21: =AD21+AE21-X21 -> 1.3186349e+10 | AG21: =AD21+AE21-AA21 -> 1.4119821e+10 | AH21: =($AB$17+$I$17)/10 -> 337517.81 | AI21: =AF21/AH21 -> 39068.602 | AK21: =AG21/AH21 -> 41834.3 | AM21: =(POWER(AI21, -0.26) - 1)/-0.26 -> 3.6000313 | AN21: =(AM21-$AM$18)*100 -> 16.452789 | AO21: =LOG(AI21) -> 4.5918279 | AP21: =(POWER(AK21, -0.26) - 1)/-0.26 -> 3.6043695 | AQ21: =(AP21-$AP$18)*100 -> 16.233801 | AR21: =LOG(AK21) -> 4.6215325 | AT21: 1.8973748 | AX21: =SQRT(AO21) -> 2.1428551 | BB21: 1.8985177 | BF21: =SQRT(AR21) -> 2.149775
A22: 5 | N22: =$N$17*Parameters!E19 -> 9.7324298e+08 | V22: 0.070583126 | W22: =(V22*$U$17)/(Parameters!B19*POWER(Parameters!$B$8, $C$17)) -> 0.12332749 | X22: =$U$17*V22 -> 2.2884843e+09 | Y22: =Parameters!D19 -> 0.037524833 | Z22: =(Y22*$U$17)/(Parameters!B19*POWER(Parameters!$B$8, $C$17)) -> 0.06556586 | AA22: =$U$17*Y22 -> 1.2166504e+09 | AD22: =Parameters!B19*POWER(Parameters!$B$8, $C$17) -> 1.8556158e+10 | AF22: =AD22+AE22-X22 -> 1.6267673e+10 | AG22: =AD22+AE22-AA22 -> 1.7339507e+10 | AH22: =($AB$17+$I$17)/10 -> 337517.81 | AI22: =AF22/AH22 -> 48197.97 | AK22: =AG22/AH22 -> 51373.607 | AM22: =(POWER(AI22, -0.26) - 1)/-0.26 -> 3.6131092 | AN22: =(AM22-$AM$18)*100 -> 17.760577 | AO22: =LOG(AI22) -> 4.6830287 | AP22: =(POWER(AK22, -0.26) - 1)/-0.26 -> 3.6169435 | AQ22: =(AP22-$AP$18)*100 -> 17.491201 | AR22: =LOG(AK22) -> 4.7107401 | AT22: 1.900818 | AX22: =SQRT(AO22) -> 2.1640307 | BB22: 1.9018264 | BF22: =SQRT(AR22) -> 2.1704239
A23: 6 | N23: =$N$17*Parameters!E20 -> 8.1103582e+08 | V23: 0.090905111 | W23: =(V23*$U$17)/(Parameters!B20*POWER(Parameters!$B$8, $C$17)) -> 0.13319369 | X23: =$U$17*V23 -> 2.9473747e+09 | Y23: =Parameters!D20 -> 0.053698687 | Z23: =(Y23*$U$17)/(Parameters!B20*POWER(Parameters!$B$8, $C$17)) -> 0.078679033 | AA23: =$U$17*Y23 -> 1.7410479e+09 | AD23: =Parameters!B20*POWER(Parameters!$B$8, $C$17) -> 2.2128486e+10 | AF23: =AD23+AE23-X23 -> 1.9181112e+10 | AG23: =AD23+AE23-AA23 -> 2.0387438e+10 | AH23: =($AB$17+$I$17)/10 -> 337517.81 | AI23: =AF23/AH23 -> 56829.925 | AK23: =AG23/AH23 -> 60404.038 | AM23: =(POWER(AI23, -0.26) - 1)/-0.26 -> 3.6228806 | AN23: =(AM23-$AM$18)*100 -> 18.737724 | AO23: =LOG(AI23) -> 4.7545771 | AP23: =(POWER(AK23, -0.26) - 1)/-0.26 -> 3.6263934 | AQ23: =(AP23-$AP$18)*100 -> 18.436194 | AR23: =LOG(AK23) -> 4.781066 | AT23: 1.9033866 | AX23: =SQRT(AO23) -> 2.1804993 | BB23: 1.9043092 | BF23: =SQRT(AR23) -> 2.1865649
A24: 7 | N24: =$N$17*Parameters!E21 -> 6.4882865e+08 | V24: 0.11035602 | W24: =(V24*$U$17)/(Parameters!B21*POWER(Parameters!$B$8, $C$17)) -> 0.13812679 | X24: =$U$17*V24 -> 3.5780227e+09 | Y24: =Parameters!D21 -> 0.083813868 | Z24: =(Y24*$U$17)/(Parameters!B21*POWER(Parameters!$B$8, $C$17)) -> 0.10490538 | AA24: =$U$17*Y24 -> 2.7174586e+09 | AD24: =Parameters!B21*POWER(Parameters!$B$8, $C$17) -> 2.5903902e+10 | AF24: =AD24+AE24-X24 -> 2.2325879e+10 | AG24: =AD24+AE24-AA24 -> 2.3186443e+10 | AH24: =($AB$17+$I$17)/10 -> 337517.81 | AI24: =AF24/AH24 -> 66147.262 | AK24: =AG24/AH24 -> 68696.948 | AM24: =(POWER(AI24, -0.26) - 1)/-0.26 -> 3.6315223 | AN24: =(AM24-$AM$18)*100 -> 19.601889 | AO24: =LOG(AI24) -> 4.8205119 | AP24: =(POWER(AK24, -0.26) - 1)/-0.26 -> 3.6336225 | AQ24: =(AP24-$AP$18)*100 -> 19.159106 | AR24: =LOG(AK24) -> 4.8369374 | AT24: 1.9056553 | AX24: =SQRT(AO24) -> 2.1955664 | BB24: 1.9062063 | BF24: =SQRT(AR24) -> 2.1993039
A25: 8 | N25: =$N$17*Parameters!E22 -> 4.8662149e+08 | V25: 0.13623162 | W25: =(V25*$U$17)/(Parameters!B22*POWER(Parameters!$B$8, $C$17)) -> 0.14305989 | X25: =$U$17*V25 -> 4.4169752e+09 | Y25: =Parameters!D22 -> 0.13736006 | Z25: =(Y25*$U$17)/(Parameters!B22*POWER(Parameters!$B$8, $C$17)) -> 0.14424489 | AA25: =$U$17*Y25 -> 4.4535623e+09 | AD25: =Parameters!B22*POWER(Parameters!$B$8, $C$17) -> 3.0875008e+10 | AF25: =AD25+AE25-X25 -> 2.6458033e+10 | AG25: =AD25+AE25-AA25 -> 2.6421446e+10 | AH25: =($AB$17+$I$17)/10 -> 337517.81 | AI25: =AF25/AH25 -> 78390.036 | AK25: =AG25/AH25 -> 78281.635 | AM25: =(POWER(AI25, -0.26) - 1)/-0.26 -> 3.6407924 | AN25: =(AM25-$AM$18)*100 -> 20.528904 | AO25: =LOG(AI25) -> 4.8942609 | AP25: =(POWER(AK25, -0.26) - 1)/-0.26 -> 3.6407185 | AQ25: =(AP25-$AP$18)*100 -> 19.868707 | AR25: =LOG(AK25) -> 4.8936599 | AT25: 1.9080861 | AX25: =SQRT(AO25) -> 2.2122976 | BB25: 1.9080667 | BF25: =SQRT(AR25) -> 2.2121618
A26: 9 | N26: =$N$17*Parameters!E23 -> 3.2441433e+08 | V26: 0.17539672 | W26: =(V26*$U$17)/(Parameters!B23*POWER(Parameters!$B$8, $C$17)) -> 0.14799299 | X26: =$U$17*V26 -> 5.6868075e+09 | Y26: =Parameters!D23 -> 0.21757858 | Z26: =(Y26*$U$17)/(Parameters!B23*POWER(Parameters!$B$8, $C$17)) -> 0.18358441 | AA26: =$U$17*Y26 -> 7.0544505e+09 | AD26: =Parameters!B23*POWER(Parameters!$B$8, $C$17) -> 3.8426196e+10 | AF26: =AD26+AE26-X26 -> 3.2739389e+10 | AG26: =AD26+AE26-AA26 -> 3.1371745e+10 | AH26: =($AB$17+$I$17)/10 -> 337517.81 | AI26: =AF26/AH26 -> 97000.477 | AK26: =AG26/AH26 -> 92948.415 | AM26: =(POWER(AI26, -0.26) - 1)/-0.26 -> 3.6518571 | AN26: =(AM26-$AM$18)*100 -> 21.635373 | AO26: =LOG(AI26) -> 4.9867739 | AP26: =(POWER(AK26, -0.26) - 1)/-0.26 -> 3.6496895 | AQ26: =(AP26-$AP$18)*100 -> 20.765803 | AR26: =LOG(AK26) -> 4.968242 | AT26: 1.9109833 | AX26: =SQRT(AO26) -> 2.2331086 | BB26: 1.9104161 | BF26: =SQRT(AR26) -> 2.2289554
A27: 10 | N27: =$N$17*Parameters!E24 -> 1.6220716e+08 | V27: 0.3154254 | W27: =(V27*$U$17)/(Parameters!B24*POWER(Parameters!$B$8, $C$17)) -> 0.15292609 | X27: =$U$17*V27 -> 1.0226893e+10 | Y27: =Parameters!D24 -> 0.43275574 | Z27: =(Y27*$U$17)/(Parameters!B24*POWER(Parameters!$B$8, $C$17)) -> 0.20981075 | AA27: =$U$17*Y27 -> 1.4031041e+10 | AD27: =Parameters!B24*POWER(Parameters!$B$8, $C$17) -> 6.6874746e+10 | AF27: =AD27+AE27-X27 -> 5.6647853e+10 | AG27: =AD27+AE27-AA27 -> 5.2843705e+10 | AH27: =($AB$17+$I$17)/10 -> 337517.81 | AI27: =AF27/AH27 -> 167836.63 | AK27: =AG27/AH27 -> 156565.68 | AM27: =(POWER(AI27, -0.26) - 1)/-0.26 -> 3.6776708 | AN27: =(AM27-$AM$18)*100 -> 24.216744 | AO27: =LOG(AI27) -> 5.2248868 | AP27: =(POWER(AK27, -0.26) - 1)/-0.26 -> 3.674598 | AQ27: =(AP27-$AP$18)*100 -> 23.256652 | AR27: =LOG(AK27) -> 5.1946966 | AT27: 1.9177254 | AX27: =SQRT(AO27) -> 2.2858011 | BB27: 1.9169241 | BF27: =SQRT(AR27) -> 2.2791877
A29: Decile | B29: Year | D29: NZS income per recipient | V29: Baseline tax | Y29: Progressive tax | AB29: Size tax paying group by income group | AD29: Gross income | AF29: Net Income Baseline tax | AG29: Net income Progressive tax | AH29: Quintile size | AI29: Average income pp baseline tax | AK29: Average income pp progressive | AM29: Utility score baseline tax | AP29: Utility scores progressive tax | AS29: Welfare score baseline tax isoelastic utility | AW29: Welfare score baseline tax log utility | BA29: Welfare score progressive tax isoelastic utility | BE29: Welfare score progressive tax log utility
B30: Year | C30: Years since base | D30: Base year annual rate singles | E30: Base year annual rate couples | F30: Mulitplier | G30: Current year real rate singles | H30: Current year annual rate couples | I30: 65+ employed population current year | J30: Single | K30: In a relationship | L30: NZS paid singles rate | M30: NZS paid couples rate | N30: NZS paid total to employed 65+ | O30: Total 65+ population | P30: Single | Q30: In a relationship | R30: NZS paid singles rate | S30: NZS paid couples rate | T30: NZS paid total to 65+ | U30: NZS paid total after means test | V30: Revenue share | W30: Implied average tax rate | X30: Decile NZS cost | Y30: Revenue share | Z30: Implied average tax rate | AA30: Decile NZS cost | AB30: Employed working age pop current year | AC30: Total tax paying population | AD30: Employment income | AE30: Pension income | AF30: Total income | AG30: Total income | AM30: Isoelastic utility p = 1.26 | AN30: Isoelastic normalised | AO30: Isoelsatic p = 1 | AP30: Isoelastic utility p = 1.26 | AQ30: Isoelastic normalised | AR30: Isoelsatic p = 1 | AS30: Utilitarian | AT30: Adjusted score | AU30: Prioritarian | AV30: Maximin | AW30: Utilitarian | AX30: Adjusted score | AY30: Prioritarian | AZ30: Maximin | BA30: Utilitarian | BB30: Adjusted score | BC30: Prioritarian | BD30: Maximin | BE30: Utilitarian | BF30: Adjusted score | BG30: Prioritarian | BH30: Maximin
A31: Overall | B31: 2078 | C31: 54 | D31: =Parameters!$B$4 -> 27012.44 | E31: =Parameters!$B$5 -> 20778.68 | F31: =Parameters!$B$8 -> 1.01088 | G31: =D31*POWER(F31,C31) -> 48455.429 | H31: =E31*POWER(F31,C31) -> 37273.192 | I31: =Parameters!$B$3*Parameters!B42 -> 557660.4 | J31: =I31*Parameters!$B$10 -> 234217.37 | K31: =I31*Parameters!$B$9 -> 323443.03 | L31: =J31*G31 -> 1.1349103e+10 | M31: =K31*H31 -> 1.2055754e+10 | N31: =M31+L31 -> 2.3404857e+10 | O31: =Parameters!B42 -> 2239600 | P31: =O31*Parameters!$B$10 -> 940632 | Q31: =O31*Parameters!$B$9 -> 1298968 | R31: =P31*G31 -> 4.5578727e+10 | S31: =Q31*H31 -> 4.8416683e+10 | T31: =S31+R31 -> 9.399541e+10 | U31: =T31-SUM(N36:N41) -> 8.505901e+10 | AA31: =SUM(AA32:AA41) -> 8.505901e+10 | AB31: =Parameters!C42*Parameters!B2 -> 3564796.4 | AC31: =AB31+I31 -> 4122456.8 | AD31: =SUM(AD32:AD41) -> 3.4871304e+11 | AE31: =N31 -> 2.3404857e+10 | AF31: =AD31+AE31-X31 -> 3.721179e+11 | AG31: =AD31+AE31-AA31 -> 2.8705889e+11 | AS31: =SUM(AN32:AN41) -> 179.45516 | AU31: =SUM(AT32:AT41) -> 19.012675 | AV31: =MIN(AM33:AM41) -> 3.5606105 | AW31: =SUM(AO32:AO41) -> 47.263707 | AY31: =SUM(AX32:AX41) -> 21.728073 | AZ31: =MIN(AO33:AO41) -> 4.3436716 | BA31: =SUM(AQ32:AQ41) -> 176.20993 | BC31: =SUM(BB32:BB41) -> 19.021354 | BD31: =MIN(AP33:AP41) -> 3.5677396 | BE31: =SUM(AR32:AR41) -> 47.463214 | BG31: =SUM(BF31:BF41) -> 21.775657 | BH31: =MIN(AR33:AR41) -> 4.3859044
A32: 1 | N32: =$N$31*Parameters!E15 -> 4.2554286e+09 | V32: =Parameters!C15 -> 0.0036096394 | W32: =(V32*$U$31)/(Parameters!B15*POWER(Parameters!$B$8,$C$31)) -> 0.21446094 | X32: =$U$31*V32 -> 3.0703235e+08 | Y32: =Parameters!D15 -> 0 | Z32: =(Y32*$U$31)/(Parameters!B15*POWER(Parameters!$B$8,$C$31)) -> 0 | AA32: =$U$31*Y32 -> 0 | AD32: =Parameters!B15*POWER(Parameters!$B$8,$C$31) -> 1.431647e+09 | AE32: =$AE$31*Parameters!E15 -> 4.2554286e+09 | AF32: =AD32+AE32-X32 -> 5.3800432e+09 | AG32: =AD32+AE32-AA32 -> 5.6870756e+09 | AH32: =($AB$31+$I$31)/10 -> 412245.68 | AI32: =AF32/AH32 -> 13050.575 | AK32: =AG32/AH32 -> 13795.355 | AM32: =(POWER(AI32, -0.26) - 1)/-0.26 -> 3.5188411 | AN32: =(AM32-$AM$18)*100 -> 8.3337678 | AO32: =LOG(AI32) -> 4.1156296 | AP32: =(POWER(AK32, -0.26) - 1)/-0.26 -> 3.5235303 | AQ32: =(AP32-$AP$18)*100 -> 8.1498793 | AR32: =LOG(AK32) -> 4.1397329 | AT32: {=SQRT(AM32:AM41)} -> 1.8758574 | AX32: =SQRT(AO32) -> 2.0287015 | BB32: {=SQRT(AP32:AP41)} -> 1.8771069 | BF32: =SQRT(AR32) -> 2.0346334
A33: 2 | N33: =$N$31*Parameters!E16 -> 3.8298857e+09 | V33: =Parameters!C16 -> 0.014401036 | W33: =(V33*$U$31)/(Parameters!B16*POWER(Parameters!$B$8,$C$31)) -> 0.18872563 | X33: =$U$31*V33 -> 1.2249379e+09 | Y33: =Parameters!D16 -> 0.0034800777 | Z33: =(Y33*$U$31)/(Parameters!B16*POWER(Parameters!$B$8,$C$31)) -> 0.045606429 | AA33: =$U$31*Y33 -> 2.9601197e+08 | AD33: =Parameters!B16*POWER(Parameters!$B$8,$C$31) -> 6.4905754e+09 | AE33: =$AE$31*Parameters!E16 -> 3.8298857e+09 | AF33: =AD33+AE33-X33 -> 9.0955232e+09 | AG33: =AD33+AE33-AA33 -> 1.0024449e+10 | AH33: =($AB$31+$I$31)/10 -> 412245.68 | AI33: =AF33/AH33 -> 22063.356 | AK33: =AG33/AH33 -> 24316.687 | AM33: =(POWER(AI33, -0.26) - 1)/-0.26 -> 3.5606105 | AN33: =(AM33-$AM$18)*100 -> 12.51071 | AO33: =LOG(AI33) -> 4.3436716 | AP33: =(POWER(AK33, -0.26) - 1)/-0.26 -> 3.5677396 | AQ33: =(AP33-$AP$18)*100 -> 12.570809 | AR33: =LOG(AK33) -> 4.3859044 | AT33: 1.886958 | AX33: =SQRT(AO33) -> 2.0841477 | BB33: 1.8888461 | BF33: =SQRT(AR33) -> 2.0942551
A34: 3 | N34: =$N$31*Parameters!E17 -> 3.4043429e+09 | V34: =Parameters!C17 -> 0.031399077 | W34: =(V34*$U$31)/(Parameters!B17*POWER(Parameters!$B$8,$C$31)) -> 0.19730406 | X34: =$U$31*V34 -> 2.6707745e+09 | Y34: =Parameters!D17 -> 0.010886748 | Z34: =(Y34*$U$31)/(Parameters!B17*POWER(Parameters!$B$8,$C$31)) -> 0.068409644 | AA34: =$U$31*Y34 -> 9.2601605e+08 | AD34: =Parameters!B17*POWER(Parameters!$B$8,$C$31) -> 1.3536338e+10 | AE34: =$AE$31*Parameters!E17 -> 3.4043429e+09 | AF34: =AD34+AE34-X34 -> 1.4269906e+10 | AG34: =AD34+AE34-AA34 -> 1.6014665e+10 | AH34: =($AB$31+$I$31)/10 -> 412245.68 | AI34: =AF34/AH34 -> 34615.053 | AK34: =AG34/AH34 -> 38847.38 | AM34: =(POWER(AI34, -0.26) - 1)/-0.26 -> 3.5921632 | AN34: =(AM34-$AM$18)*100 -> 15.665978 | AO34: =LOG(AI34) -> 4.539265 | AP34: =(POWER(AK34, -0.26) - 1)/-0.26 -> 3.5996677 | AQ34: =(AP34-$AP$18)*100 -> 15.763618 | AR34: =LOG(AK34) -> 4.5893617 | AT34: 1.8953003 | AX34: =SQRT(AO34) -> 2.1305551 | BB34: 1.897279 | BF34: =SQRT(AR34) -> 2.1422796
A35: 4 | N35: =$N$31*Parameters!E18 -> 2.9788e+09 | V35: =Parameters!C18 -> 0.051692243 | W35: =(V35*$U$31)/(Parameters!B18*POWER(Parameters!$B$8,$C$31)) -> 0.2058825 | X35: =$U$31*V35 -> 4.396891e+09 | Y35: =Parameters!D18 -> 0.022901399 | Z35: =(Y35*$U$31)/(Parameters!B18*POWER(Parameters!$B$8,$C$31)) -> 0.091212859 | AA35: =$U$31*Y35 -> 1.9479703e+09 | AD35: =Parameters!B18*POWER(Parameters!$B$8,$C$31) -> 2.1356313e+10 | AE35: =$AE$31*Parameters!E18 -> 2.9788e+09 | AF35: =AD35+AE35-X35 -> 1.9938221e+10 | AG35: =AD35+AE35-AA35 -> 2.2387142e+10 | AH35: =($AB$31+$I$31)/10 -> 412245.68 | AI35: =AF35/AH35 -> 48364.901 | AK35: =AG35/AH35 -> 54305.341 | AM35: =(POWER(AI35, -0.26) - 1)/-0.26 -> 3.6133186 | AN35: =(AM35-$AM$18)*100 -> 17.781517 | AO35: =LOG(AI35) -> 4.6845303 | AP35: =(POWER(AK35, -0.26) - 1)/-0.26 -> 3.6202271 | AQ35: =(AP35-$AP$18)*100 -> 17.819565 | AR35: =LOG(AK35) -> 4.7348425 | AT35: 1.9008731 | AX35: =SQRT(AO35) -> 2.1643776 | BB35: 1.9026894 | BF35: =SQRT(AR35) -> 2.1759693
A36: 5 | N36: =$N$31*Parameters!E19 -> 2.5532571e+09 | V36: =Parameters!C19 -> 0.070583126 | W36: =(V36*$U$31)/(Parameters!B19*POWER(Parameters!$B$8,$C$31)) -> 0.21446094 | X36: =$U$31*V36 -> 6.0037309e+09 | Y36: =Parameters!D19 -> 0.037524833 | Z36: =(Y36*$U$31)/(Parameters!B19*POWER(Parameters!$B$8,$C$31)) -> 0.11401607 | AA36: =$U$31*Y36 -> 3.1918252e+09 | AD36: =Parameters!B19*POWER(Parameters!$B$8,$C$31) -> 2.7994519e+10 | AF36: =AD36+AE36-X36 -> 2.1990788e+10 | AG36: =AD36+AE36-AA36 -> 2.4802694e+10 | AH36: =($AB$31+$I$31)/10 -> 412245.68 | AI36: =AF36/AH36 -> 53343.89 | AK36: =AG36/AH36 -> 60164.837 | AM36: =(POWER(AI36, -0.26) - 1)/-0.26 -> 3.6191754 | AN36: =(AM36-$AM$18)*100 -> 18.367199 | AO36: =LOG(AI36) -> 4.7270847 | AP36: =(POWER(AK36, -0.26) - 1)/-0.26 -> 3.6261666 | AQ36: =(AP36-$AP$18)*100 -> 18.413511 | AR36: =LOG(AK36) -> 4.7793427 | AT36: 1.902413 | AX36: =SQRT(AO36) -> 2.174186 | BB36: 1.9042496 | BF36: =SQRT(AR36) -> 2.1861708
A37: 6 | N37: =$N$31*Parameters!E20 -> 2.1277143e+09 | V37: =Parameters!C20 -> 0.090905111 | W37: =(V37*$U$31)/(Parameters!B20*POWER(Parameters!$B$8,$C$31)) -> 0.23161781 | X37: =$U$31*V37 -> 7.7322988e+09 | Y37: =Parameters!D20 -> 0.053698687 | Z37: =(Y37*$U$31)/(Parameters!B20*POWER(Parameters!$B$8,$C$31)) -> 0.13681929 | AA37: =$U$31*Y37 -> 4.5675572e+09 | AD37: =Parameters!B20*POWER(Parameters!$B$8,$C$31) -> 3.3383869e+10 | AF37: =AD37+AE37-X37 -> 2.565157e+10 | AG37: =AD37+AE37-AA37 -> 2.8816312e+10 | AH37: =($AB$31+$I$31)/10 -> 412245.68 | AI37: =AF37/AH37 -> 62223.988 | AK37: =AG37/AH37 -> 69900.822 | AM37: =(POWER(AI37, -0.26) - 1)/-0.26 -> 3.628083 | AN37: =(AM37-$AM$18)*100 -> 19.25796 | AO37: =LOG(AI37) -> 4.7939578 | AP37: =(POWER(AK37, -0.26) - 1)/-0.26 -> 3.6345804 | AQ37: =(AP37-$AP$18)*100 -> 19.254888 | AR37: =LOG(AK37) -> 4.8444823 | AT37: 1.9047527 | AX37: =SQRT(AO37) -> 2.1895109 | BB37: 1.9064575 | BF37: =SQRT(AR37) -> 2.2010185
A38: 7 | N38: =$N$31*Parameters!E21 -> 1.7021714e+09 | V38: =Parameters!C21 -> 0.11035602 | W38: =(V38*$U$31)/(Parameters!B21*POWER(Parameters!$B$8,$C$31)) -> 0.24019625 | X38: =$U$31*V38 -> 9.3867742e+09 | Y38: =Parameters!D21 -> 0.083813868 | Z38: =(Y38*$U$31)/(Parameters!B21*POWER(Parameters!$B$8,$C$31)) -> 0.18242572 | AA38: =$U$31*Y38 -> 7.1291247e+09 | AD38: =Parameters!B21*POWER(Parameters!$B$8,$C$31) -> 3.9079603e+10 | AF38: =AD38+AE38-X38 -> 2.9692829e+10 | AG38: =AD38+AE38-AA38 -> 3.1950479e+10 | AH38: =($AB$31+$I$31)/10 -> 412245.68 | AI38: =AF38/AH38 -> 72027.023 | AK38: =AG38/AH38 -> 77503.489 | AM38: =(POWER(AI38, -0.26) - 1)/-0.26 -> 3.6362222 | AN38: =(AM38-$AM$18)*100 -> 20.071884 | AO38: =LOG(AI38) -> 4.8574955 | AP38: =(POWER(AK38, -0.26) - 1)/-0.26 -> 3.6401842 | AQ38: =(AP38-$AP$18)*100 -> 19.815277 | AR38: =LOG(AK38) -> 4.8893213 | AT38: 1.9068881 | AX38: =SQRT(AO38) -> 2.2039727 | BB38: 1.9079267 | BF38: =SQRT(AR38) -> 2.211181
A39: 8 | N39: =$N$31*Parameters!E22 -> 1.2766286e+09 | V39: =Parameters!C22 -> 0.13623162 | W39: =(V39*$U$31)/(Parameters!B22*POWER(Parameters!$B$8,$C$31)) -> 0.24877469 | X39: =$U$31*V39 -> 1.1587726e+10 | Y39: =Parameters!D22 -> 0.13736006 | Z39: =(Y39*$U$31)/(Parameters!B22*POWER(Parameters!$B$8,$C$31)) -> 0.25083536 | AA39: =$U$31*Y39 -> 1.1683711e+10 | AD39: =Parameters!B22*POWER(Parameters!$B$8,$C$31) -> 4.6579202e+10 | AF39: =AD39+AE39-X39 -> 3.4991476e+10 | AG39: =AD39+AE39-AA39 -> 3.4895491e+10 | AH39: =($AB$31+$I$31)/10 -> 412245.68 | AI39: =AF39/AH39 -> 84880.151 | AK39: =AG39/AH39 -> 84647.318 | AM39: =(POWER(AI39, -0.26) - 1)/-0.26 -> 3.644996 | AN39: =(AM39-$AM$18)*100 -> 20.949256 | AO39: =LOG(AI39) -> 4.9288061 | AP39: =(POWER(AK39, -0.26) - 1)/-0.26 -> 3.6448522 | AQ39: =(AP39-$AP$18)*100 -> 20.282077 | AR39: =LOG(AK39) -> 4.9276132 | AT39: 1.9091873 | AX39: =SQRT(AO39) -> 2.2200915 | BB39: 1.9091496 | BF39: =SQRT(AR39) -> 2.2198228
A40: 9 | N40: =$N$31*Parameters!E23 -> 8.5108572e+08 | V40: =Parameters!C23 -> 0.17539672 | W40: =(V40*$U$31)/(Parameters!B23*POWER(Parameters!$B$8,$C$31)) -> 0.25735313 | X40: =$U$31*V40 -> 1.4919072e+10 | Y40: =Parameters!D23 -> 0.21757858 | Z40: =(Y40*$U$31)/(Parameters!B23*POWER(Parameters!$B$8,$C$31)) -> 0.31924501 | AA40: =$U$31*Y40 -> 1.8507019e+10 | AD40: =Parameters!B23*POWER(Parameters!$B$8,$C$31) -> 5.7971209e+10 | AF40: =AD40+AE40-X40 -> 4.3052137e+10 | AG40: =AD40+AE40-AA40 -> 3.946419e+10 | AH40: =($AB$31+$I$31)/10 -> 412245.68 | AI40: =AF40/AH40 -> 104433.2 | AK40: =AG40/AH40 -> 95729.784 | AM40: =(POWER(AI40, -0.26) - 1)/-0.26 -> 3.6555513 | AN40: =(AM40-$AM$18)*100 -> 22.004793 | AO40: =LOG(AI40) -> 5.0188386 | AP40: =(POWER(AK40, -0.26) - 1)/-0.26 -> 3.6511899 | AQ40: =(AP40-$AP$18)*100 -> 20.915838 | AR40: =LOG(AK40) -> 4.9810471 | AT40: 1.9119496 | AX40: =SQRT(AO40) -> 2.2402765 | BB40: 1.9108087 | BF40: =SQRT(AR40) -> 2.231826
A41: 10 | N41: =$N$31*Parameters!E24 -> 4.2554286e+08 | V41: =Parameters!C24 -> 0.3154254 | W41: =(V41*$U$31)/(Parameters!B24*POWER(Parameters!$B$8,$C$31)) -> 0.26593156 | X41: =$U$31*V41 -> 2.6829773e+10 | Y41: =Parameters!D24 -> 0.43275574 | Z41: =(Y41*$U$31)/(Parameters!B24*POWER(Parameters!$B$8,$C$31)) -> 0.36485144 | AA41: =$U$31*Y41 -> 3.6809775e+10 | AD41: =Parameters!B24*POWER(Parameters!$B$8,$C$31) -> 1.0088976e+11 | AF41: =AD41+AE41-X41 -> 7.4059991e+10 | AG41: =AD41+AE41-AA41 -> 6.4079989e+10 | AH41: =($AB$31+$I$31)/10 -> 412245.68 | AI41: =AF41/AH41 -> 179650.13 | AK41: =AG41/AH41 -> 155441.26 | AM41: =(POWER(AI41, -0.26) - 1)/-0.26 -> 3.6806243 | AN41: =(AM41-$AM$18)*100 -> 24.512091 | AO41: =LOG(AI41) -> 5.2544275 | AP41: =(POWER(AK41, -0.26) - 1)/-0.26 -> 3.6742762 | AQ41: =(AP41-$AP$18)*100 -> 23.224472 | AR41: =LOG(AK41) -> 5.1915663 | AT41: 1.9184953 | AX41: =SQRT(AO41) -> 2.2922538 | BB41: 1.9168402 | BF41: =SQRT(AR41) -> 2.2785009
A44: Only the bottom four deciles get NZS
A45: Sensitivity check

Sheet Income means-test 3 deciles
A1: Decile | B1: Year | D1: NZS income per recipient | V1: Baseline tax | Y1: Progressive tax | AB1: Size tax paying group by income group | AD1: Gross income | AF1: Net Income baseline tax | AG1: Net income Progressive | AH1: Quintile size | AI1: Average income pp baseline tax | AJ1: Average income pp progressive | AK1: Utility score baseline tax | AO1: Utility score progressive | AS1: Welfare score baseline tax isoelastic utility | AW1: Welfare score baseline tax log utility | BA1: Welfare score progressive tax isoelastic utility | BE1: Welfare score progressive tax log utility | BI1: Adjusted scores prioritarian welfare p = 2
B2: Year | C2: Years since base | D2: Base year annual rate singles | E2: Base year annual rate couples | F2: Mulitplier | G2: Current year real rate singles | H2: Current year annual rate couples | I2: 65+ employed population current year | J2: Single | K2: In a relationship | L2: NZS paid singles rate | M2: NZS paid couples rate | N2: NZS paid total to employed 65+ | O2: Total 65+ population | P2: Single | Q2: In a relationship | R2: NZS paid singles rate | S2: NZS paid couples rate | T2: NZS paid total to 65+ | U2: NZS paid total after means test | V2: Revenue share | W2: Implied average tax rate | X2: Decile NZS cost | Y2: Revenue share | Z2: Implied average tax rate | AA2: Decile NZS cost | AB2: Employed working age pop current year | AC2: Total tax paying population | AD2: Employment income | AE2: Pension income | AF2: Total income | AG2: Total income | AK2: Isoelastic p = 1.26 | AL2: Isoelastic p = 1.26 normalised | AM2: Isoelastic p = 2 | AN2: Isoelsatic p = 1 | AO2: Isoelastic p = 1.26 | AP2: Isoelastic p = 1.26 normalised | AQ2: Isoelastic p = 2 | AR2: Isoelsatic p = 1 | AS2: Utilitarian | AT2: Adjusted score | AU2: Prioritarian | AV2: Maximin | AW2: Utilitarian | AX2: Adjusted score | AY2: Prioritarian | AZ2: Maximin | BA2: Utilitarian | BB2: Adjusted score | BC2: Prioritarian | BD2: Maximin | BE2: Utilitarian | BF2: Adjusted score | BG2: Prioritarian | BH2: Maximin | BI2: Baseline | BJ2: Progressive
A3: Overall | B3: 2026 | C3: 2 | D3: =Parameters!$B$4 -> 27012.44 | E3: =Parameters!$B$5 -> 20778.68 | F3: =Parameters!$B$8 -> 1.01088 | G3: =D3*POWER(F3,C3) -> 27603.428 | H3: =E3*POWER(F3,C3) -> 21233.284 | I3: =Parameters!B3*Parameters!B39 -> 232117.8 | J3: =I3*Parameters!$B$10 -> 97489.476 | K3: =I3*Parameters!$B$9 -> 134628.32 | L3: =J3*G3 -> 2.6910438e+09 | M3: =K3*H3 -> 2.8586014e+09 | N3: =M3+L3 -> 5.5496452e+09 | O3: =Parameters!B39 -> 932200 | P3: =O3*Parameters!$B$10 -> 391524 | Q3: =O3*Parameters!$B$9 -> 540676 | R3: =P3*G3 -> 1.0807405e+10 | S3: =Q3*H3 -> 1.1480327e+10 | T3: =S3+R3 -> 2.2287732e+10 | U3: =T3-SUM(N7:N13) -> 1.9462458e+10 | AA3: =SUM(AA4:AA13) -> 1.9462458e+10 | AB3: =Parameters!C39*Parameters!B2 -> 2728423.5 | AC3: =AB3+I3 -> 2960541.3 | AD3: =SUM(AD4:AD13) -> 1.9865009e+11 | AE3: =N3 -> 5.5496452e+09 | AF3: =AD3+AE3-X3 -> 2.0419974e+11 | AG3: =AD3+AE3-AA3 -> 1.8473728e+11 | AI3: post-NZS | AJ3: post-NZS | AM3: Sensitivity check | AN3: Sensitivity check | AQ3: Sensitivity check | AR3: Sensitivity check | AS3: =SUM(AK4:AK13) -> 35.991271 | AU3: =SUM(AT4:AT13) -> 18.970573 | AV3: =MIN(AK5:AK13) -> 3.5283064 | AW3: =SUM(AN4:AN13) -> 46.37589 | AY3: =SUM(AX4:AX13) -> 21.513718 | AZ3: =MIN(AN5:AN13) -> 4.1646458 | BA3: =SUM(AO4:AO13) -> 36.008792 | BC3: =SUM(BB4:BB13) -> 18.97523 | BD3: =MIN(AO5:AO13) -> 3.5322461 | BE3: =SUM(AR4:AR13) -> 46.471706 | BG3: =SUM(BF3:BF13) -> 21.537019 | BH3: =MIN(AR5:AR13) -> 4.1854795
A4: 1 | N4: =$N$3*Parameters!E15 -> 1.0090264e+09 | V4: =Parameters!C15 -> 0.0036096394 | W4: =(V4*$U$3)/(Parameters!B15*POWER(Parameters!$B$8, $C$3)) -> 0.086140022 | X4: =$U$3*V4 -> 70252453 | Y4: {=Parameters!D15:D24} -> 0 | Z4: =(Y4*$U$3)/(Parameters!B15*POWER(Parameters!$B$8, $C$3)) -> 0 | AA4: =$U$3*Y4 -> 0 | AD4: =Parameters!B15*POWER(Parameters!$B$8,$C$3) -> 8.1556113e+08 | AE4: =$AE$3*Parameters!E15 -> 1.0090264e+09 | AF4: =AD4+AE4-X4 -> 1.7543351e+09 | AG4: =AD4+AE4-AA4 -> 1.8245875e+09 | AH4: =($AB$3+$I$3)/10 -> 296054.13 | AI4: =AF4/AH4 -> 5925.724 | AJ4: =AG4/AH4 -> 6163.02 | AK4: =(POWER(AI4, -0.26) - 1)/-0.26 -> 3.4442577 | AL4: =(AK4-$AK$4)*100 -> 0 | AM4: =(POWER(AI4, -1) - 1)/-1 -> 0.99983124 | AN4: =LOG(AI4) -> 3.7727414 | AO4: =(POWER(AJ4, -0.26) - 1)/-0.26 -> 3.4483396 | AP4: =(AO4-$AO$4)*100 -> 0 | AQ4: =(POWER(AJ4, -1) - 1)/-1 -> 0.99983774 | AR4: =LOG(AJ4) -> 3.7897936 | AT4: =SQRT(AK4) -> 1.8558711 | AX4: =SQRT(AN4) -> 1.9423546 | BB4: {=SQRT(AO4:AO13)} -> 1.8569705 | BF4: =SQRT(AR4) -> 1.9467392 | BI4: =SQRT(AM4) -> 0.99991562 | BJ4: =SQRT(AQ4) -> 0.99991887
A5: 2 | N5: =$N$3*Parameters!E16 -> 9.0812375e+08 | V5: =Parameters!C16 -> 0.014401036 | W5: =(V5*$U$3)/(Parameters!B16*POWER(Parameters!$B$8, $C$3)) -> 0.075803219 | X5: =$U$3*V5 -> 2.8027956e+08 | Y5: 0.0034800777 | Z5: =(Y5*$U$3)/(Parameters!B16*POWER(Parameters!$B$8, $C$3)) -> 0.018318202 | AA5: =$U$3*Y5 -> 67730866 | AD5: =Parameters!B16*POWER(Parameters!$B$8,$C$3) -> 3.6974625e+09 | AE5: =$AE$3*Parameters!E16 -> 9.0812375e+08 | AF5: =AD5+AE5-X5 -> 4.3253067e+09 | AG5: =AD5+AE5-AA5 -> 4.5378554e+09 | AH5: =($AB$3+$I$3)/10 -> 296054.13 | AI5: =AF5/AH5 -> 14609.851 | AJ5: =AG5/AH5 -> 15327.79 | AK5: =(POWER(AI5, -0.26) - 1)/-0.26 -> 3.5283064 | AL5: =(AK5-$AK$4)*100 -> 8.4048722 | AM5: =(POWER(AI5, -1) - 1)/-1 -> 0.99993155 | AN5: =LOG(AI5) -> 4.1646458 | AO5: =(POWER(AJ5, -0.26) - 1)/-0.26 -> 3.5322461 | AP5: =(AO5-$AO$4)*100 -> 8.3906533 | AQ5: =(POWER(AJ5, -1) - 1)/-1 -> 0.99993476 | AR5: =LOG(AJ5) -> 4.1854795 | AT5: =SQRT(AK5) -> 1.8783787 | AX5: =SQRT(AN5) -> 2.0407464 | BB5: 1.8794271 | BF5: =SQRT(AR5) -> 2.0458445 | BI5: =SQRT(AM5) -> 0.99996578 | BJ5: =SQRT(AQ5) -> 0.99996738
A6: 3 | N6: =$N$3*Parameters!E17 -> 8.0722111e+08 | V6: =Parameters!C17 -> 0.031399077 | W6: =(V6*$U$3)/(Parameters!B17*POWER(Parameters!$B$8, $C$3)) -> 0.07924882 | X6: =$U$3*V6 -> 6.1110321e+08 | Y6: 0.010886748 | Z6: =(Y6*$U$3)/(Parameters!B17*POWER(Parameters!$B$8, $C$3)) -> 0.027477303 | AA6: =$U$3*Y6 -> 2.1188288e+08 | AD6: =Parameters!B17*POWER(Parameters!$B$8,$C$3) -> 7.7111964e+09 | AE6: =$AE$3*Parameters!E17 -> 8.0722111e+08 | AF6: =AD6+AE6-X6 -> 7.9073143e+09 | AG6: =AD6+AE6-AA6 -> 8.3065346e+09 | AH6: =($AB$3+$I$3)/10 -> 296054.13 | AI6: =AF6/AH6 -> 26709.015 | AJ6: =AG6/AH6 -> 28057.486 | AK6: =(POWER(AI6, -0.26) - 1)/-0.26 -> 3.5744501 | AL6: =(AK6-$AK$4)*100 -> 13.019245 | AM6: =(POWER(AI6, -1) - 1)/-1 -> 0.99996256 | AN6: =LOG(AI6) -> 4.4266579 | AO6: =(POWER(AJ6, -0.26) - 1)/-0.26 -> 3.5779074 | AP6: =(AO6-$AO$4)*100 -> 12.956779 | AQ6: =(POWER(AJ6, -1) - 1)/-1 -> 0.99996436 | AR6: =LOG(AJ6) -> 4.4480488 | AT6: =SQRT(AK6) -> 1.8906216 | AX6: =SQRT(AN6) -> 2.1039624 | BB6: 1.8915357 | BF6: =SQRT(AR6) -> 2.1090398 | BI6: =SQRT(AM6) -> 0.99998128 | BJ6: =SQRT(AQ6) -> 0.99998218
A7: 4 | N7: =$N$3*Parameters!E18 -> 7.0631848e+08 | V7: =Parameters!C18 -> 0.051692243 | W7: =(V7*$U$3)/(Parameters!B18*POWER(Parameters!$B$8, $C$3)) -> 0.082694421 | X7: =$U$3*V7 -> 1.0060581e+09 | Y7: 0.022901399 | Z7: =(Y7*$U$3)/(Parameters!B18*POWER(Parameters!$B$8, $C$3)) -> 0.036636404 | AA7: =$U$3*Y7 -> 4.457175e+08 | AD7: =Parameters!B18*POWER(Parameters!$B$8,$C$3) -> 1.2165973e+10 | AF7: =AD7+AE7-X7 -> 1.1159915e+10 | AG7: =AD7+AE7-AA7 -> 1.1720255e+10 | AH7: =($AB$3+$I$3)/10 -> 296054.13 | AI7: =AF7/AH7 -> 37695.522 | AJ7: =AG7/AH7 -> 39588.218 | AK7: =(POWER(AI7, -0.26) - 1)/-0.26 -> 3.5977311 | AL7: =(AK7-$AK$4)*100 -> 15.347346 | AM7: =(POWER(AI7, -1) - 1)/-1 -> 0.99997347 | AN7: =LOG(AI7) -> 4.5762898 | AO7: =(POWER(AJ7, -0.26) - 1)/-0.26 -> 3.6008753 | AP7: =(AO7-$AO$4)*100 -> 15.253572 | AQ7: =(POWER(AJ7, -1) - 1)/-1 -> 0.99997474 | AR7: =LOG(AJ7) -> 4.597566 | AT7: =SQRT(AK7) -> 1.8967686 | AX7: =SQRT(AN7) -> 2.1392264 | BB7: 1.8975973 | BF7: =SQRT(AR7) -> 2.1441935 | BI7: =SQRT(AM7) -> 0.99998674 | BJ7: =SQRT(AQ7) -> 0.99998737
A8: 5 | N8: =$N$3*Parameters!E19 -> 6.0541584e+08 | V8: =Parameters!C19 -> 0.070583126 | W8: =(V8*$U$3)/(Parameters!B19*POWER(Parameters!$B$8, $C$3)) -> 0.086140022 | X8: =$U$3*V8 -> 1.3737211e+09 | Y8: 0.037524833 | Z8: =(Y8*$U$3)/(Parameters!B19*POWER(Parameters!$B$8, $C$3)) -> 0.045795505 | AA8: =$U$3*Y8 -> 7.3032547e+08 | AD8: =Parameters!B19*POWER(Parameters!$B$8,$C$3) -> 1.5947536e+10 | AF8: =AD8+AE8-X8 -> 1.4573815e+10 | AG8: =AD8+AE8-AA8 -> 1.5217211e+10 | AH8: =($AB$3+$I$3)/10 -> 296054.13 | AI8: =AF8/AH8 -> 49226.859 | AJ8: =AG8/AH8 -> 51400.096 | AK8: =(POWER(AI8, -0.26) - 1)/-0.26 -> 3.6143855 | AL8: =(AK8-$AK$4)*100 -> 17.012785 | AM8: =(POWER(AI8, -1) - 1)/-1 -> 0.99997969 | AN8: =LOG(AI8) -> 4.6922021 | AO8: =(POWER(AJ8, -0.26) - 1)/-0.26 -> 3.6169742 | AP8: =(AO8-$AO$4)*100 -> 16.86346 | AQ8: =(POWER(AJ8, -1) - 1)/-1 -> 0.99998054 | AR8: =LOG(AJ8) -> 4.7109639 | AT8: =SQRT(AK8) -> 1.9011537 | AX8: =SQRT(AN8) -> 2.1661491 | BB8: 1.9018344 | BF8: =SQRT(AR8) -> 2.1704755 | BI8: =SQRT(AM8) -> 0.99998984 | BJ8: =SQRT(AQ8) -> 0.99999027
A9: 6 | N9: =$N$3*Parameters!E20 -> 5.045132e+08 | V9: =Parameters!C20 -> 0.090905111 | W9: =(V9*$U$3)/(Parameters!B20*POWER(Parameters!$B$8, $C$3)) -> 0.093031223 | X9: =$U$3*V9 -> 1.7692369e+09 | Y9: 0.053698687 | Z9: =(Y9*$U$3)/(Parameters!B20*POWER(Parameters!$B$8, $C$3)) -> 0.054954606 | AA9: =$U$3*Y9 -> 1.0451084e+09 | AD9: =Parameters!B20*POWER(Parameters!$B$8,$C$3) -> 1.9017667e+10 | AF9: =AD9+AE9-X9 -> 1.7248431e+10 | AG9: =AD9+AE9-AA9 -> 1.7972559e+10 | AH9: =($AB$3+$I$3)/10 -> 296054.13 | AI9: =AF9/AH9 -> 58261.071 | AJ9: =AG9/AH9 -> 60707.003 | AK9: =(POWER(AI9, -0.26) - 1)/-0.26 -> 3.6243198 | AL9: =(AK9-$AK$4)*100 -> 18.006211 | AM9: =(POWER(AI9, -1) - 1)/-1 -> 0.99998284 | AN9: =LOG(AI9) -> 4.7653785 | AO9: =(POWER(AJ9, -0.26) - 1)/-0.26 -> 3.6266791 | AP9: =(AO9-$AO$4)*100 -> 17.833949 | AQ9: =(POWER(AJ9, -1) - 1)/-1 -> 0.99998353 | AR9: =LOG(AJ9) -> 4.7832388 | AT9: =SQRT(AK9) -> 1.9037646 | AX9: =SQRT(AN9) -> 2.1829747 | BB9: 1.9043842 | BF9: =SQRT(AR9) -> 2.1870617 | BI9: =SQRT(AM9) -> 0.99999142 | BJ9: =SQRT(AQ9) -> 0.99999176
A10: 7 | N10: =$N$3*Parameters!E21 -> 4.0361056e+08 | V10: =Parameters!C21 -> 0.11035602 | W10: =(V10*$U$3)/(Parameters!B21*POWER(Parameters!$B$8, $C$3)) -> 0.096476824 | X10: =$U$3*V10 -> 2.1477994e+09 | Y10: 0.083813868 | Z10: =(Y10*$U$3)/(Parameters!B21*POWER(Parameters!$B$8, $C$3)) -> 0.073272809 | AA10: =$U$3*Y10 -> 1.6312239e+09 | AD10: =Parameters!B21*POWER(Parameters!$B$8,$C$3) -> 2.2262336e+10 | AF10: =AD10+AE10-X10 -> 2.0114536e+10 | AG10: =AD10+AE10-AA10 -> 2.0631112e+10 | AH10: =($AB$3+$I$3)/10 -> 296054.13 | AI10: =AF10/AH10 -> 67942.09 | AJ10: =AG10/AH10 -> 69686.958 | AK10: =(POWER(AI10, -0.26) - 1)/-0.26 -> 3.6330111 | AL10: =(AK10-$AK$4)*100 -> 18.875345 | AM10: =(POWER(AI10, -1) - 1)/-1 -> 0.99998528 | AN10: =LOG(AI10) -> 4.8321389 | AO10: =(POWER(AJ10, -0.26) - 1)/-0.26 -> 3.6344117 | AP10: =(AO10-$AO$4)*100 -> 18.607212 | AQ10: =(POWER(AJ10, -1) - 1)/-1 -> 0.99998565 | AR10: =LOG(AJ10) -> 4.8431515 | AT10: =SQRT(AK10) -> 1.9060459 | AX10: =SQRT(AN10) -> 2.1982127 | BB10: 1.9064133 | BF10: =SQRT(AR10) -> 2.2007161 | BI10: =SQRT(AM10) -> 0.99999264 | BJ10: =SQRT(AQ10) -> 0.99999283
A11: 8 | N11: =$N$3*Parameters!E22 -> 3.0270792e+08 | V11: =Parameters!C22 -> 0.13623162 | W11: =(V11*$U$3)/(Parameters!B22*POWER(Parameters!$B$8, $C$3)) -> 0.099922425 | X11: =$U$3*V11 -> 2.6514021e+09 | Y11: 0.13736006 | Z11: =(Y11*$U$3)/(Parameters!B22*POWER(Parameters!$B$8, $C$3)) -> 0.10075011 | AA11: =$U$3*Y11 -> 2.6733644e+09 | AD11: =Parameters!B22*POWER(Parameters!$B$8,$C$3) -> 2.6534605e+10 | AF11: =AD11+AE11-X11 -> 2.3883203e+10 | AG11: =AD11+AE11-AA11 -> 2.386124e+10 | AH11: =($AB$3+$I$3)/10 -> 296054.13 | AI11: =AF11/AH11 -> 80671.743 | AJ11: =AG11/AH11 -> 80597.56 | AK11: =(POWER(AI11, -0.26) - 1)/-0.26 -> 3.6423187 | AL11: =(AK11-$AK$4)*100 -> 19.806103 | AM11: =(POWER(AI11, -1) - 1)/-1 -> 0.9999876 | AN11: =LOG(AI11) -> 4.9067214 | AO11: =(POWER(AJ11, -0.26) - 1)/-0.26 -> 3.6422699 | AP11: =(AO11-$AO$4)*100 -> 19.393032 | AQ11: =(POWER(AJ11, -1) - 1)/-1 -> 0.99998759 | AR11: =LOG(AJ11) -> 4.9063219 | AT11: =SQRT(AK11) -> 1.908486 | AX11: =SQRT(AN11) -> 2.2151121 | BB11: 1.9084732 | BF11: =SQRT(AR11) -> 2.2150219 | BI11: =SQRT(AM11) -> 0.9999938 | BJ11: =SQRT(AQ11) -> 0.9999938
A12: 9 | N12: =$N$3*Parameters!E23 -> 2.0180528e+08 | V12: =Parameters!C23 -> 0.17539672 | W12: =(V12*$U$3)/(Parameters!B23*POWER(Parameters!$B$8, $C$3)) -> 0.10336803 | X12: =$U$3*V12 -> 3.4136513e+09 | Y12: 0.21757858 | Z12: =(Y12*$U$3)/(Parameters!B23*POWER(Parameters!$B$8, $C$3)) -> 0.12822742 | AA12: =$U$3*Y12 -> 4.2346139e+09 | AD12: =Parameters!B23*POWER(Parameters!$B$8,$C$3) -> 3.3024248e+10 | AF12: =AD12+AE12-X12 -> 2.9610596e+10 | AG12: =AD12+AE12-AA12 -> 2.8789634e+10 | AH12: =($AB$3+$I$3)/10 -> 296054.13 | AI12: =AF12/AH12 -> 100017.51 | AJ12: =AG12/AH12 -> 97244.493 | AK12: =(POWER(AI12, -0.26) - 1)/-0.26 -> 3.6533983 | AL12: =(AK12-$AK$4)*100 -> 20.914064 | AM12: =(POWER(AI12, -1) - 1)/-1 -> 0.99999 | AN12: =LOG(AI12) -> 5.000076 | AO12: =(POWER(AJ12, -0.26) - 1)/-0.26 -> 3.651984 | AP12: =(AO12-$AO$4)*100 -> 20.364441 | AQ12: =(POWER(AJ12, -1) - 1)/-1 -> 0.99998972 | AR12: =LOG(AJ12) -> 4.987865 | AT12: =SQRT(AK12) -> 1.9113865 | AX12: =SQRT(AN12) -> 2.236085 | BB12: 1.9110165 | BF12: =SQRT(AR12) -> 2.2333529 | BI12: =SQRT(AM12) -> 0.999995 | BJ12: =SQRT(AQ12) -> 0.99999486
A13: 10 | N13: =$N$3*Parameters!E24 -> 1.0090264e+08 | V13: =Parameters!C24 -> 0.3154254 | W13: =(V13*$U$3)/(Parameters!B24*POWER(Parameters!$B$8, $C$3)) -> 0.10681363 | X13: =$U$3*V13 -> 6.1389536e+09 | Y13: 0.43275574 | Z13: =(Y13*$U$3)/(Parameters!B24*POWER(Parameters!$B$8, $C$3)) -> 0.14654562 | AA13: =$U$3*Y13 -> 8.4224903e+09 | AD13: =Parameters!B24*POWER(Parameters!$B$8,$C$3) -> 5.7473505e+10 | AF13: =AD13+AE13-X13 -> 5.1334552e+10 | AG13: =AD13+AE13-AA13 -> 4.9051015e+10 | AH13: =($AB$3+$I$3)/10 -> 296054.13 | AI13: =AF13/AH13 -> 173395.83 | AJ13: =AG13/AH13 -> 165682.59 | AK13: =(POWER(AI13, -0.26) - 1)/-0.26 -> 3.6790923 | AL13: =(AK13-$AK$4)*100 -> 23.48346 | AM13: =(POWER(AI13, -1) - 1)/-1 -> 0.99999423 | AN13: =LOG(AI13) -> 5.2390387 | AO13: =(POWER(AJ13, -0.26) - 1)/-0.26 -> 3.677104 | AP13: =(AO13-$AO$4)*100 -> 22.876444 | AQ13: =(POWER(AJ13, -1) - 1)/-1 -> 0.99999396 | AR13: =LOG(AJ13) -> 5.2192769 | AT13: =SQRT(AK13) -> 1.918096 | AX13: =SQRT(AN13) -> 2.2888946 | BB13: 1.9175777 | BF13: =SQRT(AR13) -> 2.2845737 | BI13: =SQRT(AM13) -> 0.99999712 | BJ13: =SQRT(AQ13) -> 0.99999698
A15: Decile | B15: Year | D15: NZS income per recipient | V15: Baseline tax | Y15: Progressive tax | AB15: Size tax paying group by income group | AD15: Gross income | AF15: Net Income baseline tax | AG15: Net income Progressive | AH15: Quintile size | AI15: Average income pp baseline tax | AJ15: Average income pp progressive | AK15: Utility score baseline tax | AO15: Utility score progressive | AS15: Welfare score baseline tax isoelastic utility | AW15: Welfare score baseline tax log utility | BA15: Welfare score progressive tax isoelastic utility | BE15: Welfare score progressive tax log utility
B16: Year | C16: Years since base | D16: Base year annual rate singles | E16: Base year annual rate couples | F16: Mulitplier | G16: Current year real rate singles | H16: Current year annual rate couples | I16: 65+ employed population current year | J16: Single | K16: In a relationship | L16: NZS paid singles rate | M16: NZS paid couples rate | N16: NZS paid total to employed 65+ | O16: Total 65+ population | P16: Single | Q16: In a relationship | R16: NZS paid singles rate | S16: NZS paid couples rate | T16: NZS paid total to 65+ | U16: NZS paid total after means test | V16: Revenue share | W16: Implied average tax rate | X16: Decile NZS cost | Y16: Revenue share | Z16: Implied average tax rate | AA16: Decile NZS cost | AB16: Employed working age pop current year | AC16: Total tax paying population | AD16: Employment income | AE16: Pension income | AF16: Total income | AG16: Total income | AK16: Isoelastic p = 1.26 | AL16: Isoelastic p = 1.26 normalised | AM16: Isoelastic p = 2 | AN16: Isoelsatic p = 1 | AO16: Isoelastic p = 1.26 | AP16: Isoelastic p = 1.26 normalised | AQ16: Isoelastic p = 2 | AR16: Isoelsatic p = 1 | AS16: Utilitarian | AT16: Adjusted score | AU16: Prioritarian | AV16: Maximin | AW16: Utilitarian | AX16: Adjusted score | AY16: Prioritarian | AZ16: Maximin | BA16: Utilitarian | BB16: Adjusted score | BC16: Prioritarian | BD16: Maximin | BE16: Utilitarian | BF16: Adjusted score | BG16: Prioritarian | BH16: Maximin
A17: Overall | B17: 2040 | C17: 16 | D17: =Parameters!$B$4 -> 27012.44 | E17: =Parameters!$B$5 -> 20778.68 | F17: =Parameters!$B$8 -> 1.01088 | G17: =D17*POWER(F17,C17) -> 32118.665 | H17: =E17*POWER(F17,C17) -> 24706.523 | I17: =Parameters!B3*Parameters!B40 -> 320687.1 | J17: =I17*Parameters!$B$10 -> 134688.58 | K17: =I17*Parameters!$B$9 -> 185998.52 | L17: =J17*G17 -> 4.3260174e+09 | M17: =K17*H17 -> 4.5953766e+09 | N17: =M17+L17 -> 8.921394e+09 | O17: =Parameters!B40 -> 1287900 | P17: =O17*Parameters!$B$10 -> 540918 | Q17: =O17*Parameters!$B$9 -> 746982 | R17: =P17*G17 -> 1.7373564e+10 | S17: =Q17*H17 -> 1.8455328e+10 | T17: =S17+R17 -> 3.5828892e+10 | U17: =T17-SUM(N21:N27) -> 3.1287091e+10 | AA17: =SUM(AA18:AA27) -> 3.1287091e+10 | AB17: =Parameters!C40*Parameters!B2 -> 3054491 | AC17: =AB17+I17 -> 3375178.1 | AD17: =SUM(AD18:AD27) -> 2.3114432e+11 | AE17: =N17 -> 8.921394e+09 | AF17: =AD17+AE17-X17 -> 2.4006571e+11 | AG17: =AD17+AE17-AA17 -> 2.0877862e+11 | AM17: Sensitivity check | AN17: Sensitivity check | AQ17: Sensitivity check | AR17: Sensitivity check | AS17: =SUM(AL18:AL27) -> 161.28592 | AU17: =SUM(AT18:AT27) -> 18.964987 | AV17: =MIN(AK19:AK27) -> 3.5253719 | AW17: =SUM(AN18:AN27) -> 46.25186 | AY17: =SUM(AX18:AX27) -> 21.484131 | AZ17: =MIN(AN19:AN27) -> 4.149295 | BA17: =SUM(AP18:AP27) -> 157.53797 | BC17: =SUM(BB18:BB27) -> 18.97175 | BD17: =MIN(AO19:AO27) -> 3.5311021 | BE17: =SUM(AR18:AR27) -> 46.389107 | BG17: =SUM(BF17:BF27) -> 21.51759 | BH17: =MIN(AR19:AR27) -> 4.1794027
A18: 1 | N18: =$N$17*Parameters!E15 -> 1.6220716e+09 | V18: {=Parameters!C15:C24} -> 0.0036096394 | W18: =(V18*$U$17)/(Parameters!B15*POWER(Parameters!$B$8, $C$17)) -> 0.11900851 | X18: =$U$17*V18 -> 1.1293512e+08 | Y18: =Parameters!D15 -> 0 | Z18: =(Y18*$U$17)/(Parameters!B15*POWER(Parameters!$B$8, $C$17)) -> 0 | AA18: =$U$17*Y18 -> 0 | AD18: =Parameters!B15*POWER(Parameters!$B$8, $C$17) -> 9.4896671e+08 | AE18: =$AE$3*Parameters!E15 -> 1.0090264e+09 | AF18: =AD18+AE18-X18 -> 1.845058e+09 | AG18: =AD18+AE18-AA18 -> 1.9579931e+09 | AH18: =($AB$17+$I$17)/10 -> 337517.81 | AI18: =AF18/AH18 -> 5466.55 | AJ18: =AG18/AH18 -> 5801.1549 | AK18: =(POWER(AI18, -0.26) - 1)/-0.26 -> 3.4357408 | AL18: =(AK18-$AK$18)*100 -> 0 | AM18: =(POWER(AI18, -1) - 1)/-1 -> 0.99981707 | AN18: =LOG(AI18) -> 3.7377133 | AO18: =(POWER(AJ18, -0.26) - 1)/-0.26 -> 3.4420315 | AP18: =(AO18-$AO$18)*100 -> 0 | AQ18: =(POWER(AJ18, -1) - 1)/-1 -> 0.99982762 | AR18: =LOG(AJ18) -> 3.7635145 | AT18: {=SQRT(AK18:AK27)} -> 1.8535751 | AX18: =SQRT(AN18) -> 1.9333167 | BB18: {=SQRT(AO18:AO27)} -> 1.8552713 | BF18: =SQRT(AR18) -> 1.939978
A19: 2 | N19: =$N$17*Parameters!E16 -> 1.4598645e+09 | V19: 0.014401036 | W19: =(V19*$U$17)/(Parameters!B16*POWER(Parameters!$B$8, $C$17)) -> 0.10472749 | X19: =$U$17*V19 -> 4.5056654e+08 | Y19: =Parameters!D16 -> 0.0034800777 | Z19: =(Y19*$U$17)/(Parameters!B16*POWER(Parameters!$B$8, $C$17)) -> 0.025307887 | AA19: =$U$17*Y19 -> 1.0888151e+08 | AD19: =Parameters!B16*POWER(Parameters!$B$8, $C$17) -> 4.3022757e+09 | AE19: =$AE$3*Parameters!E16 -> 9.0812375e+08 | AF19: =AD19+AE19-X19 -> 4.7598329e+09 | AG19: =AD19+AE19-AA19 -> 5.101518e+09 | AH19: =($AB$17+$I$17)/10 -> 337517.81 | AI19: =AF19/AH19 -> 14102.465 | AJ19: =AG19/AH19 -> 15114.811 | AK19: =(POWER(AI19, -0.26) - 1)/-0.26 -> 3.5253719 | AL19: =(AK19-$AK$18)*100 -> 8.9631106 | AM19: =(POWER(AI19, -1) - 1)/-1 -> 0.99992909 | AN19: =LOG(AI19) -> 4.149295 | AO19: =(POWER(AJ19, -0.26) - 1)/-0.26 -> 3.5311021 | AP19: =(AO19-$AO$18)*100 -> 8.9070586 | AQ19: =(POWER(AJ19, -1) - 1)/-1 -> 0.99993384 | AR19: =LOG(AJ19) -> 4.1794027 | AT19: 1.8775974 | AX19: =SQRT(AN19) -> 2.0369818 | BB19: 1.8791227 | BF19: =SQRT(AR19) -> 2.0443588
A20: 3 | N20: =$N$17*Parameters!E17 -> 1.2976573e+09 | V20: 0.031399077 | W20: =(V20*$U$17)/(Parameters!B17*POWER(Parameters!$B$8, $C$17)) -> 0.10948783 | X20: =$U$17*V20 -> 9.8238579e+08 | Y20: =Parameters!D17 -> 0.010886748 | Z20: =(Y20*$U$17)/(Parameters!B17*POWER(Parameters!$B$8, $C$17)) -> 0.037961831 | AA20: =$U$17*Y20 -> 3.4061469e+08 | AD20: =Parameters!B17*POWER(Parameters!$B$8, $C$17) -> 8.972557e+09 | AE20: =$AE$3*Parameters!E17 -> 8.0722111e+08 | AF20: =AD20+AE20-X20 -> 8.7973923e+09 | AG20: =AD20+AE20-AA20 -> 9.4391634e+09 | AH20: =($AB$17+$I$17)/10 -> 337517.81 | AI20: =AF20/AH20 -> 26064.972 | AJ20: =AG20/AH20 -> 27966.416 | AK20: =(POWER(AI20, -0.26) - 1)/-0.26 -> 3.5727203 | AL20: =(AK20-$AK$18)*100 -> 13.697955 | AM20: =(POWER(AI20, -1) - 1)/-1 -> 0.99996163 | AN20: =LOG(AI20) -> 4.4160573 | AO20: =(POWER(AJ20, -0.26) - 1)/-0.26 -> 3.5776806 | AP20: =(AO20-$AO$18)*100 -> 13.564908 | AQ20: =(POWER(AJ20, -1) - 1)/-1 -> 0.99996424 | AR20: =LOG(AJ20) -> 4.4466368 | AT20: 1.8901641 | AX20: =SQRT(AN20) -> 2.1014417 | BB20: 1.8914758 | BF20: =SQRT(AR20) -> 2.108705
A21: 4 | N21: =$N$17*Parameters!E18 -> 1.1354501e+09 | V21: 0.051692243 | W21: =(V21*$U$17)/(Parameters!B18*POWER(Parameters!$B$8, $C$17)) -> 0.11424817 | X21: =$U$17*V21 -> 1.6172999e+09 | Y21: =Parameters!D18 -> 0.022901399 | Z21: =(Y21*$U$17)/(Parameters!B18*POWER(Parameters!$B$8, $C$17)) -> 0.050615775 | AA21: =$U$17*Y21 -> 7.1651815e+08 | AD21: =Parameters!B18*POWER(Parameters!$B$8, $C$17) -> 1.4156025e+10 | AF21: =AD21+AE21-X21 -> 1.2538725e+10 | AG21: =AD21+AE21-AA21 -> 1.3439506e+10 | AH21: =($AB$17+$I$17)/10 -> 337517.81 | AI21: =AF21/AH21 -> 37149.816 | AJ21: =AG21/AH21 -> 39818.658 | AK21: =(POWER(AI21, -0.26) - 1)/-0.26 -> 3.5967875 | AL21: =(AK21-$AK$18)*100 -> 16.104668 | AM21: =(POWER(AI21, -1) - 1)/-1 -> 0.99997308 | AN21: =LOG(AI21) -> 4.5699567 | AO21: =(POWER(AJ21, -0.26) - 1)/-0.26 -> 3.6012452 | AP21: =(AO21-$AO$18)*100 -> 15.921372 | AQ21: =(POWER(AJ21, -1) - 1)/-1 -> 0.99997489 | AR21: =LOG(AJ21) -> 4.6000866 | AT21: 1.8965198 | AX21: =SQRT(AN21) -> 2.1377457 | BB21: 1.8976947 | BF21: =SQRT(AR21) -> 2.1447813
A22: 5 | N22: =$N$17*Parameters!E19 -> 9.7324298e+08 | V22: 0.070583126 | W22: =(V22*$U$17)/(Parameters!B19*POWER(Parameters!$B$8, $C$17)) -> 0.11900851 | X22: =$U$17*V22 -> 2.2083407e+09 | Y22: =Parameters!D19 -> 0.037524833 | Z22: =(Y22*$U$17)/(Parameters!B19*POWER(Parameters!$B$8, $C$17)) -> 0.063269718 | AA22: =$U$17*Y22 -> 1.1740429e+09 | AD22: =Parameters!B19*POWER(Parameters!$B$8, $C$17) -> 1.8556158e+10 | AF22: =AD22+AE22-X22 -> 1.6347817e+10 | AG22: =AD22+AE22-AA22 -> 1.7382115e+10 | AH22: =($AB$17+$I$17)/10 -> 337517.81 | AI22: =AF22/AH22 -> 48435.42 | AJ22: =AG22/AH22 -> 51499.845 | AK22: =(POWER(AI22, -0.26) - 1)/-0.26 -> 3.6134068 | AL22: =(AK22-$AK$18)*100 -> 17.766599 | AM22: =(POWER(AI22, -1) - 1)/-1 -> 0.99997935 | AN22: =LOG(AI22) -> 4.6851631 | AO22: =(POWER(AJ22, -0.26) - 1)/-0.26 -> 3.6170897 | AP22: =(AO22-$AO$18)*100 -> 17.505823 | AQ22: =(POWER(AJ22, -1) - 1)/-1 -> 0.99998058 | AR22: =LOG(AJ22) -> 4.7118059 | AT22: 1.9008963 | AX22: =SQRT(AN22) -> 2.1645238 | BB22: 1.9018648 | BF22: =SQRT(AR22) -> 2.1706695
A23: 6 | N23: =$N$17*Parameters!E20 -> 8.1103582e+08 | V23: 0.090905111 | W23: =(V23*$U$17)/(Parameters!B20*POWER(Parameters!$B$8, $C$17)) -> 0.12852919 | X23: =$U$17*V23 -> 2.8441565e+09 | Y23: =Parameters!D20 -> 0.053698687 | Z23: =(Y23*$U$17)/(Parameters!B20*POWER(Parameters!$B$8, $C$17)) -> 0.075923662 | AA23: =$U$17*Y23 -> 1.6800757e+09 | AD23: =Parameters!B20*POWER(Parameters!$B$8, $C$17) -> 2.2128486e+10 | AF23: =AD23+AE23-X23 -> 1.928433e+10 | AG23: =AD23+AE23-AA23 -> 2.0448411e+10 | AH23: =($AB$17+$I$17)/10 -> 337517.81 | AI23: =AF23/AH23 -> 57135.74 | AJ23: =AG23/AH23 -> 60584.686 | AK23: =(POWER(AI23, -0.26) - 1)/-0.26 -> 3.623192 | AL23: =(AK23-$AK$18)*100 -> 18.74512 | AM23: =(POWER(AI23, -1) - 1)/-1 -> 0.9999825 | AN23: =LOG(AI23) -> 4.7569079 | AO23: =(POWER(AJ23, -0.26) - 1)/-0.26 -> 3.626564 | AP23: =(AO23-$AO$18)*100 -> 18.45325 | AQ23: =(POWER(AJ23, -1) - 1)/-1 -> 0.99998349 | AR23: =LOG(AJ23) -> 4.7823629 | AT23: 1.9034684 | AX23: =SQRT(AN23) -> 2.1810337 | BB23: 1.904354 | BF23: =SQRT(AR23) -> 2.1868614
A24: 7 | N24: =$N$17*Parameters!E21 -> 6.4882865e+08 | V24: 0.11035602 | W24: =(V24*$U$17)/(Parameters!B21*POWER(Parameters!$B$8, $C$17)) -> 0.13328953 | X24: =$U$17*V24 -> 3.452719e+09 | Y24: =Parameters!D21 -> 0.083813868 | Z24: =(Y24*$U$17)/(Parameters!B21*POWER(Parameters!$B$8, $C$17)) -> 0.10123155 | AA24: =$U$17*Y24 -> 2.6222921e+09 | AD24: =Parameters!B21*POWER(Parameters!$B$8, $C$17) -> 2.5903902e+10 | AF24: =AD24+AE24-X24 -> 2.2451183e+10 | AG24: =AD24+AE24-AA24 -> 2.328161e+10 | AH24: =($AB$17+$I$17)/10 -> 337517.81 | AI24: =AF24/AH24 -> 66518.513 | AJ24: =AG24/AH24 -> 68978.907 | AK24: =(POWER(AI24, -0.26) - 1)/-0.26 -> 3.6318344 | AL24: =(AK24-$AK$18)*100 -> 19.609362 | AM24: =(POWER(AI24, -1) - 1)/-1 -> 0.99998497 | AN24: =LOG(AI24) -> 4.8229425 | AO24: =(POWER(AJ24, -0.26) - 1)/-0.26 -> 3.6338488 | AP24: =(AO24-$AO$18)*100 -> 19.181728 | AQ24: =(POWER(AJ24, -1) - 1)/-1 -> 0.9999855 | AR24: =LOG(AJ24) -> 4.8387163 | AT24: 1.9057372 | AX24: =SQRT(AN24) -> 2.1961199 | BB24: 1.9062657 | BF24: =SQRT(AR24) -> 2.1997082
A25: 8 | N25: =$N$17*Parameters!E22 -> 4.8662149e+08 | V25: 0.13623162 | W25: =(V25*$U$17)/(Parameters!B22*POWER(Parameters!$B$8, $C$17)) -> 0.13804987 | X25: =$U$17*V25 -> 4.262291e+09 | Y25: =Parameters!D22 -> 0.13736006 | Z25: =(Y25*$U$17)/(Parameters!B22*POWER(Parameters!$B$8, $C$17)) -> 0.13919338 | AA25: =$U$17*Y25 -> 4.2975968e+09 | AD25: =Parameters!B22*POWER(Parameters!$B$8, $C$17) -> 3.0875008e+10 | AF25: =AD25+AE25-X25 -> 2.6612717e+10 | AG25: =AD25+AE25-AA25 -> 2.6577412e+10 | AH25: =($AB$17+$I$17)/10 -> 337517.81 | AI25: =AF25/AH25 -> 78848.335 | AJ25: =AG25/AH25 -> 78743.731 | AK25: =(POWER(AI25, -0.26) - 1)/-0.26 -> 3.6411035 | AL25: =(AK25-$AK$18)*100 -> 20.536269 | AM25: =(POWER(AI25, -1) - 1)/-1 -> 0.99998732 | AN25: =LOG(AI25) -> 4.8967925 | AO25: =(POWER(AJ25, -0.26) - 1)/-0.26 -> 3.6410327 | AP25: =(AO25-$AO$18)*100 -> 19.90012 | AQ25: =(POWER(AJ25, -1) - 1)/-1 -> 0.9999873 | AR25: =LOG(AJ25) -> 4.896216 | AT25: 1.9081676 | AX25: =SQRT(AN25) -> 2.2128697 | BB25: 1.908149 | BF25: =SQRT(AR25) -> 2.2127395
A26: 9 | N26: =$N$17*Parameters!E23 -> 3.2441433e+08 | V26: 0.17539672 | W26: =(V26*$U$17)/(Parameters!B23*POWER(Parameters!$B$8, $C$17)) -> 0.14281021 | X26: =$U$17*V26 -> 5.4876532e+09 | Y26: =Parameters!D23 -> 0.21757858 | Z26: =(Y26*$U$17)/(Parameters!B23*POWER(Parameters!$B$8, $C$17)) -> 0.17715521 | AA26: =$U$17*Y26 -> 6.8074009e+09 | AD26: =Parameters!B23*POWER(Parameters!$B$8, $C$17) -> 3.8426196e+10 | AF26: =AD26+AE26-X26 -> 3.2938543e+10 | AG26: =AD26+AE26-AA26 -> 3.1618795e+10 | AH26: =($AB$17+$I$17)/10 -> 337517.81 | AI26: =AF26/AH26 -> 97590.532 | AJ26: =AG26/AH26 -> 93680.375 | AK26: =(POWER(AI26, -0.26) - 1)/-0.26 -> 3.6521633 | AL26: =(AK26-$AK$18)*100 -> 21.642249 | AM26: =(POWER(AI26, -1) - 1)/-1 -> 0.99998975 | AN26: =LOG(AI26) -> 4.9894077 | AO26: =(POWER(AJ26, -0.26) - 1)/-0.26 -> 3.6500898 | AP26: =(AO26-$AO$18)*100 -> 20.80583 | AQ26: =(POWER(AJ26, -1) - 1)/-1 -> 0.99998933 | AR26: =LOG(AJ26) -> 4.9716486 | AT26: 1.9110634 | AX26: =SQRT(AN26) -> 2.2336982 | BB26: 1.9105208 | BF26: =SQRT(AR26) -> 2.2297194
A27: 10 | N27: =$N$17*Parameters!E24 -> 1.6220716e+08 | V27: 0.3154254 | W27: =(V27*$U$17)/(Parameters!B24*POWER(Parameters!$B$8, $C$17)) -> 0.14757055 | X27: =$U$17*V27 -> 9.8687433e+09 | Y27: =Parameters!D24 -> 0.43275574 | Z27: =(Y27*$U$17)/(Parameters!B24*POWER(Parameters!$B$8, $C$17)) -> 0.2024631 | AA27: =$U$17*Y27 -> 1.3539668e+10 | AD27: =Parameters!B24*POWER(Parameters!$B$8, $C$17) -> 6.6874746e+10 | AF27: =AD27+AE27-X27 -> 5.7006003e+10 | AG27: =AD27+AE27-AA27 -> 5.3335078e+10 | AH27: =($AB$17+$I$17)/10 -> 337517.81 | AI27: =AF27/AH27 -> 168897.76 | AJ27: =AG27/AH27 -> 158021.52 | AK27: =(POWER(AI27, -0.26) - 1)/-0.26 -> 3.6779467 | AL27: =(AK27-$AK$18)*100 -> 24.220593 | AM27: =(POWER(AI27, -1) - 1)/-1 -> 0.99999408 | AN27: =LOG(AI27) -> 5.2276239 | AO27: =(POWER(AJ27, -0.26) - 1)/-0.26 -> 3.6750103 | AP27: =(AO27-$AO$18)*100 -> 23.297886 | AQ27: =(POWER(AJ27, -1) - 1)/-1 -> 0.99999367 | AR27: =LOG(AJ27) -> 5.1987162 | AT27: 1.9177974 | AX27: =SQRT(AN27) -> 2.2863998 | BB27: 1.9170316 | BF27: =SQRT(AR27) -> 2.2800693
A29: Decile | B29: Year | D29: NZS income per recipient | V29: Baseline tax | Y29: Progressive tax | AB29: Size tax paying group by income group | AD29: Gross income | AF29: Net Income baseline tax | AG29: Net income Progressive | AH29: Quintile size | AI29: Average income pp baseline tax | AJ29: Average income pp progressive | AK29: Utility score baseline tax | AO29: Utility score progressive | AS29: Welfare score baseline tax isoelastic utility | AW29: Welfare score baseline tax log utility | BA29: Welfare score progressive tax isoelastic utility | BE29: Welfare score progressive tax log utility
B30: Year | C30: Years since base | D30: Base year annual rate singles | E30: Base year annual rate couples | F30: Mulitplier | G30: Current year real rate singles | H30: Current year annual rate couples | I30: 65+ employed population current year | J30: Single | K30: In a relationship | L30: NZS paid singles rate | M30: NZS paid couples rate | N30: NZS paid total to employed 65+ | O30: Total 65+ population | P30: Single | Q30: In a relationship | R30: NZS paid singles rate | S30: NZS paid couples rate | T30: NZS paid total to 65+ | U30: NZS paid total after means test | V30: Revenue share | W30: Implied average tax rate | X30: Decile NZS cost | Y30: Revenue share | Z30: Implied average tax rate | AA30: Decile NZS cost | AB30: Employed working age pop current year | AC30: Total tax paying population | AD30: Employment income | AE30: Pension income | AF30: Total income | AG30: Total income | AK30: Isoelastic p = 1.26 | AL30: Isoelastic p = 1.26 normalised | AM30: Isoelastic p = 2 | AN30: Isoelsatic p = 1 | AO30: Isoelastic p = 1.26 | AP30: Isoelastic p = 1.26 normalised | AQ30: Isoelastic p = 2 | AR30: Isoelsatic p = 1 | AS30: Utilitarian | AT30: Adjusted score | AU30: Prioritarian | AV30: Maximin | AW30: Utilitarian | AX30: Adjusted score | AY30: Prioritarian | AZ30: Maximin | BA30: Utilitarian | BB30: Adjusted score | BC30: Prioritarian | BD30: Maximin | BE30: Utilitarian | BF30: Adjusted score | BG30: Prioritarian | BH30: Maximin
A31: Overall | B31: 2078 | C31: 54 | D31: =Parameters!$B$4 -> 27012.44 | E31: =Parameters!$B$5 -> 20778.68 | F31: =Parameters!$B$8 -> 1.01088 | G31: =D31*POWER(F31,C31) -> 48455.429 | H31: =E31*POWER(F31,C31) -> 37273.192 | I31: =Parameters!$B$3*Parameters!B42 -> 557660.4 | J31: =I31*Parameters!$B$10 -> 234217.37 | K31: =I31*Parameters!$B$9 -> 323443.03 | L31: =J31*G31 -> 1.1349103e+10 | M31: =K31*H31 -> 1.2055754e+10 | N31: =M31+L31 -> 2.3404857e+10 | O31: =Parameters!B42 -> 2239600 | P31: =O31*Parameters!$B$10 -> 940632 | Q31: =O31*Parameters!$B$9 -> 1298968 | R31: =P31*G31 -> 4.5578727e+10 | S31: =Q31*H31 -> 4.8416683e+10 | T31: =S31+R31 -> 9.399541e+10 | U31: =T31-SUM(N35:N41) -> 8.208021e+10 | AA31: =SUM(AA32:AA41) -> 8.208021e+10 | AB31: =Parameters!C42*Parameters!B2 -> 3564796.4 | AC31: =AB31+I31 -> 4122456.8 | AD31: =SUM(AD32:AD41) -> 3.4871304e+11 | AE31: =N31 -> 2.3404857e+10 | AF31: =AD31+AE31-X31 -> 3.721179e+11 | AG31: =AD31+AE31-AA31 -> 2.9003769e+11 | AM31: Sensitivity check | AN31: Sensitivity check | AQ31: Sensitivity check | AR31: Sensitivity check | AS31: =SUM(AL32:AL41) -> 178.71893 | AU31: =SUM(AT32:AT41) -> 19.011359 | AV31: =MIN(AK33:AK41) -> 3.5609596 | AW31: =SUM(AN32:AN41) -> 47.232301 | AY31: =SUM(AX32:AX41) -> 21.720627 | AZ31: =MIN(AN33:AN41) -> 4.3457151 | BA31: =SUM(AP32:AP41) -> 175.72714 | BC31: =SUM(BB32:BB41) -> 19.02008 | BD31: =MIN(AO33:AO41) -> 3.5678144 | BE31: =SUM(AR32:AR41) -> 47.43258 | BG31: =SUM(BF31:BF41) -> 21.768405 | BH31: =MIN(AR33:AR41) -> 4.3863533
A32: 1 | N32: =$N$31*Parameters!E15 -> 4.2554286e+09 | V32: =Parameters!C15 -> 0.0036096394 | W32: =(V32*$U$31)/(Parameters!B15*POWER(Parameters!$B$8,$C$31)) -> 0.20695043 | X32: =$U$31*V32 -> 2.9627996e+08 | Y32: =Parameters!D15 -> 0 | Z32: =(Y32*$U$31)/(Parameters!B15*POWER(Parameters!$B$8,$C$31)) -> 0 | AA32: =$U$31*Y32 -> 0 | AD32: =Parameters!B15*POWER(Parameters!$B$8,$C$31) -> 1.431647e+09 | AE32: =$AE$31*Parameters!E15 -> 4.2554286e+09 | AF32: =AD32+AE32-X32 -> 5.3907956e+09 | AG32: =AD32+AE32-AA32 -> 5.6870756e+09 | AH32: =($AB$31+$I$31)/10 -> 412245.68 | AI32: =AF32/AH32 -> 13076.658 | AJ32: =AG32/AH32 -> 13795.355 | AK32: =(POWER(AI32, -0.26) - 1)/-0.26 -> 3.5190109 | AL32: =(AK32-$AK$18)*100 -> 8.3270176 | AM32: =(POWER(AI32, -1) - 1)/-1 -> 0.99992353 | AN32: =LOG(AI32) -> 4.1164968 | AO32: =(POWER(AJ32, -0.26) - 1)/-0.26 -> 3.5235303 | AP32: =(AO32-$AO$18)*100 -> 8.1498793 | AQ32: =(POWER(AJ32, -1) - 1)/-1 -> 0.99992751 | AR32: =LOG(AJ32) -> 4.1397329 | AT32: {=SQRT(AK32:AK41)} -> 1.8759027 | AX32: =SQRT(AN32) -> 2.0289152 | BB32: {=SQRT(AO32:AO41)} -> 1.8771069 | BF32: =SQRT(AR32) -> 2.0346334
A33: 2 | N33: =$N$31*Parameters!E16 -> 3.8298857e+09 | V33: =Parameters!C16 -> 0.014401036 | W33: =(V33*$U$31)/(Parameters!B16*POWER(Parameters!$B$8,$C$31)) -> 0.18211638 | X33: =$U$31*V33 -> 1.1820401e+09 | Y33: =Parameters!D16 -> 0.0034800777 | Z33: =(Y33*$U$31)/(Parameters!B16*POWER(Parameters!$B$8,$C$31)) -> 0.044009274 | AA33: =$U$31*Y33 -> 2.8564551e+08 | AD33: =Parameters!B16*POWER(Parameters!$B$8,$C$31) -> 6.4905754e+09 | AE33: =$AE$31*Parameters!E16 -> 3.8298857e+09 | AF33: =AD33+AE33-X33 -> 9.138421e+09 | AG33: =AD33+AE33-AA33 -> 1.0034816e+10 | AH33: =($AB$31+$I$31)/10 -> 412245.68 | AI33: =AF33/AH33 -> 22167.415 | AJ33: =AG33/AH33 -> 24341.833 | AK33: =(POWER(AI33, -0.26) - 1)/-0.26 -> 3.5609596 | AL33: =(AK33-$AK$18)*100 -> 12.521884 | AM33: =(POWER(AI33, -1) - 1)/-1 -> 0.99995489 | AN33: =LOG(AI33) -> 4.3457151 | AO33: =(POWER(AJ33, -0.26) - 1)/-0.26 -> 3.5678144 | AP33: =(AO33-$AO$18)*100 -> 12.57829 | AQ33: =(POWER(AJ33, -1) - 1)/-1 -> 0.99995892 | AR33: =LOG(AJ33) -> 4.3863533 | AT33: 1.8870505 | AX33: =SQRT(AN33) -> 2.0846379 | BB33: 1.8888659 | BF33: =SQRT(AR33) -> 2.0943623
A34: 3 | N34: =$N$31*Parameters!E17 -> 3.4043429e+09 | V34: =Parameters!C17 -> 0.031399077 | W34: =(V34*$U$31)/(Parameters!B17*POWER(Parameters!$B$8,$C$31)) -> 0.1903944 | X34: =$U$31*V34 -> 2.5772429e+09 | Y34: =Parameters!D17 -> 0.010886748 | Z34: =(Y34*$U$31)/(Parameters!B17*POWER(Parameters!$B$8,$C$31)) -> 0.066013911 | AA34: =$U$31*Y34 -> 8.9358661e+08 | AD34: =Parameters!B17*POWER(Parameters!$B$8,$C$31) -> 1.3536338e+10 | AE34: =$AE$31*Parameters!E17 -> 3.4043429e+09 | AF34: =AD34+AE34-X34 -> 1.4363438e+10 | AG34: =AD34+AE34-AA34 -> 1.6047094e+10 | AH34: =($AB$31+$I$31)/10 -> 412245.68 | AI34: =AF34/AH34 -> 34841.936 | AJ34: =AG34/AH34 -> 38926.045 | AK34: =(POWER(AI34, -0.26) - 1)/-0.26 -> 3.5925942 | AL34: =(AK34-$AK$18)*100 -> 15.685347 | AM34: =(POWER(AI34, -1) - 1)/-1 -> 0.9999713 | AN34: =LOG(AI34) -> 4.5421023 | AO34: =(POWER(AJ34, -0.26) - 1)/-0.26 -> 3.5997973 | AP34: =(AO34-$AO$18)*100 -> 15.776578 | AQ34: =(POWER(AJ34, -1) - 1)/-1 -> 0.99997431 | AR34: =LOG(AJ34) -> 4.5902403 | AT34: 1.895414 | AX34: =SQRT(AN34) -> 2.1312208 | BB34: 1.8973132 | BF34: =SQRT(AR34) -> 2.1424846
A35: 4 | N35: =$N$31*Parameters!E18 -> 2.9788e+09 | V35: =Parameters!C18 -> 0.051692243 | W35: =(V35*$U$31)/(Parameters!B18*POWER(Parameters!$B$8,$C$31)) -> 0.19867241 | X35: =$U$31*V35 -> 4.2429102e+09 | Y35: =Parameters!D18 -> 0.022901399 | Z35: =(Y35*$U$31)/(Parameters!B18*POWER(Parameters!$B$8,$C$31)) -> 0.088018549 | AA35: =$U$31*Y35 -> 1.8797516e+09 | AD35: =Parameters!B18*POWER(Parameters!$B$8,$C$31) -> 2.1356313e+10 | AF35: =AD35+AE35-X35 -> 1.7113402e+10 | AG35: =AD35+AE35-AA35 -> 1.9476561e+10 | AH35: =($AB$31+$I$31)/10 -> 412245.68 | AI35: =AF35/AH35 -> 41512.63 | AJ35: =AG35/AH35 -> 47245.033 | AK35: =(POWER(AI35, -0.26) - 1)/-0.26 -> 3.6038838 | AL35: =(AK35-$AK$18)*100 -> 16.814299 | AM35: =(POWER(AI35, -1) - 1)/-1 -> 0.99997591 | AN35: =LOG(AI35) -> 4.6181802 | AO35: =(POWER(AJ35, -0.26) - 1)/-0.26 -> 3.6118961 | AP35: =(AO35-$AO$18)*100 -> 16.986458 | AQ35: =(POWER(AJ35, -1) - 1)/-1 -> 0.99997883 | AR35: =LOG(AJ35) -> 4.6743562 | AT35: 1.8983898 | AX35: =SQRT(AN35) -> 2.1489952 | BB35: 1.9004989 | BF35: =SQRT(AR35) -> 2.1620259
A36: 5 | N36: =$N$31*Parameters!E19 -> 2.5532571e+09 | V36: =Parameters!C19 -> 0.070583126 | W36: =(V36*$U$31)/(Parameters!B19*POWER(Parameters!$B$8,$C$31)) -> 0.20695043 | X36: =$U$31*V36 -> 5.7934778e+09 | Y36: =Parameters!D19 -> 0.037524833 | Z36: =(Y36*$U$31)/(Parameters!B19*POWER(Parameters!$B$8,$C$31)) -> 0.11002319 | AA36: =$U$31*Y36 -> 3.0800462e+09 | AD36: =Parameters!B19*POWER(Parameters!$B$8,$C$31) -> 2.7994519e+10 | AF36: =AD36+AE36-X36 -> 2.2201041e+10 | AG36: =AD36+AE36-AA36 -> 2.4914473e+10 | AH36: =($AB$31+$I$31)/10 -> 412245.68 | AI36: =AF36/AH36 -> 53853.909 | AJ36: =AG36/AH36 -> 60435.983 | AK36: =(POWER(AI36, -0.26) - 1)/-0.26 -> 3.6197363 | AL36: =(AK36-$AK$18)*100 -> 18.399548 | AM36: =(POWER(AI36, -1) - 1)/-1 -> 0.99998143 | AN36: =LOG(AI36) -> 4.7312172 | AO36: =(POWER(AJ36, -0.26) - 1)/-0.26 -> 3.6264236 | AP36: =(AO36-$AO$18)*100 -> 18.439215 | AQ36: =(POWER(AJ36, -1) - 1)/-1 -> 0.99998345 | AR36: =LOG(AJ36) -> 4.7812956 | AT36: 1.9025604 | AX36: =SQRT(AN36) -> 2.1751361 | BB36: 1.9043171 | BF36: =SQRT(AR36) -> 2.1866174
A37: 6 | N37: =$N$31*Parameters!E20 -> 2.1277143e+09 | V37: =Parameters!C20 -> 0.090905111 | W37: =(V37*$U$31)/(Parameters!B20*POWER(Parameters!$B$8,$C$31)) -> 0.22350647 | X37: =$U$31*V37 -> 7.4615106e+09 | Y37: =Parameters!D20 -> 0.053698687 | Z37: =(Y37*$U$31)/(Parameters!B20*POWER(Parameters!$B$8,$C$31)) -> 0.13202782 | AA37: =$U$31*Y37 -> 4.4075996e+09 | AD37: =Parameters!B20*POWER(Parameters!$B$8,$C$31) -> 3.3383869e+10 | AF37: =AD37+AE37-X37 -> 2.5922359e+10 | AG37: =AD37+AE37-AA37 -> 2.897627e+10 | AH37: =($AB$31+$I$31)/10 -> 412245.68 | AI37: =AF37/AH37 -> 62880.849 | AJ37: =AG37/AH37 -> 70288.837 | AK37: =(POWER(AI37, -0.26) - 1)/-0.26 -> 3.6286776 | AL37: =(AK37-$AK$18)*100 -> 19.293681 | AM37: =(POWER(AI37, -1) - 1)/-1 -> 0.9999841 | AN37: =LOG(AI37) -> 4.7985184 | AO37: =(POWER(AJ37, -0.26) - 1)/-0.26 -> 3.6348846 | AP37: =(AO37-$AO$18)*100 -> 19.285317 | AQ37: =(POWER(AJ37, -1) - 1)/-1 -> 0.99998577 | AR37: =LOG(AJ37) -> 4.8468864 | AT37: 1.9049088 | AX37: =SQRT(AN37) -> 2.1905521 | BB37: 1.9065373 | BF37: =SQRT(AR37) -> 2.2015645
A38: 7 | N38: =$N$31*Parameters!E21 -> 1.7021714e+09 | V38: =Parameters!C21 -> 0.11035602 | W38: =(V38*$U$31)/(Parameters!B21*POWER(Parameters!$B$8,$C$31)) -> 0.23178448 | X38: =$U$31*V38 -> 9.0580457e+09 | Y38: =Parameters!D21 -> 0.083813868 | Z38: =(Y38*$U$31)/(Parameters!B21*POWER(Parameters!$B$8,$C$31)) -> 0.1760371 | AA38: =$U$31*Y38 -> 6.8794599e+09 | AD38: =Parameters!B21*POWER(Parameters!$B$8,$C$31) -> 3.9079603e+10 | AF38: =AD38+AE38-X38 -> 3.0021558e+10 | AG38: =AD38+AE38-AA38 -> 3.2200143e+10 | AH38: =($AB$31+$I$31)/10 -> 412245.68 | AI38: =AF38/AH38 -> 72824.432 | AJ38: =AG38/AH38 -> 78109.111 | AK38: =(POWER(AI38, -0.26) - 1)/-0.26 -> 3.6368223 | AL38: =(AK38-$AK$18)*100 -> 20.108157 | AM38: =(POWER(AI38, -1) - 1)/-1 -> 0.99998627 | AN38: =LOG(AI38) -> 4.8622771 | AO38: =(POWER(AJ38, -0.26) - 1)/-0.26 -> 3.6406007 | AP38: =(AO38-$AO$18)*100 -> 19.856918 | AQ38: =(POWER(AJ38, -1) - 1)/-1 -> 0.9999872 | AR38: =LOG(AJ38) -> 4.8927017 | AT38: 1.9070454 | AX38: =SQRT(AN38) -> 2.2050572 | BB38: 1.9080358 | BF38: =SQRT(AR38) -> 2.2119452
A39: 8 | N39: =$N$31*Parameters!E22 -> 1.2766286e+09 | V39: =Parameters!C22 -> 0.13623162 | W39: =(V39*$U$31)/(Parameters!B22*POWER(Parameters!$B$8,$C$31)) -> 0.2400625 | X39: =$U$31*V39 -> 1.118192e+10 | Y39: =Parameters!D22 -> 0.13736006 | Z39: =(Y39*$U$31)/(Parameters!B22*POWER(Parameters!$B$8,$C$31)) -> 0.24205101 | AA39: =$U$31*Y39 -> 1.1274543e+10 | AD39: =Parameters!B22*POWER(Parameters!$B$8,$C$31) -> 4.6579202e+10 | AF39: =AD39+AE39-X39 -> 3.5397282e+10 | AG39: =AD39+AE39-AA39 -> 3.5304659e+10 | AH39: =($AB$31+$I$31)/10 -> 412245.68 | AI39: =AF39/AH39 -> 85864.532 | AJ39: =AG39/AH39 -> 85639.852 | AK39: =(POWER(AI39, -0.26) - 1)/-0.26 -> 3.6455981 | AL39: =(AK39-$AK$18)*100 -> 20.985735 | AM39: =(POWER(AI39, -1) - 1)/-1 -> 0.99998835 | AN39: =LOG(AI39) -> 4.9338138 | AO39: =(POWER(AJ39, -0.26) - 1)/-0.26 -> 3.6454615 | AP39: =(AO39-$AO$18)*100 -> 20.342998 | AQ39: =(POWER(AJ39, -1) - 1)/-1 -> 0.99998832 | AR39: =LOG(AJ39) -> 4.9326759 | AT39: 1.9093449 | AX39: =SQRT(AN39) -> 2.221219 | BB39: 1.9093092 | BF39: =SQRT(AR39) -> 2.2209628
A40: 9 | N40: =$N$31*Parameters!E23 -> 8.5108572e+08 | V40: =Parameters!C23 -> 0.17539672 | W40: =(V40*$U$31)/(Parameters!B23*POWER(Parameters!$B$8,$C$31)) -> 0.24834052 | X40: =$U$31*V40 -> 1.43966e+10 | Y40: =Parameters!D23 -> 0.21757858 | Z40: =(Y40*$U$31)/(Parameters!B23*POWER(Parameters!$B$8,$C$31)) -> 0.30806492 | AA40: =$U$31*Y40 -> 1.7858896e+10 | AD40: =Parameters!B23*POWER(Parameters!$B$8,$C$31) -> 5.7971209e+10 | AF40: =AD40+AE40-X40 -> 4.3574609e+10 | AG40: =AD40+AE40-AA40 -> 4.0112313e+10 | AH40: =($AB$31+$I$31)/10 -> 412245.68 | AI40: =AF40/AH40 -> 105700.58 | AJ40: =AG40/AH40 -> 97301.96 | AK40: =(POWER(AI40, -0.26) - 1)/-0.26 -> 3.6561482 | AL40: =(AK40-$AK$18)*100 -> 22.040742 | AM40: =(POWER(AI40, -1) - 1)/-1 -> 0.99999054 | AN40: =LOG(AI40) -> 5.0240774 | AO40: =(POWER(AJ40, -0.26) - 1)/-0.26 -> 3.6520138 | AP40: =(AO40-$AO$18)*100 -> 20.998236 | AQ40: =(POWER(AJ40, -1) - 1)/-1 -> 0.99998972 | AR40: =LOG(AJ40) -> 4.9881216 | AT40: 1.9121057 | AX40: =SQRT(AN40) -> 2.2414454 | BB40: 1.9110243 | BF40: =SQRT(AR40) -> 2.2334103
A41: 10 | N41: =$N$31*Parameters!E24 -> 4.2554286e+08 | V41: =Parameters!C24 -> 0.3154254 | W41: =(V41*$U$31)/(Parameters!B24*POWER(Parameters!$B$8,$C$31)) -> 0.25661854 | X41: =$U$31*V41 -> 2.5890183e+10 | Y41: =Parameters!D24 -> 0.43275574 | Z41: =(Y41*$U$31)/(Parameters!B24*POWER(Parameters!$B$8,$C$31)) -> 0.35207419 | AA41: =$U$31*Y41 -> 3.5520682e+10 | AD41: =Parameters!B24*POWER(Parameters!$B$8,$C$31) -> 1.0088976e+11 | AF41: =AD41+AE41-X41 -> 7.4999581e+10 | AG41: =AD41+AE41-AA41 -> 6.5369082e+10 | AH41: =($AB$31+$I$31)/10 -> 412245.68 | AI41: =AF41/AH41 -> 181929.33 | AJ41: =AG41/AH41 -> 158568.26 | AK41: =(POWER(AI41, -0.26) - 1)/-0.26 -> 3.681166 | AL41: =(AK41-$AK$18)*100 -> 24.542523 | AM41: =(POWER(AI41, -1) - 1)/-1 -> 0.9999945 | AN41: =LOG(AI41) -> 5.2599027 | AO41: =(POWER(AJ41, -0.26) - 1)/-0.26 -> 3.675164 | AP41: =(AO41-$AO$18)*100 -> 23.313248 | AQ41: =(POWER(AJ41, -1) - 1)/-1 -> 0.99999369 | AR41: =LOG(AJ41) -> 5.2002163 | AT41: 1.9186365 | AX41: =SQRT(AN41) -> 2.2934478 | BB41: 1.9170717 | BF41: =SQRT(AR41) -> 2.2803983
A44: Only the bottom three deciles get NZS

Sheet Income universal
A1: Decile | B1: Year | D1: NZS income per recipient | U1: Baselinetax | X1: Progressive tax | AA1: Size tax paying group by income group | AC1: Gross income | AE1: Net Income Baseline | AG1: Net income Progressive | AI1: Decile size | AJ1: Average income pp Baseline | AL1: Average income pp progressive | AN1: Utility score baseline tax post-NZS income | AR1: Utility score progressive tax post-NZS income | AV1: Welfare score baseline tax post-NZS income isoelastic utility | AZ1: Welfare score baseline tax post-NZS income log utility | BD1: Welfare score progressive tax post-NZS income isoelastic utility | BH1: Welfare score progressive tax post-NZS income log utility | BL1: Welfare score baseline tax pre-NZS income isoelastic utility | BP1: Welfare score baseline tax pre-NZS income log utility | BT1: Welfare score progressive tax pre-NZS income isoelastic utility | BX1: Welfare score progressive tax pre-NZS income log utility | CB1: Utility score baseline tax pre-NZS income | CE1: Utility score progressive tax pre-NZS income | CH1: Adjusted scores prioritarian welfare p = 2
B2: Year | C2: Years since base | D2: Base year annual rate singles | E2: Base year annual rate couples | F2: Mulitplier | G2: Current year real rate singles | H2: Current year annual rate couples | I2: 65+ employed population current year | J2: Single | K2: In a relationship | L2: NZS paid singles rate | M2: NZS paid couples rate | N2: NZS paid total to employed 65+ | O2: Total 65+ population | P2: Single | Q2: In a relationship | R2: NZS paid singles rate | S2: NZS paid couples rate | T2: NZS paid total to 65+ | U2: Revenue share | V2: Implied effective tax rate | W2: Decile NZS cost | X2: Revenue share | Y2: Implied effective tax rate | Z2: Decile NZS cost | AA2: Employed working age pop current year | AB2: Total tax paying population | AC2: Employment income | AD2: Pension income | AE2: Total income | AF2: Total income without NZS | AG2: Total income | AH2: Total income without NZS | AJ2: post-NZS | AK2: pre-NZS | AL2: post-NZS | AM2: pre-NZS | AN2: Isoelastic p = 1.26 | AO2: Isoelastic p= 1.26 normalised | AP2: Isoelastic p = 2 | AQ2: Isoelsatic p = 1 | AR2: Isoelastic p = 1.26 | AS2: Isoelastic p = 1.26 normalised | AT2: Isoelastic p = 2 | AU2: Isoelsatic p = 1 | AV2: Utilitarian | AW2: Adjusted score | AX2: Prioritarian | AY2: Maximin | AZ2: Utilitarian | BA2: Adjusted score | BB2: Prioritarian | BC2: Maximin | BD2: Utilitarian | BE2: Adjusted score | BF2: Prioritarian | BG2: Maximin | BH2: Utilitarian | BI2: Adjusted score | BJ2: Prioritarian | BK2: Maximin | BL2: Utilitarian | BM2: Adjusted score | BN2: Prioritarian | BO2: Maximin | BP2: Utilitarian | BQ2: Adjusted score | BR2: Prioritarian | BS2: Maximin | BT2: Utilitarian | BU2: Adjusted score | BV2: Prioritarian | BW2: Maximin | BX2: Utilitarian | BY2: Adjusted score | BZ2: Prioritarian | CA2: Maximin | CB2: Isoelsatic p = 1.26 | CC2: Isoelastic normalised | CD2: Isoelsatic p = 1 | CE2: Isoelsatic p = 1.26 | CF2: Isoelastic p = 1.26 normalised | CG2: Isoelsatic p = 1 | CH2: Baseline | CI2: Progressive
A3: Overall | B3: 2026 | C3: 2 | D3: =Parameters!$B$4 -> 27012.44 | E3: =Parameters!$B$5 -> 20778.68 | F3: =Parameters!$B$8 -> 1.01088 | G3: =D3*POWER(F3,C3) -> 27603.428 | H3: =E3*POWER(F3,C3) -> 21233.284 | I3: =Parameters!B3*Parameters!B39 -> 232117.8 | J3: =I3*Parameters!$B$10 -> 97489.476 | K3: =I3*Parameters!$B$9 -> 134628.32 | L3: =J3*G3 -> 2.6910438e+09 | M3: =K3*H3 -> 2.8586014e+09 | N3: =M3+L3 -> 5.5496452e+09 | O3: =Parameters!B39 -> 932200 | P3: =O3*Parameters!$B$10 -> 391524 | Q3: =O3*Parameters!$B$9 -> 540676 | R3: =P3*G3 -> 1.0807405e+10 | S3: =Q3*H3 -> 1.1480327e+10 | T3: =S3+R3 -> 2.2287732e+10 | W3: =SUM(W4:W13) -> 2.2287732e+10 | Z3: =SUM(Z4:Z13) -> 2.2287732e+10 | AA3: =Parameters!C39*Parameters!B2 -> 2728423.5 | AB3: =AA3+I3 -> 2960541.3 | AC3: =SUM(AC4:AC13) -> 1.9865009e+11 | AD3: =N3 -> 5.5496452e+09 | AE3: =AC3+AD3-W3 -> 1.81912e+11 | AF3: =AC3-W3 -> 1.7636236e+11 | AG3: =AC3+AD3-Z3 -> 1.81912e+11 | AH3: =AC3-Z3 -> 1.7636236e+11 | AP3: Sensitivity check | AQ3: Sensitivity check | AT3: Sensitivity check | AU3: Sensitivity check | AV3: =SUM(AN4:AN13) -> 35.99359 | AW3: Prioritarian | AX3: =SUM(AW4:AW13) -> 18.971179 | AY3: =MIN(AN5:AN13) -> 3.5275244 | AZ3: =SUM(AQ4:AQ13) -> 46.393167 | BB3: =SUM(BA4:BA13) -> 21.517704 | BC3: =MIN(AQ5:AQ13) -> 4.1605412 | BD3: =SUM(AR4:AR13) -> 36.013256 | BF3: =SUM(BE4:BE13) -> 18.976407 | BG3: =MIN(AR5:AR13) -> 3.5320691 | BH3: =SUM(AU4:AU13) -> 46.500386 | BJ3: =SUM(BI3:BI13) -> 21.543793 | BK3: =MIN(AU5:AU13) -> 4.1845375 | BL3: =SUM(CB4:CB13) -> 35.853623 | BN3: =SUM(BM4:BM13) -> 18.933425 | BO3: =MIN(CB5:CB13) -> 3.5071677 | BP3: =SUM(CD4:CD13) -> 45.791359 | BR3: =SUM(BQ4:BQ13) -> 21.364289 | BS3: =MIN(CD5:CD13) -> 4.0570951 | BT3: =SUM(CE4:CE13) -> 35.884658 | BV3: =SUM(BU4:BU13) -> 18.941763 | BW3: =MIN(CE5:CE13) -> 3.5132475 | BX3: =SUM(CG4:CG13) -> 45.936067 | BZ3: =SUM(BY3:BY13) -> 21.400568 | CA3: =MIN(CG5:CG13) -> 4.0873254
A4: 1 | U4: =Parameters!C15 -> 0.0036096394 | V4: =(U4*$T$3)/(Parameters!B15*POWER(Parameters!$B$8,$C$3)) -> 0.098644565 | W4: =$T$3*U4 -> 80450673 | X4: {=Parameters!D15:D24} -> 0 | Y4: =(X4*$T$3)/(Parameters!B15*POWER(Parameters!$B$8,$C$3)) -> 0 | Z4: =$T$3*X4 -> 0 | AC4: =Parameters!B15*POWER(Parameters!$B$8,$C$3) -> 8.1556113e+08 | AD4: =$AD$3*Parameters!E15 -> 1.0090264e+09 | AE4: =AC4+AD4-W4 -> 1.7441369e+09 | AF4: =AC4-W4 -> 7.3511046e+08 | AG4: =AC4+AD4-Z4 -> 1.8245875e+09 | AH4: =AC4-Z4 -> 8.1556113e+08 | AI4: =($AA$3+$I$3)/10 -> 296054.13 | AJ4: =AE4/AI4 -> 5891.2769 | AK4: =AF4/AI4 -> 2483.0272 | AL4: =AG4/AI4 -> 6163.02 | AM4: =AH4/AI4 -> 2754.7703 | AN4: =(POWER(AJ4, -0.26) - 1)/-0.26 -> 3.443648 | AO4: =(AN4-$AN$4)*100 -> 0 | AP4: =(POWER(AJ4, -1) - 1)/-1 -> 0.99983026 | AQ4: =LOG(AJ4) -> 3.7702094 | AR4: =(POWER(AL4, -0.26) - 1)/-0.26 -> 3.4483396 | AS4: =(AR4-$AR$4)*100 -> 0 | AT4: =(POWER(AL4, -1) - 1)/-1 -> 0.99983774 | AU4: =LOG(AL4) -> 3.7897936 | AW4: =SQRT(AN4) -> 1.8557069 | BA4: =SQRT(AQ4) -> 1.9417027 | BE4: =SQRT(AR4) -> 1.8569705 | BI4: =SQRT(AU4) -> 1.9467392 | BM4: =SQRT(CB4) -> 1.8281873 | BQ4: =SQRT(CD4) -> 1.8425476 | BU4: =SQRT(CE4) -> 1.831855 | BY4: =SQRT(CG4) -> 1.8547467 | CB4: =(POWER(AK4, -0.26) - 1)/-0.26 -> 3.3422688 | CC4: =(CB4-$CB$4)*100 -> 0 | CD4: =LOG(AK4) -> 3.3949815 | CE4: =(POWER(AM4, -0.26) - 1)/-0.26 -> 3.3556929 | CF4: =(CE4-$CE$4)*100 -> 0 | CG4: =LOG(AM4) -> 3.4400854 | CH4: =SQRT(AP4) -> 0.99991513 | CI4: =SQRT(AT4) -> 0.99991887
A5: 2 | U5: =Parameters!C16 -> 0.014401036 | V5: =(U5*$T$3)/(Parameters!B16*POWER(Parameters!$B$8,$C$3)) -> 0.086807218 | W5: =$T$3*U5 -> 3.2096643e+08 | X5: 0.0034800777 | Y5: =(X5*$T$3)/(Parameters!B16*POWER(Parameters!$B$8,$C$3)) -> 0.02097737 | Z5: =$T$3*X5 -> 77563039 | AC5: =Parameters!B16*POWER(Parameters!$B$8,$C$3) -> 3.6974625e+09 | AD5: =$AD$3*Parameters!E16 -> 9.0812375e+08 | AE5: =AC5+AD5-W5 -> 4.2846198e+09 | AF5: =AC5-W5 -> 3.3764961e+09 | AG5: =AC5+AD5-Z5 -> 4.5280232e+09 | AH5: =AC5-Z5 -> 3.6198995e+09 | AI5: =($AA$3+$I$3)/10 -> 296054.13 | AJ5: =AE5/AI5 -> 14472.42 | AK5: =AF5/AI5 -> 11404.996 | AL5: =AG5/AI5 -> 15294.579 | AM5: =AH5/AI5 -> 12227.154 | AN5: =(POWER(AJ5, -0.26) - 1)/-0.26 -> 3.5275244 | AO5: =(AN5-$AN$4)*100 -> 8.3876377 | AP5: =(POWER(AJ5, -1) - 1)/-1 -> 0.9999309 | AQ5: =LOG(AJ5) -> 4.1605412 | AR5: =(POWER(AL5, -0.26) - 1)/-0.26 -> 3.5320691 | AS5: =(AR5-$AR$4)*100 -> 8.3729454 | AT5: =(POWER(AL5, -1) - 1)/-1 -> 0.99993462 | AU5: =LOG(AL5) -> 4.1845375 | AW5: =SQRT(AN5) -> 1.8781705 | BA5: =SQRT(AQ5) -> 2.0397405 | BE5: =SQRT(AR5) -> 1.87938 | BI5: =SQRT(AU5) -> 2.0456142 | BM5: =SQRT(CB5) -> 1.8727434 | BQ5: =SQRT(CD5) -> 2.0142232 | BU5: =SQRT(CE5) -> 1.8743659 | BY5: =SQRT(CG5) -> 2.0217135 | CB5: =(POWER(AK5, -0.26) - 1)/-0.26 -> 3.5071677 | CC5: =(CB5-$CB$4)*100 -> 16.489892 | CD5: =LOG(AK5) -> 4.0570951 | CE5: =(POWER(AM5, -0.26) - 1)/-0.26 -> 3.5132475 | CF5: =(CE5-$CE$4)*100 -> 15.755464 | CG5: =LOG(AM5) -> 4.0873254 | CH5: =SQRT(AP5) -> 0.99996545 | CI5: =SQRT(AT5) -> 0.99996731
A6: 3 | U6: =Parameters!C17 -> 0.031399077 | V6: =(U6*$T$3)/(Parameters!B17*POWER(Parameters!$B$8,$C$3)) -> 0.090753 | W6: =$T$3*U6 -> 6.9981421e+08 | X6: 0.010886748 | Y6: =(X6*$T$3)/(Parameters!B17*POWER(Parameters!$B$8,$C$3)) -> 0.031466055 | Z6: =$T$3*X6 -> 2.4264093e+08 | AC6: =Parameters!B17*POWER(Parameters!$B$8,$C$3) -> 7.7111964e+09 | AD6: =$AD$3*Parameters!E17 -> 8.0722111e+08 | AE6: =AC6+AD6-W6 -> 7.8186033e+09 | AF6: =AC6-W6 -> 7.0113822e+09 | AG6: =AC6+AD6-Z6 -> 8.2757766e+09 | AH6: =AC6-Z6 -> 7.4685555e+09 | AI6: =($AA$3+$I$3)/10 -> 296054.13 | AJ6: =AE6/AI6 -> 26409.371 | AK6: =AF6/AI6 -> 23682.771 | AL6: =AG6/AI6 -> 27953.593 | AM6: =AH6/AI6 -> 25226.993 | AN6: =(POWER(AJ6, -0.26) - 1)/-0.26 -> 3.5736519 | AO6: =(AN6-$AN$4)*100 -> 13.000394 | AP6: =(POWER(AJ6, -1) - 1)/-1 -> 0.99996213 | AQ6: =LOG(AJ6) -> 4.4217581 | AR6: =(POWER(AL6, -0.26) - 1)/-0.26 -> 3.5776485 | AS6: =(AR6-$AR$4)*100 -> 12.930893 | AT6: =(POWER(AL6, -1) - 1)/-1 -> 0.99996423 | AU6: =LOG(AL6) -> 4.4464376 | AW6: =SQRT(AN6) -> 1.8904105 | BA6: =SQRT(AQ6) -> 2.1027977 | BE6: =SQRT(AR6) -> 1.8914673 | BI6: =SQRT(AU6) -> 2.1086578 | BM6: =SQRT(CB6) -> 1.8883381 | BQ6: =SQRT(CD6) -> 2.0915144 | BU6: =SQRT(CE6) -> 1.8895468 | BY6: =SQRT(CG6) -> 2.0980623 | CB6: =(POWER(AK6, -0.26) - 1)/-0.26 -> 3.5658209 | CC6: =(CB6-$CB$4)*100 -> 22.355206 | CD6: =LOG(AK6) -> 4.3744325 | CE6: =(POWER(AM6, -0.26) - 1)/-0.26 -> 3.5703873 | CF6: =(CE6-$CE$4)*100 -> 21.469439 | CG6: =LOG(AM6) -> 4.4018655 | CH6: =SQRT(AP6) -> 0.99998107 | CI6: =SQRT(AT6) -> 0.99998211
A7: 4 | U7: =Parameters!C18 -> 0.051692243 | V7: =(U7*$T$3)/(Parameters!B18*POWER(Parameters!$B$8,$C$3)) -> 0.094698783 | W7: =$T$3*U7 -> 1.1521028e+09 | X7: 0.022901399 | Y7: =(X7*$T$3)/(Parameters!B18*POWER(Parameters!$B$8,$C$3)) -> 0.04195474 | Z7: =$T$3*X7 -> 5.1042023e+08 | AC7: =Parameters!B18*POWER(Parameters!$B$8,$C$3) -> 1.2165973e+10 | AD7: =$AD$3*Parameters!E18 -> 7.0631848e+08 | AE7: =AC7+AD7-W7 -> 1.1720189e+10 | AF7: =AC7-W7 -> 1.101387e+10 | AG7: =AC7+AD7-Z7 -> 1.2361871e+10 | AH7: =AC7-Z7 -> 1.1655553e+10 | AI7: =($AA$3+$I$3)/10 -> 296054.13 | AJ7: =AE7/AI7 -> 39587.992 | AK7: =AF7/AI7 -> 37202.218 | AL7: =AG7/AI7 -> 41755.443 | AM7: =AH7/AI7 -> 39369.668 | AN7: =(POWER(AJ7, -0.26) - 1)/-0.26 -> 3.600875 | AO7: =(AN7-$AN$4)*100 -> 15.722698 | AP7: =(POWER(AJ7, -1) - 1)/-1 -> 0.99997474 | AQ7: =LOG(AJ7) -> 4.5975635 | AR7: =(POWER(AL7, -0.26) - 1)/-0.26 -> 3.6042508 | AS7: =(AR7-$AR$4)*100 -> 15.591124 | AT7: =(POWER(AL7, -1) - 1)/-1 -> 0.99997605 | AU7: =LOG(AL7) -> 4.6207131 | AW7: =SQRT(AN7) -> 1.8975972 | BA7: =SQRT(AQ7) -> 2.144193 | BE7: =SQRT(AR7) -> 1.8984865 | BI7: =SQRT(AU7) -> 2.1495844 | BM7: =SQRT(CB7) -> 1.8965439 | BQ7: =SQRT(CD7) -> 2.1378889 | BU7: =SQRT(CE7) -> 1.8975042 | BY7: =SQRT(CG7) -> 2.1436328 | CB7: =(POWER(AK7, -0.26) - 1)/-0.26 -> 3.5968788 | CC7: =(CB7-$CB$4)*100 -> 25.461003 | CD7: =LOG(AK7) -> 4.5705688 | CE7: =(POWER(AM7, -0.26) - 1)/-0.26 -> 3.600522 | CF7: =(CE7-$CE$4)*100 -> 24.482916 | CG7: =LOG(AM7) -> 4.5951618 | CH7: =SQRT(AP7) -> 0.99998737 | CI7: =SQRT(AT7) -> 0.99998803
A8: 5 | U8: =Parameters!C19 -> 0.070583126 | V8: =(U8*$T$3)/(Parameters!B19*POWER(Parameters!$B$8,$C$3)) -> 0.098644565 | W8: =$T$3*U8 -> 1.5731378e+09 | X8: 0.037524833 | Y8: =(X8*$T$3)/(Parameters!B19*POWER(Parameters!$B$8,$C$3)) -> 0.052443425 | Z8: =$T$3*X8 -> 8.3634341e+08 | AC8: =Parameters!B19*POWER(Parameters!$B$8,$C$3) -> 1.5947536e+10 | AD8: =$AD$3*Parameters!E19 -> 6.0541584e+08 | AE8: =AC8+AD8-W8 -> 1.4979814e+10 | AF8: =AC8-W8 -> 1.4374398e+10 | AG8: =AC8+AD8-Z8 -> 1.5716609e+10 | AH8: =AC8-Z8 -> 1.5111193e+10 | AI8: =($AA$3+$I$3)/10 -> 296054.13 | AJ8: =AE8/AI8 -> 50598.227 | AK8: =AF8/AI8 -> 48553.278 | AL8: =AG8/AI8 -> 53086.942 | AM8: =AH8/AI8 -> 51041.993 | AN8: =(POWER(AJ8, -0.26) - 1)/-0.26 -> 3.6160354 | AO8: =(AN8-$AN$4)*100 -> 17.238738 | AP8: =(POWER(AJ8, -1) - 1)/-1 -> 0.99998024 | AQ8: =LOG(AJ8) -> 4.7041353 | AR8: =(POWER(AL8, -0.26) - 1)/-0.26 -> 3.6188903 | AS8: =(AR8-$AR$4)*100 -> 17.055066 | AT8: =(POWER(AL8, -1) - 1)/-1 -> 0.99998116 | AU8: =LOG(AL8) -> 4.7249877 | AW8: =SQRT(AN8) -> 1.9015876 | BA8: =SQRT(AQ8) -> 2.1689019 | BE8: =SQRT(AR8) -> 1.9023381 | BI8: =SQRT(AU8) -> 2.1737037 | BM8: =SQRT(CB8) -> 1.900935 | BQ8: =SQRT(CD8) -> 2.1647676 | BU8: =SQRT(CE8) -> 1.9017248 | BY8: =SQRT(CG8) -> 2.1697759 | CB8: =(POWER(AK8, -0.26) - 1)/-0.26 -> 3.6135538 | CC8: =(CB8-$CB$4)*100 -> 27.128498 | CD8: =LOG(AK8) -> 4.6862186 | CE8: =(POWER(AM8, -0.26) - 1)/-0.26 -> 3.6165572 | CF8: =(CE8-$CE$4)*100 -> 26.086436 | CG8: =LOG(AM8) -> 4.7079276 | CH8: =SQRT(AP8) -> 0.99999012 | CI8: =SQRT(AT8) -> 0.99999058
A9: 6 | U9: =Parameters!C20 -> 0.090905111 | V9: =(U9*$T$3)/(Parameters!B20*POWER(Parameters!$B$8,$C$3)) -> 0.10653613 | W9: =$T$3*U9 -> 2.0260687e+09 | X9: 0.053698687 | Y9: =(X9*$T$3)/(Parameters!B20*POWER(Parameters!$B$8,$C$3)) -> 0.062932109 | Z9: =$T$3*X9 -> 1.1968219e+09 | AC9: =Parameters!B20*POWER(Parameters!$B$8,$C$3) -> 1.9017667e+10 | AD9: =$AD$3*Parameters!E20 -> 5.045132e+08 | AE9: =AC9+AD9-W9 -> 1.7496112e+10 | AF9: =AC9-W9 -> 1.6991599e+10 | AG9: =AC9+AD9-Z9 -> 1.8325359e+10 | AH9: =AC9-Z9 -> 1.7820846e+10 | AI9: =($AA$3+$I$3)/10 -> 296054.13 | AJ9: =AE9/AI9 -> 59097.679 | AK9: =AF9/AI9 -> 57393.554 | AL9: =AG9/AI9 -> 61898.676 | AM9: =AH9/AI9 -> 60194.551 | AN9: =(POWER(AJ9, -0.26) - 1)/-0.26 -> 3.6251406 | AO9: =(AN9-$AN$4)*100 -> 18.149259 | AP9: =(POWER(AJ9, -1) - 1)/-1 -> 0.99998308 | AQ9: =LOG(AJ9) -> 4.7715704 | AR9: =(POWER(AL9, -0.26) - 1)/-0.26 -> 3.6277856 | AS9: =(AR9-$AR$4)*100 -> 17.944599 | AT9: =(POWER(AL9, -1) - 1)/-1 -> 0.99998384 | AU9: =LOG(AL9) -> 4.7916814 | AW9: =SQRT(AN9) -> 1.9039802 | BA9: =SQRT(AQ9) -> 2.1843925 | BE9: =SQRT(AR9) -> 1.9046747 | BI9: =SQRT(AU9) -> 2.1889909 | BM9: =SQRT(CB9) -> 1.9035369 | BQ9: =SQRT(CD9) -> 2.1814819 | BU9: =SQRT(CE9) -> 1.904257 | BY9: =SQRT(CG9) -> 2.1862198 | CB9: =(POWER(AK9, -0.26) - 1)/-0.26 -> 3.6234528 | CC9: =(CB9-$CB$4)*100 -> 28.118401 | CD9: =LOG(AK9) -> 4.7588631 | CE9: =(POWER(AM9, -0.26) - 1)/-0.26 -> 3.6261948 | CF9: =(CE9-$CE$4)*100 -> 27.050194 | CG9: =LOG(AM9) -> 4.7795572 | CH9: =SQRT(AP9) -> 0.99999154 | CI9: =SQRT(AT9) -> 0.99999192
A10: 7 | U10: =Parameters!C21 -> 0.11035602 | V10: =(U10*$T$3)/(Parameters!B21*POWER(Parameters!$B$8,$C$3)) -> 0.11048191 | W10: =$T$3*U10 -> 2.4595854e+09 | X10: 0.083813868 | Y10: =(X10*$T$3)/(Parameters!B21*POWER(Parameters!$B$8,$C$3)) -> 0.083909479 | Z10: =$T$3*X10 -> 1.868021e+09 | AC10: =Parameters!B21*POWER(Parameters!$B$8,$C$3) -> 2.2262336e+10 | AD10: =$AD$3*Parameters!E21 -> 4.0361056e+08 | AE10: =AC10+AD10-W10 -> 2.0206361e+10 | AF10: =AC10-W10 -> 1.980275e+10 | AG10: =AC10+AD10-Z10 -> 2.0797925e+10 | AH10: =AC10-Z10 -> 2.0394315e+10 | AI10: =($AA$3+$I$3)/10 -> 296054.13 | AJ10: =AE10/AI10 -> 68252.251 | AK10: =AF10/AI10 -> 66888.951 | AL10: =AG10/AI10 -> 70250.414 | AM10: =AH10/AI10 -> 68887.114 | AN10: =(POWER(AJ10, -0.26) - 1)/-0.26 -> 3.6332634 | AO10: =(AN10-$AN$4)*100 -> 18.961537 | AP10: =(POWER(AJ10, -1) - 1)/-1 -> 0.99998535 | AQ10: =LOG(AJ10) -> 4.834117 | AR10: =(POWER(AL10, -0.26) - 1)/-0.26 -> 3.6348546 | AS10: =(AR10-$AR$4)*100 -> 18.651499 | AT10: =(POWER(AL10, -1) - 1)/-1 -> 0.99998577 | AU10: =LOG(AL10) -> 4.8466489 | AW10: =SQRT(AN10) -> 1.9061121 | BA10: =SQRT(AQ10) -> 2.1986625 | BE10: =SQRT(AR10) -> 1.9065295 | BI10: =SQRT(AU10) -> 2.2015106 | BM10: =SQRT(CB10) -> 1.9058184 | BQ10: =SQRT(CD10) -> 2.1966689 | BU10: =SQRT(CE10) -> 1.9062464 | BY10: =SQRT(CG10) -> 2.1995768 | CB10: =(POWER(AK10, -0.26) - 1)/-0.26 -> 3.6321436 | CC10: =(CB10-$CB$4)*100 -> 28.987482 | CD10: =LOG(AK10) -> 4.8253544 | CE10: =(POWER(AM10, -0.26) - 1)/-0.26 -> 3.6337752 | CF10: =(CE10-$CE$4)*100 -> 27.808236 | CG10: =LOG(AM10) -> 4.838138 | CH10: =SQRT(AP10) -> 0.99999267 | CI10: =SQRT(AT10) -> 0.99999288
A11: 8 | U11: =Parameters!C22 -> 0.13623162 | V11: =(U11*$T$3)/(Parameters!B22*POWER(Parameters!$B$8,$C$3)) -> 0.1144277 | W11: =$T$3*U11 -> 3.0362937e+09 | X11: 0.13736006 | Y11: =(X11*$T$3)/(Parameters!B22*POWER(Parameters!$B$8,$C$3)) -> 0.11537553 | Z11: =$T$3*X11 -> 3.0614442e+09 | AC11: =Parameters!B22*POWER(Parameters!$B$8,$C$3) -> 2.6534605e+10 | AD11: =$AD$3*Parameters!E22 -> 3.0270792e+08 | AE11: =AC11+AD11-W11 -> 2.3801019e+10 | AF11: =AC11-W11 -> 2.3498311e+10 | AG11: =AC11+AD11-Z11 -> 2.3775869e+10 | AH11: =AC11-Z11 -> 2.3473161e+10 | AI11: =($AA$3+$I$3)/10 -> 296054.13 | AJ11: =AE11/AI11 -> 80394.146 | AK11: =AF11/AI11 -> 79371.671 | AL11: =AG11/AI11 -> 80309.194 | AM11: =AH11/AI11 -> 79286.719 | AN11: =(POWER(AJ11, -0.26) - 1)/-0.26 -> 3.6421359 | AO11: =(AN11-$AN$4)*100 -> 19.848794 | AP11: =(POWER(AJ11, -1) - 1)/-1 -> 0.99998756 | AQ11: =LOG(AJ11) -> 4.9052244 | AR11: =(POWER(AL11, -0.26) - 1)/-0.26 -> 3.6420798 | AS11: =(AR11-$AR$4)*100 -> 19.374023 | AT11: =(POWER(AL11, -1) - 1)/-1 -> 0.99998755 | AU11: =LOG(AL11) -> 4.9047653 | AW11: =SQRT(AN11) -> 1.9084381 | BA11: =SQRT(AQ11) -> 2.2147741 | BE11: =SQRT(AR11) -> 1.9084234 | BI11: =SQRT(AU11) -> 2.2146705 | BM11: =SQRT(CB11) -> 1.9082599 | BQ11: =SQRT(CD11) -> 2.2135188 | BU11: =SQRT(CE11) -> 1.908245 | BY11: =SQRT(CG11) -> 2.2134138 | CB11: =(POWER(AK11, -0.26) - 1)/-0.26 -> 3.6414558 | CC11: =(CB11-$CB$4)*100 -> 29.918704 | CD11: =LOG(AK11) -> 4.8996655 | CE11: =(POWER(AM11, -0.26) - 1)/-0.26 -> 3.6413988 | CF11: =(CE11-$CE$4)*100 -> 28.570596 | CG11: =LOG(AM11) -> 4.8992004 | CH11: =SQRT(AP11) -> 0.99999378 | CI11: =SQRT(AT11) -> 0.99999377
A12: 9 | U12: =Parameters!C23 -> 0.17539672 | V12: =(U12*$T$3)/(Parameters!B23*POWER(Parameters!$B$8,$C$3)) -> 0.11837348 | W12: =$T$3*U12 -> 3.9091951e+09 | X12: 0.21757858 | Y12: =(X12*$T$3)/(Parameters!B23*POWER(Parameters!$B$8,$C$3)) -> 0.14684159 | Z12: =$T$3*X12 -> 4.849333e+09 | AC12: =Parameters!B23*POWER(Parameters!$B$8,$C$3) -> 3.3024248e+10 | AD12: =$AD$3*Parameters!E23 -> 2.0180528e+08 | AE12: =AC12+AD12-W12 -> 2.9316858e+10 | AF12: =AC12-W12 -> 2.9115053e+10 | AG12: =AC12+AD12-Z12 -> 2.837672e+10 | AH12: =AC12-Z12 -> 2.8174915e+10 | AI12: =($AA$3+$I$3)/10 -> 296054.13 | AJ12: =AE12/AI12 -> 99025.33 | AK12: =AF12/AI12 -> 98343.68 | AL12: =AG12/AI12 -> 95849.769 | AM12: =AH12/AI12 -> 95168.119 | AN12: =(POWER(AJ12, -0.26) - 1)/-0.26 -> 3.652898 | AO12: =(AN12-$AN$4)*100 -> 20.925002 | AP12: =(POWER(AJ12, -1) - 1)/-1 -> 0.9999899 | AQ12: =LOG(AJ12) -> 4.9957463 | AR12: =(POWER(AL12, -0.26) - 1)/-0.26 -> 3.6512533 | AS12: =(AR12-$AR$4)*100 -> 20.291373 | AT12: =(POWER(AL12, -1) - 1)/-1 -> 0.99998957 | AU12: =LOG(AL12) -> 4.9815911 | AW12: =SQRT(AN12) -> 1.9112556 | BA12: =SQRT(AQ12) -> 2.2351166 | BE12: =SQRT(AR12) -> 1.9108253 | BI12: =SQRT(AU12) -> 2.2319478 | BM12: =SQRT(CB12) -> 1.9111647 | BQ12: =SQRT(CD12) -> 2.2344454 | BU12: =SQRT(CE12) -> 1.9107306 | BY12: =SQRT(CG12) -> 2.2312533 | CB12: =(POWER(AK12, -0.26) - 1)/-0.26 -> 3.6525506 | CC12: =(CB12-$CB$4)*100 -> 31.028183 | CD12: =LOG(AK12) -> 4.9927465 | CE12: =(POWER(AM12, -0.26) - 1)/-0.26 -> 3.6508913 | CF12: =(CE12-$CE$4)*100 -> 29.519846 | CG12: =LOG(AM12) -> 4.9784915 | CH12: =SQRT(AP12) -> 0.99999495 | CI12: =SQRT(AT12) -> 0.99999478
A13: 10 | U13: =Parameters!C24 -> 0.3154254 | V13: =(U13*$T$3)/(Parameters!B24*POWER(Parameters!$B$8,$C$3)) -> 0.12231926 | W13: =$T$3*U13 -> 7.0301167e+09 | X13: 0.43275574 | Y13: =(X13*$T$3)/(Parameters!B24*POWER(Parameters!$B$8,$C$3)) -> 0.16781896 | Z13: =$T$3*X13 -> 9.6451438e+09 | AC13: =Parameters!B24*POWER(Parameters!$B$8,$C$3) -> 5.7473505e+10 | AD13: =$AD$3*Parameters!E24 -> 1.0090264e+08 | AE13: =AC13+AD13-W13 -> 5.0544291e+10 | AF13: =AC13-W13 -> 5.0443389e+10 | AG13: =AC13+AD13-Z13 -> 4.7929264e+10 | AH13: =AC13-Z13 -> 4.7828362e+10 | AI13: =($AA$3+$I$3)/10 -> 296054.13 | AJ13: =AE13/AI13 -> 170726.52 | AK13: =AF13/AI13 -> 170385.69 | AL13: =AG13/AI13 -> 161893.58 | AM13: =AH13/AI13 -> 161552.76 | AN13: =(POWER(AJ13, -0.26) - 1)/-0.26 -> 3.678417 | AO13: =(AN13-$AN$4)*100 -> 23.476904 | AP13: =(POWER(AJ13, -1) - 1)/-1 -> 0.99999414 | AQ13: =LOG(AJ13) -> 5.232301 | AR13: =(POWER(AL13, -0.26) - 1)/-0.26 -> 3.6760841 | AS13: =(AR13-$AR$4)*100 -> 22.774454 | AT13: =(POWER(AL13, -1) - 1)/-1 -> 0.99999382 | AU13: =LOG(AL13) -> 5.2092296 | AW13: =SQRT(AN13) -> 1.91792 | BA13: =SQRT(AQ13) -> 2.2874223 | BE13: =SQRT(AR13) -> 1.9173117 | BI13: =SQRT(AU13) -> 2.2823737 | BM13: =SQRT(CB13) -> 1.9178972 | BQ13: =SQRT(CD13) -> 2.2872326 | BU13: =SQRT(CE13) -> 1.9172874 | BY13: =SQRT(CG13) -> 2.2821732 | CB13: =(POWER(AK13, -0.26) - 1)/-0.26 -> 3.6783299 | CC13: =(CB13-$CB$4)*100 -> 33.606106 | CD13: =LOG(AK13) -> 5.2314331 | CE13: =(POWER(AM13, -0.26) - 1)/-0.26 -> 3.6759909 | CF13: =(CE13-$CE$4)*100 -> 32.029805 | CG13: =LOG(AM13) -> 5.2083144 | CH13: =SQRT(AP13) -> 0.99999707 | CI13: =SQRT(AT13) -> 0.99999691
A15: Decile | B15: Year | D15: NZS income per recipient | U15: Baseline tax | X15: Progressive tax | AA15: Size tax paying group by income group | AC15: Gross income | AE15: Net Income Baseline | AG15: Net income Progressive | AI15: Decile size | AJ15: Average income pp Baseline | AL15: Average income pp progressive | AN15: Utility score baseline tax post-NZS income | AR15: Utility score progressive tax post-NZS income | AV15: Welfare score baseline tax post-NZS income isoelastic utility | AZ15: Welfare score baseline tax post-NZS income log utility | BD15: Welfare score progressive tax post-NZS income isoelastic utility | BH15: Welfare score progressive tax post-NZS income log utility | BL15: Welfare score baseline tax pre-NZS income isoelastic utility | BP15: Welfare score baseline tax pre-NZS income log utility | BT15: Welfare score progressive tax pre-NZS income isoelastic utility | BX15: Welfare score progressive tax pre-NZS income log utility | CB15: Utility score baseline tax pre-NZS income | CE15: Utility score progressive tax pre-NZS income
B16: Year | C16: Years since base | D16: Base year annual rate singles | E16: Base year annual rate couples | F16: Mulitplier | G16: Current year real rate singles | H16: Current year annual rate couples | I16: 65+ employed population current year | J16: Single | K16: In a relationship | L16: NZS paid singles rate | M16: NZS paid couples rate | N16: NZS paid total to employed 65+ | O16: Total 65+ population | P16: Single | Q16: In a relationship | R16: NZS paid singles rate | S16: NZS paid couples rate | T16: NZS paid total to 65+ | U16: Revenue share | V16: Implied effective tax rate | W16: Decile NZS cost | X16: Revenue share | Y16: Implied effective tax rate | Z16: Decile NZS cost | AA16: Employed working age pop current year | AB16: Total tax paying population | AC16: Employment income | AD16: Pension income | AE16: Total income | AF16: Total income without NZS | AG16: Total income | AH16: Total income without NZS | AJ16: post-NZS | AK16: pre-NZS | AL16: post-NZS | AM16: pre-NZS | AN16: Isoelastic p = 1.26 | AO16: Isoelastic p= 1.26 normalised | AP16: Isoelastic p = 2 | AQ16: Isoelsatic p = 1 | AR16: Isoelastic p = 1.26 | AS16: Isoelastic p = 1.26 normalised | AT16: Isoelastic p = 2 | AU16: Isoelsatic p = 1 | AV16: Utilitarian | AW16: Adjusted score | AX16: Prioritarian | AY16: Maximin | AZ16: Utilitarian | BA16: Adjusted score | BB16: Prioritarian | BC16: Maximin | BD16: Utilitarian | BE16: Adjusted score | BF16: Prioritarian | BG16: Maximin | BH16: Utilitarian | BI16: Adjusted score | BJ16: Prioritarian | BK16: Maximin | BL16: Utilitarian | BM16: Adjusted score | BN16: Prioritarian | BO16: Maximin | BP16: Utilitarian | BQ16: Adjusted score | BR16: Prioritarian | BS16: Maximin | BT16: Utilitarian | BU16: Adjusted score | BV16: Prioritarian | BW16: Maximin | BX16: Utilitarian | BY16: Adjusted score | BZ16: Prioritarian | CA16: Maximin | CB16: Isoelsatic p = 1.26 | CC16: Isoelastic normalised | CD16: Isoelsatic p = 1 | CE16: Isoelsatic p = 1.26 | CF16: Isoelastic p = 1.26 normalised | CG16: Isoelsatic p = 1
A17: Overall | B17: 2040 | C17: 16 | D17: =Parameters!$B$4 -> 27012.44 | E17: =Parameters!$B$5 -> 20778.68 | F17: =Parameters!$B$8 -> 1.01088 | G17: =D17*POWER(F17,C17) -> 32118.665 | H17: =E17*POWER(F17,C17) -> 24706.523 | I17: =Parameters!B3*Parameters!B40 -> 320687.1 | J17: =I17*Parameters!$B$10 -> 134688.58 | K17: =I17*Parameters!$B$9 -> 185998.52 | L17: =J17*G17 -> 4.3260174e+09 | M17: =K17*H17 -> 4.5953766e+09 | N17: =M17+L17 -> 8.921394e+09 | O17: =Parameters!B40 -> 1287900 | P17: =O17*Parameters!$B$10 -> 540918 | Q17: =O17*Parameters!$B$9 -> 746982 | R17: =P17*G17 -> 1.7373564e+10 | S17: =Q17*H17 -> 1.8455328e+10 | T17: =S17+R17 -> 3.5828892e+10 | W17: =SUM(W18:W27) -> 3.5828892e+10 | Z17: =SUM(Z18:Z27) -> 3.5828892e+10 | AA17: =Parameters!C40*Parameters!B2 -> 3054491 | AB17: =AA17+I17 -> 3375178.1 | AC17: =SUM(AC18:AC27) -> 2.3114432e+11 | AD17: =N17 -> 8.921394e+09 | AE17: =AC17+AD17-W17 -> 2.0423682e+11 | AF17: =AC17-W17 -> 1.9531543e+11 | AG17: =AC17+AD17-Z17 -> 2.0423682e+11 | AH17: =AC17-Z17 -> 1.9531543e+11 | AP17: Sensitivity check | AQ17: Sensitivity check | AT17: Sensitivity check | AU17: Sensitivity check | AV17: =SUM(AO18:AO27) -> 161.99809 | AW17: Prioritarian | AX17: =SUM(AW18:AW27) -> 18.964346 | AY17: =MIN(AN19:AN27) -> 3.5242158 | AZ17: =SUM(AQ18:AQ27) -> 46.23521 | BB17: =SUM(BA18:BA27) -> 21.480292 | BC17: =MIN(AQ19:AQ27) -> 4.1432858 | BD17: =SUM(AS18:AS27) -> 157.62497 | BF17: =SUM(BE18:BE27) -> 18.971984 | BG17: =MIN(AR19:AR27) -> 3.5308478 | BH17: =SUM(AU18:AU27) -> 46.389508 | BJ17: =SUM(BI17:BI27) -> 21.51794 | BK17: =MIN(AU19:AU27) -> 4.1780551 | BL17: =SUM(CB18:CB27) -> 35.837402 | BN17: =SUM(BM18:BM27) -> 18.929127 | BO17: =MIN(CB19:CB27) -> 3.5057082 | BP17: =SUM(CD18:CD27) -> 45.682559 | BR17: =SUM(BQ18:BQ27) -> 21.338952 | BS17: =MIN(CD19:CD27) -> 4.0499186 | BT17: =SUM(CE18:CE27) -> 35.881174 | BV17: =SUM(BU18:BU27) -> 18.940889 | BW17: =MIN(CE19:CE27) -> 3.5143029 | BX17: =SUM(CG18:CG27) -> 45.886016 | BZ17: =SUM(BY17:BY27) -> 21.389996 | CA17: =MIN(CG19:CG27) -> 4.092629 | CB17: =Parameters!AO19 -> 0
A18: 1 | U18: {=Parameters!C15:C24} -> 0.0036096394 | V18: =(U18*$T$17)/(Parameters!B15*POWER(Parameters!$B$8, $C$17)) -> 0.13628442 | W18: =$T$17*U18 -> 1.2932938e+08 | X18: =Parameters!D15 -> 0 | Y18: =(X18*$T$17)/(Parameters!B15*POWER(Parameters!$B$8, $C$17)) -> 0 | Z18: =$T$17*X18 -> 0 | AC18: =Parameters!B15*POWER(Parameters!$B$8, $C$17) -> 9.4896671e+08 | AD18: =$AD$3*Parameters!E15 -> 1.0090264e+09 | AE18: =AC18+AD18-W18 -> 1.8286637e+09 | AF18: =AC18-W18 -> 8.1963733e+08 | AG18: =AC18+AD18-Z18 -> 1.9579931e+09 | AH18: =AC18-Z18 -> 9.4896671e+08 | AI18: =($AA$17+$I$17)/10 -> 337517.81 | AJ18: =AE18/AI18 -> 5417.977 | AK18: =AF18/AI18 -> 2428.4269 | AL18: =AG18/AI18 -> 5801.1549 | AM18: =AH18/AI18 -> 2811.6049 | AN18: =(POWER(AJ18, -0.26) - 1)/-0.26 -> 3.4347873 | AO18: =(AN18-$AN$18)*100 -> 0 | AP18: =(POWER(AJ18, -1) - 1)/-1 -> 0.99981543 | AQ18: =LOG(AJ18) -> 3.7338372 | AR18: =(POWER(AL18, -0.26) - 1)/-0.26 -> 3.4420315 | AS18: =(AR18-$AR$18)*100 -> 0 | AT18: =(POWER(AL18, -1) - 1)/-1 -> 0.99982762 | AU18: =LOG(AL18) -> 3.7635145 | AW18: {=SQRT(AN18:AN27)} -> 1.8533179 | BA18: =SQRT(AQ18) -> 1.9323139 | BE18: {=SQRT(AR18:AR27)} -> 1.8552713 | BI18: =SQRT(AU18) -> 1.939978 | BM18: =SQRT(CB18) -> 1.8273881 | BQ18: =SQRT(CD18) -> 1.8399253 | BU18: =SQRT(CE18) -> 1.8325638 | BY18: =SQRT(CG18) -> 1.857136 | CB18: =(POWER(AK18, -0.26) - 1)/-0.26 -> 3.3393474 | CC18: =(CB18-$CB$4)*100 -> -0.29214163 | CD18: =LOG(AK18) -> 3.385325 | CE18: =(POWER(AM18, -0.26) - 1)/-0.26 -> 3.3582901 | CF18: =(CE18-$CE$4)*100 -> 0.2597229 | CG18: =LOG(AM18) -> 3.4489543
A19: 2 | U19: 0.014401036 | V19: =(U19*$T$17)/(Parameters!B16*POWER(Parameters!$B$8, $C$17)) -> 0.11993029 | W19: =$T$17*U19 -> 5.1597317e+08 | X19: =Parameters!D16 -> 0.0034800777 | Y19: =(X19*$T$17)/(Parameters!B16*POWER(Parameters!$B$8, $C$17)) -> 0.028981715 | Z19: =$T$17*X19 -> 1.2468733e+08 | AC19: =Parameters!B16*POWER(Parameters!$B$8, $C$17) -> 4.3022757e+09 | AD19: =$AD$3*Parameters!E16 -> 9.0812375e+08 | AE19: =AC19+AD19-W19 -> 4.6944263e+09 | AF19: =AC19-W19 -> 3.7863026e+09 | AG19: =AC19+AD19-Z19 -> 5.0857121e+09 | AH19: =AC19-Z19 -> 4.1775884e+09 | AI19: =($AA$17+$I$17)/10 -> 337517.81 | AJ19: =AE19/AI19 -> 13908.677 | AK19: =AF19/AI19 -> 11218.082 | AL19: =AG19/AI19 -> 15067.982 | AM19: =AH19/AI19 -> 12377.387 | AN19: =(POWER(AJ19, -0.26) - 1)/-0.26 -> 3.5242158 | AO19: =(AN19-$AN$18)*100 -> 8.9428496 | AP19: =(POWER(AJ19, -1) - 1)/-1 -> 0.9999281 | AQ19: =LOG(AJ19) -> 4.1432858 | AR19: =(POWER(AL19, -0.26) - 1)/-0.26 -> 3.5308478 | AS19: =(AR19-$AR$18)*100 -> 8.8816301 | AT19: =(POWER(AL19, -1) - 1)/-1 -> 0.99993363 | AU19: =LOG(AL19) -> 4.1780551 | AW19: 1.8772895 | BA19: =SQRT(AQ19) -> 2.0355063 | BE19: 1.879055 | BI19: =SQRT(AU19) -> 2.0440291 | BM19: =SQRT(CB19) -> 1.8723536 | BQ19: =SQRT(CD19) -> 2.012441 | BU19: =SQRT(CE19) -> 1.8746474 | BY19: =SQRT(CG19) -> 2.0230247 | CB19: =(POWER(AK19, -0.26) - 1)/-0.26 -> 3.5057082 | CC19: =(CB19-$CB$4)*100 -> 16.343938 | CD19: =LOG(AK19) -> 4.0499186 | CE19: =(POWER(AM19, -0.26) - 1)/-0.26 -> 3.5143029 | CF19: =(CE19-$CE$4)*100 -> 15.860997 | CG19: =LOG(AM19) -> 4.092629
A20: 3 | U20: 0.031399077 | V20: =(U20*$T$17)/(Parameters!B17*POWER(Parameters!$B$8, $C$17)) -> 0.12538167 | W20: =$T$17*U20 -> 1.1249941e+09 | X20: =Parameters!D17 -> 0.010886748 | Y20: =(X20*$T$17)/(Parameters!B17*POWER(Parameters!$B$8, $C$17)) -> 0.043472572 | Z20: =$T$17*X20 -> 3.9006013e+08 | AC20: =Parameters!B17*POWER(Parameters!$B$8, $C$17) -> 8.972557e+09 | AD20: =$AD$3*Parameters!E17 -> 8.0722111e+08 | AE20: =AC20+AD20-W20 -> 8.6547839e+09 | AF20: =AC20-W20 -> 7.8475628e+09 | AG20: =AC20+AD20-Z20 -> 9.3897179e+09 | AH20: =AC20-Z20 -> 8.5824968e+09 | AI20: =($AA$17+$I$17)/10 -> 337517.81 | AJ20: =AE20/AI20 -> 25642.451 | AK20: =AF20/AI20 -> 23250.811 | AL20: =AG20/AI20 -> 27819.918 | AM20: =AH20/AI20 -> 25428.278 | AN20: =(POWER(AJ20, -0.26) - 1)/-0.26 -> 3.571556 | AO20: =(AN20-$AN$18)*100 -> 13.676869 | AP20: =(POWER(AJ20, -1) - 1)/-1 -> 0.999961 | AQ20: =LOG(AJ20) -> 4.4089595 | AR20: =(POWER(AL20, -0.26) - 1)/-0.26 -> 3.5773137 | AS20: =(AR20-$AR$18)*100 -> 13.528222 | AT20: =(POWER(AL20, -1) - 1)/-1 -> 0.99996405 | AU20: =LOG(AL20) -> 4.4443559 | AW20: 1.8898561 | BA20: =SQRT(AQ20) -> 2.0997523 | BE20: 1.8913788 | BI20: =SQRT(AU20) -> 2.1081641 | BM20: =SQRT(CB20) -> 1.887982 | BQ20: =SQRT(CD20) -> 2.0896024 | BU20: =SQRT(CE20) -> 1.8896975 | BY20: =SQRT(CG20) -> 2.0988847 | CB20: =(POWER(AK20, -0.26) - 1)/-0.26 -> 3.564476 | CC20: =(CB20-$CB$4)*100 -> 22.220716 | CD20: =LOG(AK20) -> 4.3664381 | CE20: =(POWER(AM20, -0.26) - 1)/-0.26 -> 3.5709565 | CF20: =(CE20-$CE$4)*100 -> 21.526362 | CG20: =LOG(AM20) -> 4.405317
A21: 4 | U21: 0.051692243 | V21: =(U21*$T$17)/(Parameters!B18*POWER(Parameters!$B$8, $C$17)) -> 0.13083304 | W21: =$T$17*U21 -> 1.8520758e+09 | X21: =Parameters!D18 -> 0.022901399 | Y21: =(X21*$T$17)/(Parameters!B18*POWER(Parameters!$B$8, $C$17)) -> 0.05796343 | Z21: =$T$17*X21 -> 8.2053173e+08 | AC21: =Parameters!B18*POWER(Parameters!$B$8, $C$17) -> 1.4156025e+10 | AD21: =$AD$3*Parameters!E18 -> 7.0631848e+08 | AE21: =AC21+AD21-W21 -> 1.3010267e+10 | AF21: =AC21-W21 -> 1.2303949e+10 | AG21: =AC21+AD21-Z21 -> 1.4041811e+10 | AH21: =AC21-Z21 -> 1.3335493e+10 | AI21: =($AA$17+$I$17)/10 -> 337517.81 | AJ21: =AE21/AI21 -> 38546.906 | AK21: =AF21/AI21 -> 36454.221 | AL21: =AG21/AI21 -> 41603.171 | AM21: =AH21/AI21 -> 39510.486 | AN21: =(POWER(AJ21, -0.26) - 1)/-0.26 -> 3.5991695 | AO21: =(AN21-$AN$18)*100 -> 16.438225 | AP21: =(POWER(AJ21, -1) - 1)/-1 -> 0.99997406 | AQ21: =LOG(AJ21) -> 4.5859895 | AR21: =(POWER(AL21, -0.26) - 1)/-0.26 -> 3.604021 | AS21: =(AR21-$AR$18)*100 -> 16.198948 | AT21: =(POWER(AL21, -1) - 1)/-1 -> 0.99997596 | AU21: =LOG(AL21) -> 4.6191264 | AW21: 1.8971477 | BA21: =SQRT(AQ21) -> 2.1414924 | BE21: 1.8984259 | BI21: =SQRT(AU21) -> 2.1492153 | BM21: =SQRT(CB21) -> 1.8961959 | BQ21: =SQRT(CD21) -> 2.1358249 | BU21: =SQRT(CE21) -> 1.8975642 | BY21: =SQRT(CG21) -> 2.1439945 | CB21: =(POWER(AK21, -0.26) - 1)/-0.26 -> 3.595559 | CC21: =(CB21-$CB$4)*100 -> 25.329015 | CD21: =LOG(AK21) -> 4.5617478 | CE21: =(POWER(AM21, -0.26) - 1)/-0.26 -> 3.60075 | CF21: =(CE21-$CE$4)*100 -> 24.505708 | CG21: =LOG(AM21) -> 4.5967124
A22: 5 | U22: 0.070583126 | V22: =(U22*$T$17)/(Parameters!B19*POWER(Parameters!$B$8, $C$17)) -> 0.13628442 | W22: =$T$17*U22 -> 2.5289152e+09 | X22: =Parameters!D19 -> 0.037524833 | Y22: =(X22*$T$17)/(Parameters!B19*POWER(Parameters!$B$8, $C$17)) -> 0.072454287 | Z22: =$T$17*X22 -> 1.3444732e+09 | AC22: =Parameters!B19*POWER(Parameters!$B$8, $C$17) -> 1.8556158e+10 | AD22: =$AD$3*Parameters!E19 -> 6.0541584e+08 | AE22: =AC22+AD22-W22 -> 1.6632658e+10 | AF22: =AC22-W22 -> 1.6027242e+10 | AG22: =AC22+AD22-Z22 -> 1.78171e+10 | AH22: =AC22-Z22 -> 1.7211684e+10 | AI22: =($AA$17+$I$17)/10 -> 337517.81 | AJ22: =AE22/AI22 -> 49279.35 | AK22: =AF22/AI22 -> 47485.62 | AL22: =AG22/AI22 -> 52788.623 | AM22: =AH22/AI22 -> 50994.893 | AN22: =(POWER(AJ22, -0.26) - 1)/-0.26 -> 3.6144497 | AO22: =(AN22-$AN$18)*100 -> 17.966244 | AP22: =(POWER(AJ22, -1) - 1)/-1 -> 0.99997971 | AQ22: =LOG(AJ22) -> 4.692665 | AR22: =(POWER(AL22, -0.26) - 1)/-0.26 -> 3.618557 | AS22: =(AR22-$AR$18)*100 -> 17.652556 | AT22: =(POWER(AL22, -1) - 1)/-1 -> 0.99998106 | AU22: =LOG(AL22) -> 4.7225403 | AW22: 1.9011706 | BA22: =SQRT(AQ22) -> 2.166256 | BE22: 1.9022505 | BI22: =SQRT(AU22) -> 2.1731407 | BM22: =SQRT(CB22) -> 1.9005802 | BQ22: =SQRT(CD22) -> 2.162536 | BU22: =SQRT(CE22) -> 1.9017103 | BY22: =SQRT(CG22) -> 2.1696835 | CB22: =(POWER(AK22, -0.26) - 1)/-0.26 -> 3.6122052 | CC22: =(CB22-$CB$4)*100 -> 26.993642 | CD22: =LOG(AK22) -> 4.6765621 | CE22: =(POWER(AM22, -0.26) - 1)/-0.26 -> 3.6165021 | CF22: =(CE22-$CE$4)*100 -> 26.080924 | CG22: =LOG(AM22) -> 4.7075267
A23: 6 | U23: 0.090905111 | V23: =(U23*$T$17)/(Parameters!B20*POWER(Parameters!$B$8, $C$17)) -> 0.14718717 | W23: =$T$17*U23 -> 3.2570294e+09 | X23: =Parameters!D20 -> 0.053698687 | Y23: =(X23*$T$17)/(Parameters!B20*POWER(Parameters!$B$8, $C$17)) -> 0.086945145 | Z23: =$T$17*X23 -> 1.9239644e+09 | AC23: =Parameters!B20*POWER(Parameters!$B$8, $C$17) -> 2.2128486e+10 | AD23: =$AD$3*Parameters!E20 -> 5.045132e+08 | AE23: =AC23+AD23-W23 -> 1.937597e+10 | AF23: =AC23-W23 -> 1.8871457e+10 | AG23: =AC23+AD23-Z23 -> 2.0709035e+10 | AH23: =AC23-Z23 -> 2.0204522e+10 | AI23: =($AA$17+$I$17)/10 -> 337517.81 | AJ23: =AE23/AI23 -> 57407.253 | AK23: =AF23/AI23 -> 55912.478 | AL23: =AG23/AI23 -> 61356.866 | AM23: =AH23/AI23 -> 59862.091 | AN23: =(POWER(AJ23, -0.26) - 1)/-0.26 -> 3.6234666 | AO23: =(AN23-$AN$18)*100 -> 18.867935 | AP23: =(POWER(AJ23, -1) - 1)/-1 -> 0.99998258 | AQ23: =LOG(AJ23) -> 4.7589668 | AR23: =(POWER(AL23, -0.26) - 1)/-0.26 -> 3.6272859 | AS23: =(AR23-$AR$18)*100 -> 18.525439 | AT23: =(POWER(AL23, -1) - 1)/-1 -> 0.9999837 | AU23: =LOG(AL23) -> 4.7878632 | AW23: 1.9035406 | BA23: =SQRT(AQ23) -> 2.1815056 | BE23: 1.9045435 | BI23: =SQRT(AU23) -> 2.1881186 | BM23: =SQRT(CB23) -> 1.9031379 | BQ23: =SQRT(CD23) -> 2.1788779 | BU23: =SQRT(CE23) -> 1.9041738 | BY23: =SQRT(CG23) -> 2.1856697 | CB23: =(POWER(AK23, -0.26) - 1)/-0.26 -> 3.6219338 | CC23: =(CB23-$CB$4)*100 -> 27.966503 | CD23: =LOG(AK23) -> 4.7475087 | CE23: =(POWER(AM23, -0.26) - 1)/-0.26 -> 3.6258779 | CF23: =(CE23-$CE$4)*100 -> 27.018498 | CG23: =LOG(AM23) -> 4.7771519
A24: 7 | U24: 0.11035602 | V24: =(U24*$T$17)/(Parameters!B21*POWER(Parameters!$B$8, $C$17)) -> 0.15263855 | W24: =$T$17*U24 -> 3.953934e+09 | X24: =Parameters!D21 -> 0.083813868 | Y24: =(X24*$T$17)/(Parameters!B21*POWER(Parameters!$B$8, $C$17)) -> 0.11592686 | Z24: =$T$17*X24 -> 3.002958e+09 | AC24: =Parameters!B21*POWER(Parameters!$B$8, $C$17) -> 2.5903902e+10 | AD24: =$AD$3*Parameters!E21 -> 4.0361056e+08 | AE24: =AC24+AD24-W24 -> 2.2353578e+10 | AF24: =AC24-W24 -> 2.1949968e+10 | AG24: =AC24+AD24-Z24 -> 2.3304554e+10 | AH24: =AC24-Z24 -> 2.2900944e+10 | AI24: =($AA$17+$I$17)/10 -> 337517.81 | AJ24: =AE24/AI24 -> 66229.33 | AK24: =AF24/AI24 -> 65033.51 | AL24: =AG24/AI24 -> 69046.888 | AM24: =AH24/AI24 -> 67851.068 | AN24: =(POWER(AJ24, -0.26) - 1)/-0.26 -> 3.6315915 | AO24: =(AN24-$AN$18)*100 -> 19.68042 | AP24: =(POWER(AJ24, -1) - 1)/-1 -> 0.9999849 | AQ24: =LOG(AJ24) -> 4.8210504 | AR24: =(POWER(AL24, -0.26) - 1)/-0.26 -> 3.6339031 | AS24: =(AR24-$AR$18)*100 -> 19.187164 | AT24: =(POWER(AL24, -1) - 1)/-1 -> 0.99998552 | AU24: =LOG(AL24) -> 4.8391441 | AW24: 1.9056735 | BA24: =SQRT(AQ24) -> 2.195689 | BE24: 1.9062799 | BI24: =SQRT(AU24) -> 2.1998055 | BM24: =SQRT(CB24) -> 1.9054062 | BQ24: =SQRT(CD24) -> 2.1938863 | BU24: =SQRT(CE24) -> 1.9060264 | BY24: =SQRT(CG24) -> 2.1980802 | CB24: =(POWER(AK24, -0.26) - 1)/-0.26 -> 3.6305726 | CC24: =(CB24-$CB$4)*100 -> 28.83038 | CD24: =LOG(AK24) -> 4.8131372 | CE24: =(POWER(AM24, -0.26) - 1)/-0.26 -> 3.6329368 | CF24: =(CE24-$CE$4)*100 -> 27.724392 | CG24: =LOG(AM24) -> 4.8315567
A25: 8 | U25: 0.13623162 | V25: =(U25*$T$17)/(Parameters!B22*POWER(Parameters!$B$8, $C$17)) -> 0.15808993 | W25: =$T$17*U25 -> 4.8810278e+09 | X25: =Parameters!D22 -> 0.13736006 | Y25: =(X25*$T$17)/(Parameters!B22*POWER(Parameters!$B$8, $C$17)) -> 0.15939943 | Z25: =$T$17*X25 -> 4.9214588e+09 | AC25: =Parameters!B22*POWER(Parameters!$B$8, $C$17) -> 3.0875008e+10 | AD25: =$AD$3*Parameters!E22 -> 3.0270792e+08 | AE25: =AC25+AD25-W25 -> 2.6296688e+10 | AF25: =AC25-W25 -> 2.5993981e+10 | AG25: =AC25+AD25-Z25 -> 2.6256257e+10 | AH25: =AC25-Z25 -> 2.595355e+10 | AI25: =($AA$17+$I$17)/10 -> 337517.81 | AJ25: =AE25/AI25 -> 77912.002 | AK25: =AF25/AI25 -> 77015.137 | AL25: =AG25/AI25 -> 77792.213 | AM25: =AH25/AI25 -> 76895.348 | AN25: =(POWER(AJ25, -0.26) - 1)/-0.26 -> 3.6404656 | AO25: =(AN25-$AN$18)*100 -> 20.56783 | AP25: =(POWER(AJ25, -1) - 1)/-1 -> 0.99998717 | AQ25: =LOG(AJ25) -> 4.8916044 | AR25: =(POWER(AL25, -0.26) - 1)/-0.26 -> 3.6403833 | AS25: =(AR25-$AR$18)*100 -> 19.83518 | AT25: =(POWER(AL25, -1) - 1)/-1 -> 0.99998715 | AU25: =LOG(AL25) -> 4.8909361 | AW25: 1.9080004 | BA25: =SQRT(AQ25) -> 2.2116972 | BE25: 1.9079788 | BI25: =SQRT(AU25) -> 2.2115461 | BM25: =SQRT(CB25) -> 1.9078379 | BQ25: =SQRT(CD25) -> 2.2105601 | BU25: =SQRT(CE25) -> 1.907816 | BY25: =SQRT(CG25) -> 2.2104072 | CB25: =(POWER(AK25, -0.26) - 1)/-0.26 -> 3.6398455 | CC25: =(CB25-$CB$4)*100 -> 29.757666 | CD25: =LOG(AK25) -> 4.8865761 | CE25: =(POWER(AM25, -0.26) - 1)/-0.26 -> 3.639762 | CF25: =(CE25-$CE$4)*100 -> 28.406907 | CG25: =LOG(AM25) -> 4.8859001
A26: 9 | U26: 0.17539672 | V26: =(U26*$T$17)/(Parameters!B23*POWER(Parameters!$B$8, $C$17)) -> 0.1635413 | W26: =$T$17*U26 -> 6.2842702e+09 | X26: =Parameters!D23 -> 0.21757858 | Y26: =(X26*$T$17)/(Parameters!B23*POWER(Parameters!$B$8, $C$17)) -> 0.202872 | Z26: =$T$17*X26 -> 7.7955994e+09 | AC26: =Parameters!B23*POWER(Parameters!$B$8, $C$17) -> 3.8426196e+10 | AD26: =$AD$3*Parameters!E23 -> 2.0180528e+08 | AE26: =AC26+AD26-W26 -> 3.2343731e+10 | AF26: =AC26-W26 -> 3.2141926e+10 | AG26: =AC26+AD26-Z26 -> 3.0832402e+10 | AH26: =AC26-Z26 -> 3.0630597e+10 | AI26: =($AA$17+$I$17)/10 -> 337517.81 | AJ26: =AE26/AI26 -> 95828.22 | AK26: =AF26/AI26 -> 95230.31 | AL26: =AG26/AI26 -> 91350.444 | AM26: =AH26/AI26 -> 90752.534 | AN26: =(POWER(AJ26, -0.26) - 1)/-0.26 -> 3.6512419 | AO26: =(AN26-$AN$18)*100 -> 21.645466 | AP26: =(POWER(AJ26, -1) - 1)/-1 -> 0.99998956 | AQ26: =LOG(AJ26) -> 4.9814934 | AR26: =(POWER(AL26, -0.26) - 1)/-0.26 -> 3.6488017 | AS26: =(AR26-$AR$18)*100 -> 20.677021 | AT26: =(POWER(AL26, -1) - 1)/-1 -> 0.99998905 | AU26: =LOG(AL26) -> 4.9607107 | AW26: 1.9108223 | BA26: =SQRT(AQ26) -> 2.2319259 | BE26: 1.9101837 | BI26: =SQRT(AU26) -> 2.2272653 | BM26: =SQRT(CB26) -> 1.9107393 | BQ26: =SQRT(CD26) -> 2.2313169 | BU26: =SQRT(CE26) -> 1.9100954 | BY26: =SQRT(CG26) -> 2.226625 | CB26: =(POWER(AK26, -0.26) - 1)/-0.26 -> 3.6509245 | CC26: =(CB26-$CB$4)*100 -> 30.86557 | CD26: =LOG(AK26) -> 4.9787752 | CE26: =(POWER(AM26, -0.26) - 1)/-0.26 -> 3.6484645 | CF26: =(CE26-$CE$4)*100 -> 29.277157 | CG26: =LOG(AM26) -> 4.9578588
A27: 10 | U27: 0.3154254 | V27: =(U27*$T$17)/(Parameters!B24*POWER(Parameters!$B$8, $C$17)) -> 0.16899268 | W27: =$T$17*U27 -> 1.1301343e+10 | X27: =Parameters!D24 -> 0.43275574 | Y27: =(X27*$T$17)/(Parameters!B24*POWER(Parameters!$B$8, $C$17)) -> 0.23185372 | Z27: =$T$17*X27 -> 1.5505159e+10 | AC27: =Parameters!B24*POWER(Parameters!$B$8, $C$17) -> 6.6874746e+10 | AD27: =$AD$3*Parameters!E24 -> 1.0090264e+08 | AE27: =AC27+AD27-W27 -> 5.5674306e+10 | AF27: =AC27-W27 -> 5.5573403e+10 | AG27: =AC27+AD27-Z27 -> 5.147049e+10 | AH27: =AC27-Z27 -> 5.1369587e+10 | AI27: =($AA$17+$I$17)/10 -> 337517.81 | AJ27: =AE27/AI27 -> 164952.2 | AK27: =AF27/AI27 -> 164653.25 | AL27: =AG27/AI27 -> 152497.11 | AM27: =AH27/AI27 -> 152198.15 | AN27: =(POWER(AJ27, -0.26) - 1)/-0.26 -> 3.6769097 | AO27: =(AN27-$AN$18)*100 -> 24.212246 | AP27: =(POWER(AJ27, -1) - 1)/-1 -> 0.99999394 | AQ27: =LOG(AJ27) -> 5.2173581 | AR27: =(POWER(AL27, -0.26) - 1)/-0.26 -> 3.6734195 | AS27: =(AR27-$AR$18)*100 -> 23.138805 | AT27: =(POWER(AL27, -1) - 1)/-1 -> 0.99999344 | AU27: =LOG(AL27) -> 5.1832616 | AW27: 1.917527 | BA27: =SQRT(AQ27) -> 2.2841537 | BE27: 1.9166167 | BI27: =SQRT(AU27) -> 2.2766778 | BM27: =SQRT(CB27) -> 1.9175062 | BQ27: =SQRT(CD27) -> 2.2839812 | BU27: =SQRT(CE27) -> 1.9165937 | BY27: =SQRT(CG27) -> 2.2764906 | CB27: =(POWER(AK27, -0.26) - 1)/-0.26 -> 3.6768299 | CC27: =(CB27-$CB$4)*100 -> 33.45611 | CD27: =LOG(AK27) -> 5.2165703 | CE27: =(POWER(AM27, -0.26) - 1)/-0.26 -> 3.6733314 | CF27: =(CE27-$CE$4)*100 -> 31.763849 | CG27: =LOG(AM27) -> 5.1824094
A29: Decile | B29: Year | D29: NZS income per recipient | U29: Baseline tax | X29: Progressive tax | AA29: Size tax paying group by income group | AC29: Gross income | AE29: Net Income Baseline | AG29: Net income Progressive | AI29: Decile size | AJ29: Average income pp Baseline | AL29: Average income pp progressive | AN29: Utility score baseline tax post-NZS income | AR29: Utility score progressive tax post-NZS income | AV29: Welfare score baseline tax post-NZS income isoelastic utility | AZ29: Welfare score baseline tax post-NZS income log utility | BD29: Welfare score progressive tax post-NZS income isoelastic utility | BH29: Welfare score progressive tax post-NZS income log utility | BL29: Welfare score baseline tax pre-NZS income isoelastic utility | BP29: Welfare score baseline tax pre-NZS income log utility | BT29: Welfare score progressive tax pre-NZS income isoelastic utility | BX29: Welfare score progressive tax pre-NZS income log utility | CB29: Utility score baseline tax pre-NZS income | CE29: Utility score progressive tax pre-NZS income
B30: Year | C30: Years since base | D30: Base year annual rate singles | E30: Base year annual rate couples | F30: Mulitplier | G30: Current year real rate singles | H30: Current year annual rate couples | I30: 65+ employed population current year | J30: Single | K30: In a relationship | L30: NZS paid singles rate | M30: NZS paid couples rate | N30: NZS paid total to employed 65+ | O30: Total 65+ population | P30: Single | Q30: In a relationship | R30: NZS paid singles rate | S30: NZS paid couples rate | T30: NZS paid total to 65+ | U30: Revenue share | V30: Implied effective tax rate | W30: Decile NZS cost | X30: Revenue share | Y30: Implied effective tax rate | Z30: Decile NZS cost | AA30: Employed working age pop current year | AB30: Total tax paying population | AC30: Employment income | AD30: Pension income | AE30: Total income | AF30: Total income without NZS | AG30: Total income | AH30: Total income without NZS | AJ30: post-NZS | AK30: pre-NZS | AL30: post-NZS | AM30: pre-NZS | AN30: Isoelastic p = 1.26 | AO30: Isoelastic p= 1.26 normalised | AP30: Isoelastic p = 2 | AQ30: Isoelsatic p = 1 | AR30: Isoelastic p = 1.26 | AS30: Isoelastic p = 1.26 normalised | AT30: Isoelastic p = 2 | AU30: Isoelsatic p = 1 | AV30: Utilitarian | AW30: Adjusted score | AX30: Prioritarian | AY30: Maximin | AZ30: Utilitarian | BA30: Adjusted score | BB30: Prioritarian | BC30: Maximin | BD30: Utilitarian | BE30: Adjusted score | BF30: Prioritarian | BG30: Maximin | BH30: Utilitarian | BI30: Adjusted score | BJ30: Prioritarian | BK30: Maximin | BL30: Utilitarian | BM30: Adjusted score | BN30: Prioritarian | BO30: Maximin | BP30: Utilitarian | BQ30: Adjusted score | BR30: Prioritarian | BS30: Maximin | BT30: Utilitarian | BU30: Adjusted score | BV30: Prioritarian | BW30: Maximin | BX30: Utilitarian | BY30: Adjusted score | BZ30: Prioritarian | CA30: Maximin | CB30: Isoelsatic p = 1.26 | CC30: Isoelastic normalised | CD30: Isoelsatic p = 1 | CE30: Isoelsatic p = 1.26 | CF30: Isoelastic p = 1.26 normalised | CG30: Isoelsatic p = 1
A31: Overall | B31: 2078 | C31: 54 | D31: =Parameters!$B$4 -> 27012.44 | E31: =Parameters!$B$5 -> 20778.68 | F31: =Parameters!$B$8 -> 1.01088 | G31: =D31*POWER(F31,C31) -> 48455.429 | H31: =E31*POWER(F31,C31) -> 37273.192 | I31: =Parameters!$B$3*Parameters!B42 -> 557660.4 | J31: =I31*Parameters!$B$10 -> 234217.37 | K31: =I31*Parameters!$B$9 -> 323443.03 | L31: =J31*G31 -> 1.1349103e+10 | M31: =K31*H31 -> 1.2055754e+10 | N31: =M31+L31 -> 2.3404857e+10 | O31: =Parameters!B42 -> 2239600 | P31: =O31*Parameters!$B$10 -> 940632 | Q31: =O31*Parameters!$B$9 -> 1298968 | R31: =P31*G31 -> 4.5578727e+10 | S31: =Q31*H31 -> 4.8416683e+10 | T31: =S31+R31 -> 9.399541e+10 | W31: =SUM(W32:W41) -> 9.399541e+10 | Z31: =SUM(Z32:Z41) -> 9.399541e+10 | AA31: =Parameters!C42*Parameters!B2 -> 3564796.4 | AB31: =AA31+I31 -> 4122456.8 | AC31: =SUM(AC32:AC41) -> 3.4871304e+11 | AD31: =N31 -> 2.3404857e+10 | AE31: =AC31+AD31-W31 -> 2.7812249e+11 | AF31: =AC31-W31 -> 2.5471763e+11 | AG31: =AC31+AD31-Z31 -> 2.7812249e+11 | AH31: =AC31-Z31 -> 2.5471763e+11 | AP31: Sensitivity check | AQ31: Sensitivity check | AT31: Sensitivity check | AU31: Sensitivity check | AV31: =SUM(AO32:AO41) -> 180.42437 | AW31: Prioritarian | AX31: =SUM(AW32:AW41) -> 19.013336 | AY31: =MIN(AN33:AN41) -> 3.5595506 | AZ31: =SUM(AQ32:AQ41) -> 47.283746 | BB31: =SUM(BA32:BA41) -> 21.732645 | BC31: =MIN(AQ33:AQ41) -> 4.3374828 | BD31: =SUM(AS32:AS41) -> 176.65527 | BF31: =SUM(BE32:BE41) -> 19.022525 | BG31: =MIN(AR33:AR41) -> 3.5675146 | BH31: =SUM(AU32:AU41) -> 47.493778 | BJ31: =SUM(BI31:BI41) -> 21.782791 | BK31: =MIN(AU33:AU41) -> 4.384555 | BL31: =SUM(CB32:CB41) -> 35.892667 | BN31: =SUM(BM32:BM41) -> 18.943815 | BO31: =MIN(CB33:CB41) -> 3.5148824 | BP31: =SUM(CD32:CD41) -> 46.02154 | BR31: =SUM(BQ32:BQ41) -> 21.41923 | BS31: =MIN(CD33:CD41) -> 4.0955487 | BT31: =SUM(CE32:CE41) -> 35.969942 | BV31: =SUM(BU32:BU41) -> 18.964541 | BW31: =MIN(CE33:CE41) -> 3.5302079 | BX31: =SUM(CG32:CG41) -> 46.391121 | BZ31: =SUM(BY31:BY41) -> 21.511413 | CA31: =MIN(CG33:CG41) -> 4.1746688 | CB31: =Parameters!AO32 -> 0
A32: 1 | U32: =Parameters!C15 -> 0.0036096394 | V32: =(U32*$T$31)/(Parameters!B15*POWER(Parameters!$B$8,$C$31)) -> 0.23699246 | W32: =$T$31*U32 -> 3.3928953e+08 | X32: =Parameters!D15 -> 0 | Y32: =(X32*$T$31)/(Parameters!B15*POWER(Parameters!$B$8,$C$31)) -> 0 | Z32: =$T$31*X32 -> 0 | AC32: =Parameters!B15*POWER(Parameters!$B$8,$C$31) -> 1.431647e+09 | AD32: =$AD$31*Parameters!E15 -> 4.2554286e+09 | AE32: =AC32+AD32-W32 -> 5.347786e+09 | AF32: =AC32-W32 -> 1.0923574e+09 | AG32: =AC32+AD32-Z32 -> 5.6870756e+09 | AH32: =AC32-Z32 -> 1.431647e+09 | AI32: =($AA$31+$I$31)/10 -> 412245.68 | AJ32: =AE32/AI32 -> 12972.328 | AK32: =AF32/AI32 -> 2649.7729 | AL32: =AG32/AI32 -> 13795.355 | AM32: =AH32/AI32 -> 3472.8004 | AN32: =(POWER(AJ32, -0.26) - 1)/-0.26 -> 3.5183289 | AO32: =(AN32-$AN$18)*100 -> 8.3541622 | AP32: =(POWER(AJ32, -1) - 1)/-1 -> 0.99992291 | AQ32: =LOG(AJ32) -> 4.1130179 | AR32: =(POWER(AL32, -0.26) - 1)/-0.26 -> 3.5235303 | AS32: =(AR32-$AR$18)*100 -> 8.1498793 | AT32: =(POWER(AL32, -1) - 1)/-1 -> 0.99992751 | AU32: =LOG(AL32) -> 4.1397329 | AW32: {=SQRT(AN32:AN41)} -> 1.8757209 | BA32: =SQRT(AQ32) -> 2.0280577 | BE32: {=SQRT(AR32:AR41)} -> 1.8771069 | BI32: =SQRT(AU32) -> 2.0346334 | BM32: =SQRT(CB32) -> 1.8304951 | BQ32: =SQRT(CD32) -> 1.8501915 | BU32: =SQRT(CE32) -> 1.8396625 | BY32: =SQRT(CG32) -> 1.8816694 | CB32: =(POWER(AK32, -0.26) - 1)/-0.26 -> 3.3507123 | CC32: =(CB32-$CB$4)*100 -> 0.84435218 | CD32: =LOG(AK32) -> 3.4232087 | CE32: =(POWER(AM32, -0.26) - 1)/-0.26 -> 3.3843581 | CF32: =(CE32-$CE$4)*100 -> 2.8665253 | CG32: =LOG(AM32) -> 3.5406798
A33: 2 | U33: =Parameters!C16 -> 0.014401036 | V33: =(U33*$T$31)/(Parameters!B16*POWER(Parameters!$B$8,$C$31)) -> 0.20855336 | W33: =$T$31*U33 -> 1.3536313e+09 | X33: =Parameters!D16 -> 0.0034800777 | Y33: =(X33*$T$31)/(Parameters!B16*POWER(Parameters!$B$8,$C$31)) -> 0.050397895 | Z33: =$T$31*X33 -> 3.2711134e+08 | AC33: =Parameters!B16*POWER(Parameters!$B$8,$C$31) -> 6.4905754e+09 | AD33: =$AD$31*Parameters!E16 -> 3.8298857e+09 | AE33: =AC33+AD33-W33 -> 8.9668298e+09 | AF33: =AC33-W33 -> 5.1369441e+09 | AG33: =AC33+AD33-Z33 -> 9.9933498e+09 | AH33: =AC33-Z33 -> 6.1634641e+09 | AI33: =($AA$31+$I$31)/10 -> 412245.68 | AJ33: =AE33/AI33 -> 21751.18 | AK33: =AF33/AI33 -> 12460.88 | AL33: =AG33/AI33 -> 24241.248 | AM33: =AH33/AI33 -> 14950.949 | AN33: =(POWER(AJ33, -0.26) - 1)/-0.26 -> 3.5595506 | AO33: =(AN33-$AN$18)*100 -> 12.476331 | AP33: =(POWER(AJ33, -1) - 1)/-1 -> 0.99995403 | AQ33: =LOG(AJ33) -> 4.3374828 | AR33: =(POWER(AL33, -0.26) - 1)/-0.26 -> 3.5675146 | AS33: =(AR33-$AR$18)*100 -> 12.548308 | AT33: =(POWER(AL33, -1) - 1)/-1 -> 0.99995875 | AU33: =LOG(AL33) -> 4.384555 | AW33: 1.8866771 | BA33: =SQRT(AQ33) -> 2.0826624 | BE33: 1.8887865 | BI33: =SQRT(AU33) -> 2.0939329 | BM33: =SQRT(CB33) -> 1.874802 | BQ33: =SQRT(CD33) -> 2.0237462 | BU33: =SQRT(CE33) -> 1.8788848 | BY33: =SQRT(CG33) -> 2.0432006 | CB33: =(POWER(AK33, -0.26) - 1)/-0.26 -> 3.5148824 | CC33: =(CB33-$CB$4)*100 -> 17.261361 | CD33: =LOG(AK33) -> 4.0955487 | CE33: =(POWER(AM33, -0.26) - 1)/-0.26 -> 3.5302079 | CF33: =(CE33-$CE$4)*100 -> 17.451503 | CG33: =LOG(AM33) -> 4.1746688
A34: 3 | U34: =Parameters!C17 -> 0.031399077 | V34: =(U34*$T$31)/(Parameters!B17*POWER(Parameters!$B$8,$C$31)) -> 0.21803306 | W34: =$T$31*U34 -> 2.9513692e+09 | X34: =Parameters!D17 -> 0.010886748 | Y34: =(X34*$T$31)/(Parameters!B17*POWER(Parameters!$B$8,$C$31)) -> 0.075596842 | Z34: =$T$31*X34 -> 1.0233044e+09 | AC34: =Parameters!B17*POWER(Parameters!$B$8,$C$31) -> 1.3536338e+10 | AD34: =$AD$31*Parameters!E17 -> 3.4043429e+09 | AE34: =AC34+AD34-W34 -> 1.3989312e+10 | AF34: =AC34-W34 -> 1.0584969e+10 | AG34: =AC34+AD34-Z34 -> 1.5917376e+10 | AH34: =AC34-Z34 -> 1.2513033e+10 | AI34: =($AA$31+$I$31)/10 -> 412245.68 | AJ34: =AE34/AI34 -> 33934.404 | AK34: =AF34/AI34 -> 25676.36 | AL34: =AG34/AI34 -> 38611.384 | AM34: =AH34/AI34 -> 30353.34 | AN34: =(POWER(AJ34, -0.26) - 1)/-0.26 -> 3.5908483 | AO34: =(AN34-$AN$18)*100 -> 15.606105 | AP34: =(POWER(AJ34, -1) - 1)/-1 -> 0.99997053 | AQ34: =LOG(AJ34) -> 4.5306402 | AR34: =(POWER(AL34, -0.26) - 1)/-0.26 -> 3.5992768 | AS34: =(AR34-$AR$18)*100 -> 15.724536 | AT34: =(POWER(AL34, -1) - 1)/-1 -> 0.9999741 | AU34: =LOG(AL34) -> 4.5867154 | AW34: 1.8949534 | BA34: =SQRT(AQ34) -> 2.1285301 | BE34: 1.897176 | BI34: =SQRT(AU34) -> 2.1416618 | BM34: =SQRT(CB34) -> 1.889881 | BQ34: =SQRT(CD34) -> 2.0998889 | BU34: =SQRT(CE34) -> 1.8929705 | BY34: =SQRT(CG34) -> 2.1171222 | CB34: =(POWER(AK34, -0.26) - 1)/-0.26 -> 3.5716503 | CC34: =(CB34-$CB$4)*100 -> 22.93815 | CD34: =LOG(AK34) -> 4.4095335 | CE34: =(POWER(AM34, -0.26) - 1)/-0.26 -> 3.5833371 | CF34: =(CE34-$CE$4)*100 -> 22.764426 | CG34: =LOG(AM34) -> 4.4822065
A35: 4 | U35: =Parameters!C18 -> 0.051692243 | V35: =(U35*$T$31)/(Parameters!B18*POWER(Parameters!$B$8,$C$31)) -> 0.22751276 | W35: =$T$31*U35 -> 4.8588336e+09 | X35: =Parameters!D18 -> 0.022901399 | Y35: =(X35*$T$31)/(Parameters!B18*POWER(Parameters!$B$8,$C$31)) -> 0.10079579 | Z35: =$T$31*X35 -> 2.1526264e+09 | AC35: =Parameters!B18*POWER(Parameters!$B$8,$C$31) -> 2.1356313e+10 | AD35: =$AD$31*Parameters!E18 -> 2.9788e+09 | AE35: =AC35+AD35-W35 -> 1.9476279e+10 | AF35: =AC35-W35 -> 1.6497479e+10 | AG35: =AC35+AD35-Z35 -> 2.2182486e+10 | AH35: =AC35-Z35 -> 1.9203686e+10 | AI35: =($AA$31+$I$31)/10 -> 412245.68 | AJ35: =AE35/AI35 -> 47244.349 | AK35: =AF35/AI35 -> 40018.561 | AL35: =AG35/AI35 -> 53808.899 | AM35: =AH35/AI35 -> 46583.111 | AN35: =(POWER(AJ35, -0.26) - 1)/-0.26 -> 3.6118952 | AO35: =(AN35-$AN$18)*100 -> 17.710789 | AP35: =(POWER(AJ35, -1) - 1)/-1 -> 0.99997883 | AQ35: =LOG(AJ35) -> 4.6743499 | AR35: =(POWER(AL35, -0.26) - 1)/-0.26 -> 3.619687 | AS35: =(AR35-$AR$18)*100 -> 17.765555 | AT35: =(POWER(AL35, -1) - 1)/-1 -> 0.99998142 | AU35: =LOG(AL35) -> 4.7308541 | AW35: 1.9004987 | BA35: =SQRT(AQ35) -> 2.1620245 | BE35: 1.9025475 | BI35: =SQRT(AU35) -> 2.1750527 | BM35: =SQRT(CB35) -> 1.8977787 | BQ35: =SQRT(CD35) -> 2.1452882 | BU35: =SQRT(CE35) -> 1.9002724 | BY35: =SQRT(CG35) -> 2.1606084 | CB35: =(POWER(AK35, -0.26) - 1)/-0.26 -> 3.6015639 | CC35: =(CB35-$CB$4)*100 -> 25.929506 | CD35: =LOG(AK35) -> 4.6022615 | CE35: =(POWER(AM35, -0.26) - 1)/-0.26 -> 3.6110351 | CF35: =(CE35-$CE$4)*100 -> 25.534223 | CG35: =LOG(AM35) -> 4.6682285
A36: 5 | U36: =Parameters!C19 -> 0.070583126 | V36: =(U36*$T$31)/(Parameters!B19*POWER(Parameters!$B$8,$C$31)) -> 0.23699246 | W36: =$T$31*U36 -> 6.6344899e+09 | X36: =Parameters!D19 -> 0.037524833 | Y36: =(X36*$T$31)/(Parameters!B19*POWER(Parameters!$B$8,$C$31)) -> 0.12599474 | Z36: =$T$31*X36 -> 3.5271621e+09 | AC36: =Parameters!B19*POWER(Parameters!$B$8,$C$31) -> 2.7994519e+10 | AD36: =$AD$31*Parameters!E19 -> 2.5532571e+09 | AE36: =AC36+AD36-W36 -> 2.3913286e+10 | AF36: =AC36-W36 -> 2.1360029e+10 | AG36: =AC36+AD36-Z36 -> 2.7020614e+10 | AH36: =AC36-Z36 -> 2.4467357e+10 | AI36: =($AA$31+$I$31)/10 -> 412245.68 | AJ36: =AE36/AI36 -> 58007.367 | AK36: =AF36/AI36 -> 51813.834 | AL36: =AG36/AI36 -> 65544.93 | AM36: =AH36/AI36 -> 59351.397 | AN36: =(POWER(AJ36, -0.26) - 1)/-0.26 -> 3.6240679 | AO36: =(AN36-$AN$18)*100 -> 18.928064 | AP36: =(POWER(AJ36, -1) - 1)/-1 -> 0.99998276 | AQ36: =LOG(AJ36) -> 4.7634832 | AR36: =(POWER(AL36, -0.26) - 1)/-0.26 -> 3.6310112 | AS36: =(AR36-$AR$18)*100 -> 18.897973 | AT36: =(POWER(AL36, -1) - 1)/-1 -> 0.99998474 | AU36: =LOG(AL36) -> 4.8165391 | AW36: 1.9036985 | BA36: =SQRT(AQ36) -> 2.1825405 | BE36: 1.9055212 | BI36: =SQRT(AU36) -> 2.1946615 | BM36: =SQRT(CB36) -> 1.9019599 | BQ36: =SQRT(CD36) -> 2.1712774 | BU36: =SQRT(CE36) -> 1.9040448 | BY36: =SQRT(CG36) -> 2.1848183 | CB36: =(POWER(AK36, -0.26) - 1)/-0.26 -> 3.6174514 | CC36: =(CB36-$CB$4)*100 -> 27.518262 | CD36: =LOG(AK36) -> 4.7144457 | CE36: =(POWER(AM36, -0.26) - 1)/-0.26 -> 3.6253866 | CF36: =(CE36-$CE$4)*100 -> 26.969374 | CG36: =LOG(AM36) -> 4.7734309
